Workbook

Sheet Dashboard
A1: VODAFONE–VOIS INTELLIGENT AI ASSISTANT
A2: Executive Project Dashboard · Enterprise GenAI · RAG · MCP on Microsoft Azure AI Foundry
A3: ="Status as at "&TEXT(StatusDate,"dd mmm yyyy")&" · Week "&(INT((StatusDate-ProjectStart)/7)+1)&" of 20 · PM: Ananya Rao · Sponsor: Rajesh Menon" -> Status as at 15 Jan 2027 · Week 13 of 20 · PM: Ananya Rao · Sponsor: Rajesh Menon
A5: OVERALL PROGRESS | E5: SCHEDULE PERFORMANCE (SPI) | I5: COST PERFORMANCE (CPI) | M5: BUDGET AT COMPLETION | Q5: MILESTONES ACHIEVED | U5: OVERALL RAG
A6: ='WBS Schedule'!K7 -> 0.53424242 | E6: =IF('WBS Schedule'!Q7=0,1,'WBS Schedule'!R7/'WBS Schedule'!Q7) -> 0.94278075 | I6: =IF('WBS Schedule'!S7=0,1,'WBS Schedule'!R7/'WBS Schedule'!S7) -> 0.96240191 | M6: ='WBS Schedule'!P7 -> 105.6 | Q6: =COUNT(Milestones!F5:F9)&" / 5" -> 2 / 5 | U6: =IF(OR(IF('WBS Schedule'!Q7=0,1,'WBS Schedule'!R7/'WBS Schedule'!Q7)<0.9,IF('WBS Schedule'!S7=0,1,'WBS Schedule'!R7/'WBS Schedule'!S7)<0.9),"RED",IF(OR(IF('WBS Schedule'!Q7=0,1,'WBS Schedule'!R7/'WBS Schedule'!Q7)<0.97,IF('WBS Schedule'!S7=0,1,'WBS Schedule'!R7/'WBS Schedule'!S7)<0.97),"AMBER","GREEN")) -> AMBER
A7: ="Planned: "&TEXT('WBS Schedule'!J7,"0%") -> Planned: 57% | E7: =IF(IF('WBS Schedule'!Q7=0,1,'WBS Schedule'!R7/'WBS Schedule'!Q7)>=0.97,"On schedule",IF(IF('WBS Schedule'!Q7=0,1,'WBS Schedule'!R7/'WBS Schedule'!Q7)>=0.9,"Slightly behind","Behind schedule")) -> Slightly behind | I7: =IF(IF('WBS Schedule'!S7=0,1,'WBS Schedule'!R7/'WBS Schedule'!S7)>=0.97,"Within budget",IF(IF('WBS Schedule'!S7=0,1,'WBS Schedule'!R7/'WBS Schedule'!S7)>=0.9,"Minor overrun","Over budget")) -> Minor overrun | M7: ="EAC: ₹"&TEXT('WBS Schedule'!P7/IF('WBS Schedule'!S7=0,1,'WBS Schedule'!R7/'WBS Schedule'!S7),"#,##0.0")&" L" -> EAC: ₹109.7 L | Q7: ="Next: "&INDEX(Milestones!B5:B9,MATCH("",Milestones!F5:F9&"",0)) -> Next: Application integrations | U7: Based on SPI & CPI thresholds
A9: FORECAST FINISH | E9: WORKING DAYS ELAPSED | I9: ACTIVITIES COMPLETE | M9: BEHIND / OVERDUE | Q9: OPEN HIGH RISKS | U9: COST VARIANCE (CV)
A10: =Milestones!E9 -> 46458 | E10: =NETWORKDAYS(ProjectStart,StatusDate,Holidays) -> 61 | I10: =COUNTIFS('WBS Schedule'!$B$7:$B$68,2,'WBS Schedule'!$G$7:$G$68,">0",'WBS Schedule'!$M$7:$M$68,"Complete") -> 27 | M10: =COUNTIFS('WBS Schedule'!$B$7:$B$68,2,'WBS Schedule'!$M$7:$M$68,"Behind")+COUNTIFS('WBS Schedule'!$B$7:$B$68,2,'WBS Schedule'!$M$7:$M$68,"Overdue") -> 5 | Q10: ='Chart Data'!B46 -> 2 | U10: ='WBS Schedule'!R7-'WBS Schedule'!S7 -> -2.204
A11: ="Baseline: "&TEXT(Milestones!D9,"dd-mmm-yy") -> Baseline: 12-Mar-27 | E11: ="of "&'WBS Schedule'!G7&" total · "&TEXT(NETWORKDAYS(ProjectStart,StatusDate,Holidays)/'WBS Schedule'!G7,"0%") -> of 100 total · 61% | I11: ="of "&COUNTIFS('WBS Schedule'!$B$7:$B$68,2,'WBS Schedule'!$G$7:$G$68,">0")&" activities" -> of 51 activities | M11: Activities needing attention | Q11: ="of "&COUNTIFS('RAID Log'!B5:B22,"Risk",'RAID Log'!K5:K22,"<>Closed")&" active risks" -> of 10 active risks | U11: ="EV ₹"&TEXT('WBS Schedule'!R7,"0.0")&" L vs AC ₹"&TEXT('WBS Schedule'!S7,"0.0")&" L" -> EV ₹56.4 L vs AC ₹58.6 L
A13: KEY HIGHLIGHTS | M13: ISSUES, RISKS & ACTIONS
A14: ✔ M1 Architecture approved and M2 AI Assistant MVP delivered | M14: ✖ Oracle sandbox access delayed ~2 weeks — M3 re-forecast; escalated to sponsor
A15: ✔ Foundry IQ retrieval at 88% recall@5 on a 250-question benchmark (target 85%) | M15: ✖ SAP connector effort over estimate — CPI below 1.0; recovery plan in Month 4
A16: ✔ SAP and QA/testing connectors running end-to-end in non-production | M16: ! GPT-5 TPM quota limits load tests — increase requested with Microsoft
A17: ✔ P95 response time 6.4 s at 50 concurrent users (target ≤ 8 s) | M17: ! Groundedness 87% vs 90% target — prompt & citation tuning in sprint S7
A18: ► Next 2 weeks: Entra ID RBAC, authorization rules, AI evaluation sprint | M18: ► Decision needed: approve 1-week M3 slip or descope Oracle write-back demo
A20: 1 · EARNED VALUE — PV vs EV vs AC | M20: 2 · PERFORMANCE INDICES TREND
A40: 3 · PHASE TIMELINE | M40: 4 · PHASE PROGRESS
A60: 5 · COST PERFORMANCE | M60: 6 · ACTIVITY STATUS
A80: 7 · RESOURCE LOADING | M80: 8 · BURNDOWN
A100: 9 · AI QUALITY KPIs | M100: 10 · RAID SUMMARY
A120: 11 · RISK EXPOSURE | M120: 12 · RISK RATING MIX
A140: 13 · RISK HEAT MAP (count of active risks) | M140: 14 · MILESTONE TRACKER
A141: Probability ↓ / Impact → | C141: 1 | E141: 2 | G141: 3 | I141: 4 | K141: 5 | M141: ID | N141: Milestone | R141: Baseline | T141: Forecast | V141: Status | X141: Var (d)
A142: 5 | C142: =COUNTIFS('RAID Log'!$B$5:$B$22,"Risk",'RAID Log'!$E$5:$E$22,5,'RAID Log'!$F$5:$F$22,1,'RAID Log'!$K$5:$K$22,"<>Closed") -> 0 | E142: =COUNTIFS('RAID Log'!$B$5:$B$22,"Risk",'RAID Log'!$E$5:$E$22,5,'RAID Log'!$F$5:$F$22,2,'RAID Log'!$K$5:$K$22,"<>Closed") -> 0 | G142: =COUNTIFS('RAID Log'!$B$5:$B$22,"Risk",'RAID Log'!$E$5:$E$22,5,'RAID Log'!$F$5:$F$22,3,'RAID Log'!$K$5:$K$22,"<>Closed") -> 0 | I142: =COUNTIFS('RAID Log'!$B$5:$B$22,"Risk",'RAID Log'!$E$5:$E$22,5,'RAID Log'!$F$5:$F$22,4,'RAID Log'!$K$5:$K$22,"<>Closed") -> 0 | K142: =COUNTIFS('RAID Log'!$B$5:$B$22,"Risk",'RAID Log'!$E$5:$E$22,5,'RAID Log'!$F$5:$F$22,5,'RAID Log'!$K$5:$K$22,"<>Closed") -> 0 | M142: =Milestones!A5 -> M1 | N142: =Milestones!B5 -> Architecture approved | R142: =Milestones!D5 -> 46342 | T142: =IF(Milestones!F5<>"",Milestones!F5,Milestones!E5) -> 46342 | V142: =Milestones!H5 -> Achieved | X142: =Milestones!G5 -> 0
A143: 4 | C143: =COUNTIFS('RAID Log'!$B$5:$B$22,"Risk",'RAID Log'!$E$5:$E$22,4,'RAID Log'!$F$5:$F$22,1,'RAID Log'!$K$5:$K$22,"<>Closed") -> 0 | E143: =COUNTIFS('RAID Log'!$B$5:$B$22,"Risk",'RAID Log'!$E$5:$E$22,4,'RAID Log'!$F$5:$F$22,2,'RAID Log'!$K$5:$K$22,"<>Closed") -> 0 | G143: =COUNTIFS('RAID Log'!$B$5:$B$22,"Risk",'RAID Log'!$E$5:$E$22,4,'RAID Log'!$F$5:$F$22,3,'RAID Log'!$K$5:$K$22,"<>Closed") -> 1 | I143: =COUNTIFS('RAID Log'!$B$5:$B$22,"Risk",'RAID Log'!$E$5:$E$22,4,'RAID Log'!$F$5:$F$22,4,'RAID Log'!$K$5:$K$22,"<>Closed") -> 0 | K143: =COUNTIFS('RAID Log'!$B$5:$B$22,"Risk",'RAID Log'!$E$5:$E$22,4,'RAID Log'!$F$5:$F$22,5,'RAID Log'!$K$5:$K$22,"<>Closed") -> 1 | M143: =Milestones!A6 -> M2 | N143: =Milestones!B6 -> AI assistant MVP | R143: =Milestones!D6 -> 46371 | T143: =IF(Milestones!F6<>"",Milestones!F6,Milestones!E6) -> 46370 | V143: =Milestones!H6 -> Achieved | X143: =Milestones!G6 -> -1
A144: 3 | C144: =COUNTIFS('RAID Log'!$B$5:$B$22,"Risk",'RAID Log'!$E$5:$E$22,3,'RAID Log'!$F$5:$F$22,1,'RAID Log'!$K$5:$K$22,"<>Closed") -> 0 | E144: =COUNTIFS('RAID Log'!$B$5:$B$22,"Risk",'RAID Log'!$E$5:$E$22,3,'RAID Log'!$F$5:$F$22,2,'RAID Log'!$K$5:$K$22,"<>Closed") -> 0 | G144: =COUNTIFS('RAID Log'!$B$5:$B$22,"Risk",'RAID Log'!$E$5:$E$22,3,'RAID Log'!$F$5:$F$22,3,'RAID Log'!$K$5:$K$22,"<>Closed") -> 0 | I144: =COUNTIFS('RAID Log'!$B$5:$B$22,"Risk",'RAID Log'!$E$5:$E$22,3,'RAID Log'!$F$5:$F$22,4,'RAID Log'!$K$5:$K$22,"<>Closed") -> 3 | K144: =COUNTIFS('RAID Log'!$B$5:$B$22,"Risk",'RAID Log'!$E$5:$E$22,3,'RAID Log'!$F$5:$F$22,5,'RAID Log'!$K$5:$K$22,"<>Closed") -> 1 | M144: =Milestones!A7 -> M3 | N144: =Milestones!B7 -> Application integrations | R144: =Milestones!D7 -> 46401 | T144: =IF(Milestones!F7<>"",Milestones!F7,Milestones!E7) -> 46409 | V144: =Milestones!H7 -> At Risk | X144: =Milestones!G7 -> 6
A145: 2 | C145: =COUNTIFS('RAID Log'!$B$5:$B$22,"Risk",'RAID Log'!$E$5:$E$22,2,'RAID Log'!$F$5:$F$22,1,'RAID Log'!$K$5:$K$22,"<>Closed") -> 0 | E145: =COUNTIFS('RAID Log'!$B$5:$B$22,"Risk",'RAID Log'!$E$5:$E$22,2,'RAID Log'!$F$5:$F$22,2,'RAID Log'!$K$5:$K$22,"<>Closed") -> 0 | G145: =COUNTIFS('RAID Log'!$B$5:$B$22,"Risk",'RAID Log'!$E$5:$E$22,2,'RAID Log'!$F$5:$F$22,3,'RAID Log'!$K$5:$K$22,"<>Closed") -> 2 | I145: =COUNTIFS('RAID Log'!$B$5:$B$22,"Risk",'RAID Log'!$E$5:$E$22,2,'RAID Log'!$F$5:$F$22,4,'RAID Log'!$K$5:$K$22,"<>Closed") -> 1 | K145: =COUNTIFS('RAID Log'!$B$5:$B$22,"Risk",'RAID Log'!$E$5:$E$22,2,'RAID Log'!$F$5:$F$22,5,'RAID Log'!$K$5:$K$22,"<>Closed") -> 1 | M145: =Milestones!A8 -> M4 | N145: =Milestones!B8 -> Release candidate | R145: =Milestones!D8 -> 46430 | T145: =IF(Milestones!F8<>"",Milestones!F8,Milestones!E8) -> 46434 | V145: =Milestones!H8 -> At Risk | X145: =Milestones!G8 -> 2
A146: 1 | C146: =COUNTIFS('RAID Log'!$B$5:$B$22,"Risk",'RAID Log'!$E$5:$E$22,1,'RAID Log'!$F$5:$F$22,1,'RAID Log'!$K$5:$K$22,"<>Closed") -> 0 | E146: =COUNTIFS('RAID Log'!$B$5:$B$22,"Risk",'RAID Log'!$E$5:$E$22,1,'RAID Log'!$F$5:$F$22,2,'RAID Log'!$K$5:$K$22,"<>Closed") -> 0 | G146: =COUNTIFS('RAID Log'!$B$5:$B$22,"Risk",'RAID Log'!$E$5:$E$22,1,'RAID Log'!$F$5:$F$22,3,'RAID Log'!$K$5:$K$22,"<>Closed") -> 0 | I146: =COUNTIFS('RAID Log'!$B$5:$B$22,"Risk",'RAID Log'!$E$5:$E$22,1,'RAID Log'!$F$5:$F$22,4,'RAID Log'!$K$5:$K$22,"<>Closed") -> 0 | K146: =COUNTIFS('RAID Log'!$B$5:$B$22,"Risk",'RAID Log'!$E$5:$E$22,1,'RAID Log'!$F$5:$F$22,5,'RAID Log'!$K$5:$K$22,"<>Closed") -> 0 | M146: =Milestones!A9 -> M5 | N146: =Milestones!B9 -> Pilot accepted | R146: =Milestones!D9 -> 46458 | T146: =IF(Milestones!F9<>"",Milestones!F9,Milestones!E9) -> 46458 | V146: =Milestones!H9 -> On Track | X146: =Milestones!G9 -> 0
A149: 15 · PHASE SUMMARY
A150: Phase | F150: Start | H150: Finish | J150: Budget ₹ L | L150: EV ₹ L | N150: AC ₹ L | P150: CPI | R150: Planned % | T150: Actual % | V150: Status
A151: M1 Discovery | F151: ='WBS Schedule'!H8 -> 46314 | H151: ='WBS Schedule'!I8 -> 46342 | J151: ='WBS Schedule'!P8 -> 16.96 | L151: ='WBS Schedule'!R8 -> 16.96 | N151: ='WBS Schedule'!S8 -> 16.26 | P151: =IF('WBS Schedule'!S8=0,1,'WBS Schedule'!R8/'WBS Schedule'!S8) -> 1.0430504 | R151: ='WBS Schedule'!J8 -> 1 | T151: ='WBS Schedule'!K8 -> 1 | V151: ='WBS Schedule'!M8 -> Complete
A152: M2 AI Foundation | F152: ='WBS Schedule'!H20 -> 46343 | H152: ='WBS Schedule'!I20 -> 46371 | J152: ='WBS Schedule'!P20 -> 17.28 | L152: ='WBS Schedule'!R20 -> 17.28 | N152: ='WBS Schedule'!S20 -> 17.9 | P152: =IF('WBS Schedule'!S20=0,1,'WBS Schedule'!R20/'WBS Schedule'!S20) -> 0.96536313 | R152: ='WBS Schedule'!J20 -> 1 | T152: ='WBS Schedule'!K20 -> 1 | V152: ='WBS Schedule'!M20 -> Complete
A153: M3 Integration | F153: ='WBS Schedule'!H32 -> 46372 | H153: ='WBS Schedule'!I32 -> 46401 | J153: ='WBS Schedule'!P32 -> 23.68 | L153: ='WBS Schedule'!R32 -> 20 | N153: ='WBS Schedule'!S32 -> 22.28 | P153: =IF('WBS Schedule'!S32=0,1,'WBS Schedule'!R32/'WBS Schedule'!S32) -> 0.89766607 | R153: ='WBS Schedule'!J32 -> 1 | T153: ='WBS Schedule'!K32 -> 0.84459459 | V153: ='WBS Schedule'!M32 -> Overdue
A154: M4 Security & QA | F154: ='WBS Schedule'!H44 -> 46402 | H154: ='WBS Schedule'!I44 -> 46430 | J154: ='WBS Schedule'!P44 -> 23.68 | L154: ='WBS Schedule'!R44 -> 2.176 | N154: ='WBS Schedule'!S44 -> 2.18 | P154: =IF('WBS Schedule'!S44=0,1,'WBS Schedule'!R44/'WBS Schedule'!S44) -> 0.99816514 | R154: ='WBS Schedule'!J44 -> 0.081081081 | T154: ='WBS Schedule'!K44 -> 0.091891892 | V154: ='WBS Schedule'!M44 -> In Progress
A155: M5 Pilot & Handover | F155: ='WBS Schedule'!H56 -> 46433 | H155: ='WBS Schedule'!I56 -> 46458 | J155: ='WBS Schedule'!P56 -> 24 | L155: ='WBS Schedule'!R56 -> 0 | N155: ='WBS Schedule'!S56 -> 0 | P155: =IF('WBS Schedule'!S56=0,1,'WBS Schedule'!R56/'WBS Schedule'!S56) -> 1 | R155: ='WBS Schedule'!J56 -> 0 | T155: ='WBS Schedule'!K56 -> 0 | V155: ='WBS Schedule'!M56 -> Not Started
A156: Total project | F156: ='WBS Schedule'!H7 -> 46314 | H156: ='WBS Schedule'!I7 -> 46458 | J156: ='WBS Schedule'!P7 -> 105.6 | L156: ='WBS Schedule'!R7 -> 56.416 | N156: ='WBS Schedule'!S7 -> 58.62 | P156: =IF('WBS Schedule'!S7=0,1,'WBS Schedule'!R7/'WBS Schedule'!S7) -> 0.96240191 | R156: ='WBS Schedule'!J7 -> 0.56666667 | T156: ='WBS Schedule'!K7 -> 0.53424242 | V156: ='WBS Schedule'!M7 -> In Progress
A158: Demo data for illustration · Blue cells on other sheets are inputs · Change Status Date on 'Project Setup' to roll the dashboard forward

Sheet Project Setup
A1: Project Setup & Parameters
A2: Blue cells are inputs; every sheet calculates from these values
A4: Parameter | B4: Value | C4: Named range | D4: Notes
A5: Project name | B5: Vodafone–VOIS Intelligent AI Assistant
A6: Client / business unit | B6: Vodafone Intelligent Solutions (VOIS)
A7: Project code | B7: VOIS-GENAI-2026-014
A8: Project type | B8: Enterprise Generative AI · RAG · MCP integration
A9: Target platform | B9: Microsoft Azure AI Foundry (GPT-5, Foundry IQ)
A10: Azure region (demo) | B10: West Europe
A11: Delivery methodology | B11: Agile Scrum — 2-week sprints, monthly phase gates
A12: Executive sponsor | B12: Rajesh Menon — Head of Enterprise Applications
A13: Project manager | B13: Ananya Rao — PMP, PMI-ACP
A14: Product owner | B14: Vikram Desai — IT Service Excellence
A15: Project Start (Monday) | B15: 46314 | C15: ProjectStart | D15: Assumed kickoff date for the demo
A16: Status Date (data date) | B16: 46402 | C16: StatusDate | D16: Progress is reported as at this date (Week 13)
A17: Blended daily rate (₹ L / person-day) | B17: 0.32 | C17: BlendedRate | D17: Demo assumption — blended onshore/offshore rate
A18: Management reserve (% of BAC) | B18: 0.1 | C18: MgmtReserve
A19: Sprint length (calendar days) | B19: 14 | C19: SprintLen
A20: Currency / unit | B20: ₹ Lakh (1 L = ₹100,000)

Sheet WBS Schedule
A1: Vodafone–VOIS Intelligent AI Assistant — Work Breakdown Structure, Schedule & Earned Value
A2: Dates calculate from Project Start, predecessors and Holidays · Blue cells are inputs · Values in ₹ Lakh
A3: Project Start: | C3: =ProjectStart -> 46314 | D3: Status Date: | E3: =StatusDate -> 46402
A4: Gantt: black = project · grey = phase · red = activity in progress/planned · green = complete · ◆ = milestone · yellow column = status week | V4: Month 1 | Z4: Month 2 | AD4: Month 3 | AH4: Month 4 | AL4: Month 5 | AP4: +1
V5: W1 | W5: W2 | X5: W3 | Y5: W4 | Z5: W5 | AA5: W6 | AB5: W7 | AC5: W8 | AD5: W9 | AE5: W10 | AF5: W11 | AG5: W12 | AH5: W13 | AI5: W14 | AJ5: W15 | AK5: W16 | AL5: W17 | AM5: W18 | AN5: W19 | AO5: W20 | AP5: W21
A6: WBS ID | B6: Level | C6: Work Package / Activity | D6: Deliverable | E6: Responsible | F6: Predecessors | G6: Duration (work days) | H6: Start | I6: Finish | J6: Planned % | K6: Actual % | L6: Variance | M6: Status | N6: FTE | O6: Effort (person-days) | P6: Budget (BAC ₹ L) | Q6: Planned Value (PV ₹ L) | R6: Earned Value (EV ₹ L) | S6: Actual Cost (AC ₹ L) | T6: Sprint | U6: Notes / Exit Criteria | V6: =ProjectStart-WEEKDAY(ProjectStart,3)+0 -> 46314 | W6: =ProjectStart-WEEKDAY(ProjectStart,3)+7 -> 46321 | X6: =ProjectStart-WEEKDAY(ProjectStart,3)+14 -> 46328 | Y6: =ProjectStart-WEEKDAY(ProjectStart,3)+21 -> 46335 | Z6: =ProjectStart-WEEKDAY(ProjectStart,3)+28 -> 46342 | AA6: =ProjectStart-WEEKDAY(ProjectStart,3)+35 -> 46349 | AB6: =ProjectStart-WEEKDAY(ProjectStart,3)+42 -> 46356 | AC6: =ProjectStart-WEEKDAY(ProjectStart,3)+49 -> 46363 | AD6: =ProjectStart-WEEKDAY(ProjectStart,3)+56 -> 46370 | AE6: =ProjectStart-WEEKDAY(ProjectStart,3)+63 -> 46377 | AF6: =ProjectStart-WEEKDAY(ProjectStart,3)+70 -> 46384 | AG6: =ProjectStart-WEEKDAY(ProjectStart,3)+77 -> 46391 | AH6: =ProjectStart-WEEKDAY(ProjectStart,3)+84 -> 46398 | AI6: =ProjectStart-WEEKDAY(ProjectStart,3)+91 -> 46405 | AJ6: =ProjectStart-WEEKDAY(ProjectStart,3)+98 -> 46412 | AK6: =ProjectStart-WEEKDAY(ProjectStart,3)+105 -> 46419 | AL6: =ProjectStart-WEEKDAY(ProjectStart,3)+112 -> 46426 | AM6: =ProjectStart-WEEKDAY(ProjectStart,3)+119 -> 46433 | AN6: =ProjectStart-WEEKDAY(ProjectStart,3)+126 -> 46440 | AO6: =ProjectStart-WEEKDAY(ProjectStart,3)+133 -> 46447 | AP6: =ProjectStart-WEEKDAY(ProjectStart,3)+140 -> 46454
A7: 0 | B7: 0 | C7: Vodafone–VOIS Intelligent AI Assistant (Pilot) | D7: Security-reviewed, deployment-ready pilot | E7: Project Manager / Product Owner | G7: =NETWORKDAYS(H7,I7,Holidays) -> 100 | H7: =MIN(H8:H68) -> 46314 | I7: =MAX(I8:I68) -> 46458 | J7: =IF(P7=0,0,Q7/P7) -> 0.56666667 | K7: =IF(P7=0,0,R7/P7) -> 0.53424242 | L7: =K7-J7 -> -0.032424242 | M7: =IF(K7>=1,"Complete",IF(StatusDate>I7,"Overdue",IF(K7>0,IF(K7<J7-0.1,"Behind","In Progress"),IF(StatusDate>H7,"Late Start","Not Started")))) -> In Progress | O7: =O8+O20+O32+O44+O56 -> 330 | P7: =P8+P20+P32+P44+P56 -> 105.6 | Q7: =Q8+Q20+Q32+Q44+Q56 -> 59.84 | R7: =R8+R20+R32+R44+R56 -> 56.416 | S7: =S8+S20+S32+S44+S56 -> 58.62 | U7: Full enterprise rollout across all SAP/Oracle/testing apps is a subsequent phase | V7: =IF(AND($H7<=V$6+6,$I7>=V$6),1,"") -> 1 | W7: =IF(AND($H7<=W$6+6,$I7>=W$6),1,"") -> 1 | X7: =IF(AND($H7<=X$6+6,$I7>=X$6),1,"") -> 1 | Y7: =IF(AND($H7<=Y$6+6,$I7>=Y$6),1,"") -> 1 | Z7: =IF(AND($H7<=Z$6+6,$I7>=Z$6),1,"") -> 1 | AA7: =IF(AND($H7<=AA$6+6,$I7>=AA$6),1,"") -> 1 | AB7: =IF(AND($H7<=AB$6+6,$I7>=AB$6),1,"") -> 1 | AC7: =IF(AND($H7<=AC$6+6,$I7>=AC$6),1,"") -> 1 | ... AP7: =IF(AND($H7<=AP$6+6,$I7>=AP$6),1,"") -> 1
A8: 1 | B8: 1 | C8: Month 1 — Discovery, Requirements & Architecture | D8: Milestone M1: Architecture approved | E8: Project Manager | G8: =NETWORKDAYS(H8,I8,Holidays) -> 20 | H8: =MIN(H9:H19) -> 46314 | I8: =MAX(I9:I19) -> 46342 | J8: =IF(P8=0,0,Q8/P8) -> 1 | K8: =IF(P8=0,0,R8/P8) -> 1 | L8: =K8-J8 -> 0 | M8: =IF(K8>=1,"Complete",IF(StatusDate>I8,"Overdue",IF(K8>0,IF(K8<J8-0.1,"Behind","In Progress"),IF(StatusDate>H8,"Late Start","Not Started")))) -> Complete | N8: =MAX(N9:N19) -> 3 | O8: =SUM(O9:O19) -> 53 | P8: =SUM(P9:P19) -> 16.96 | Q8: =SUM(Q9:Q19) -> 16.96 | R8: =SUM(R9:R19) -> 16.96 | S8: =SUM(S9:S19) -> 16.26 | U8: Exit: Stakeholders approve the MVP scope, architecture, security approach, initial use cases and access requirements. | V8: =IF(AND($H8<=V$6+6,$I8>=V$6),1,"") -> 1 | W8: =IF(AND($H8<=W$6+6,$I8>=W$6),1,"") -> 1 | X8: =IF(AND($H8<=X$6+6,$I8>=X$6),1,"") -> 1 | Y8: =IF(AND($H8<=Y$6+6,$I8>=Y$6),1,"") -> 1 | Z8: =IF(AND($H8<=Z$6+6,$I8>=Z$6),1,"") -> 1 | AA8: =IF(AND($H8<=AA$6+6,$I8>=AA$6),1,"") | AB8: =IF(AND($H8<=AB$6+6,$I8>=AB$6),1,"") | AC8: =IF(AND($H8<=AC$6+6,$I8>=AC$6),1,"") | ... AP8: =IF(AND($H8<=AP$6+6,$I8>=AP$6),1,"")
A9: 1.1 | B9: 2 | C9: Project kickoff, objectives and stakeholder identification | D9: Project charter | E9: Project Manager | G9: 2 | H9: =WORKDAY(ProjectStart-1,1,Holidays) -> 46314 | I9: =WORKDAY(H9,G9-1,Holidays) -> 46315 | J9: =IF(StatusDate<H9,0,MIN(1,NETWORKDAYS(H9,StatusDate,Holidays)/G9)) -> 1 | K9: 1 | L9: =K9-J9 -> 0 | M9: =IF(K9>=1,"Complete",IF(StatusDate>I9,"Overdue",IF(K9>0,IF(K9<J9-0.1,"Behind","In Progress"),IF(StatusDate>H9,"Late Start","Not Started")))) -> Complete | N9: 3 | O9: =G9*N9 -> 6 | P9: =O9*BlendedRate -> 1.92 | Q9: =P9*J9 -> 1.92 | R9: =P9*K9 -> 1.92 | S9: 1.84 | T9: ="S"&(INT((H9-ProjectStart)/SprintLen)+1) -> S1 | V9: =IF(AND($H9<=V$6+6,$I9>=V$6),1,"") -> 1 | W9: =IF(AND($H9<=W$6+6,$I9>=W$6),1,"") | X9: =IF(AND($H9<=X$6+6,$I9>=X$6),1,"") | Y9: =IF(AND($H9<=Y$6+6,$I9>=Y$6),1,"") | Z9: =IF(AND($H9<=Z$6+6,$I9>=Z$6),1,"") | AA9: =IF(AND($H9<=AA$6+6,$I9>=AA$6),1,"") | AB9: =IF(AND($H9<=AB$6+6,$I9>=AB$6),1,"") | AC9: =IF(AND($H9<=AC$6+6,$I9>=AC$6),1,"") | ... AP9: =IF(AND($H9<=AP$6+6,$I9>=AP$6),1,"")
A10: 1.2 | B10: 2 | C10: Identify user personas: employees, QA, IT support, business users | D10: Persona catalogue | E10: Product Owner | F10: 1.1 | G10: 2 | H10: =WORKDAY(MAX($I$9),1,Holidays) -> 46316 | I10: =WORKDAY(H10,G10-1,Holidays) -> 46317 | J10: =IF(StatusDate<H10,0,MIN(1,NETWORKDAYS(H10,StatusDate,Holidays)/G10)) -> 1 | K10: 1 | L10: =K10-J10 -> 0 | M10: =IF(K10>=1,"Complete",IF(StatusDate>I10,"Overdue",IF(K10>0,IF(K10<J10-0.1,"Behind","In Progress"),IF(StatusDate>H10,"Late Start","Not Started")))) -> Complete | N10: 2 | O10: =G10*N10 -> 4 | P10: =O10*BlendedRate -> 1.28 | Q10: =P10*J10 -> 1.28 | R10: =P10*K10 -> 1.28 | S10: 1.23 | T10: ="S"&(INT((H10-ProjectStart)/SprintLen)+1) -> S1 | V10: =IF(AND($H10<=V$6+6,$I10>=V$6),1,"") -> 1 | W10: =IF(AND($H10<=W$6+6,$I10>=W$6),1,"") | X10: =IF(AND($H10<=X$6+6,$I10>=X$6),1,"") | Y10: =IF(AND($H10<=Y$6+6,$I10>=Y$6),1,"") | Z10: =IF(AND($H10<=Z$6+6,$I10>=Z$6),1,"") | AA10: =IF(AND($H10<=AA$6+6,$I10>=AA$6),1,"") | AB10: =IF(AND($H10<=AB$6+6,$I10>=AB$6),1,"") | AC10: =IF(AND($H10<=AC$6+6,$I10>=AC$6),1,"") | ... AP10: =IF(AND($H10<=AP$6+6,$I10>=AP$6),1,"")
A11: 1.3 | B11: 2 | C11: Gather SAP, Oracle, QA and testing use cases | D11: Use-case catalogue | E11: Product Owner / App SMEs | F11: 1.1 | G11: 3 | H11: =WORKDAY(MAX($I$9),1,Holidays) -> 46316 | I11: =WORKDAY(H11,G11-1,Holidays) -> 46318 | J11: =IF(StatusDate<H11,0,MIN(1,NETWORKDAYS(H11,StatusDate,Holidays)/G11)) -> 1 | K11: 1 | L11: =K11-J11 -> 0 | M11: =IF(K11>=1,"Complete",IF(StatusDate>I11,"Overdue",IF(K11>0,IF(K11<J11-0.1,"Behind","In Progress"),IF(StatusDate>H11,"Late Start","Not Started")))) -> Complete | N11: 3 | O11: =G11*N11 -> 9 | P11: =O11*BlendedRate -> 2.88 | Q11: =P11*J11 -> 2.88 | R11: =P11*K11 -> 2.88 | S11: 2.76 | T11: ="S"&(INT((H11-ProjectStart)/SprintLen)+1) -> S1 | V11: =IF(AND($H11<=V$6+6,$I11>=V$6),1,"") -> 1 | W11: =IF(AND($H11<=W$6+6,$I11>=W$6),1,"") | X11: =IF(AND($H11<=X$6+6,$I11>=X$6),1,"") | Y11: =IF(AND($H11<=Y$6+6,$I11>=Y$6),1,"") | Z11: =IF(AND($H11<=Z$6+6,$I11>=Z$6),1,"") | AA11: =IF(AND($H11<=AA$6+6,$I11>=AA$6),1,"") | AB11: =IF(AND($H11<=AB$6+6,$I11>=AB$6),1,"") | AC11: =IF(AND($H11<=AC$6+6,$I11>=AC$6),1,"") | ... AP11: =IF(AND($H11<=AP$6+6,$I11>=AP$6),1,"")
A12: 1.4 | B12: 2 | C12: Define functional and non-functional requirements | D12: Requirements specification | E12: Product Owner | F12: 1.3 | G12: 3 | H12: =WORKDAY(MAX($I$11),1,Holidays) -> 46321 | I12: =WORKDAY(H12,G12-1,Holidays) -> 46323 | J12: =IF(StatusDate<H12,0,MIN(1,NETWORKDAYS(H12,StatusDate,Holidays)/G12)) -> 1 | K12: 1 | L12: =K12-J12 -> 0 | M12: =IF(K12>=1,"Complete",IF(StatusDate>I12,"Overdue",IF(K12>0,IF(K12<J12-0.1,"Behind","In Progress"),IF(StatusDate>H12,"Late Start","Not Started")))) -> Complete | N12: 2 | O12: =G12*N12 -> 6 | P12: =O12*BlendedRate -> 1.92 | Q12: =P12*J12 -> 1.92 | R12: =P12*K12 -> 1.92 | S12: 1.84 | T12: ="S"&(INT((H12-ProjectStart)/SprintLen)+1) -> S1 | V12: =IF(AND($H12<=V$6+6,$I12>=V$6),1,"") | W12: =IF(AND($H12<=W$6+6,$I12>=W$6),1,"") -> 1 | X12: =IF(AND($H12<=X$6+6,$I12>=X$6),1,"") | Y12: =IF(AND($H12<=Y$6+6,$I12>=Y$6),1,"") | Z12: =IF(AND($H12<=Z$6+6,$I12>=Z$6),1,"") | AA12: =IF(AND($H12<=AA$6+6,$I12>=AA$6),1,"") | AB12: =IF(AND($H12<=AB$6+6,$I12>=AB$6),1,"") | AC12: =IF(AND($H12<=AC$6+6,$I12>=AC$6),1,"") | ... AP12: =IF(AND($H12<=AP$6+6,$I12>=AP$6),1,"")
A13: 1.5 | B13: 2 | C13: Inventory available APIs, MCP-capable tools and documentation | D13: Application inventory | E13: Backend / MCP Engineer | F13: 1.3 | G13: 3 | H13: =WORKDAY(MAX($I$11),1,Holidays) -> 46321 | I13: =WORKDAY(H13,G13-1,Holidays) -> 46323 | J13: =IF(StatusDate<H13,0,MIN(1,NETWORKDAYS(H13,StatusDate,Holidays)/G13)) -> 1 | K13: 1 | L13: =K13-J13 -> 0 | M13: =IF(K13>=1,"Complete",IF(StatusDate>I13,"Overdue",IF(K13>0,IF(K13<J13-0.1,"Behind","In Progress"),IF(StatusDate>H13,"Late Start","Not Started")))) -> Complete | N13: 2 | O13: =G13*N13 -> 6 | P13: =O13*BlendedRate -> 1.92 | Q13: =P13*J13 -> 1.92 | R13: =P13*K13 -> 1.92 | S13: 1.84 | T13: ="S"&(INT((H13-ProjectStart)/SprintLen)+1) -> S1 | V13: =IF(AND($H13<=V$6+6,$I13>=V$6),1,"") | W13: =IF(AND($H13<=W$6+6,$I13>=W$6),1,"") -> 1 | X13: =IF(AND($H13<=X$6+6,$I13>=X$6),1,"") | Y13: =IF(AND($H13<=Y$6+6,$I13>=Y$6),1,"") | Z13: =IF(AND($H13<=Z$6+6,$I13>=Z$6),1,"") | AA13: =IF(AND($H13<=AA$6+6,$I13>=AA$6),1,"") | AB13: =IF(AND($H13<=AB$6+6,$I13>=AB$6),1,"") | AC13: =IF(AND($H13<=AC$6+6,$I13>=AC$6),1,"") | ... AP13: =IF(AND($H13<=AP$6+6,$I13>=AP$6),1,"")
A14: 1.6 | B14: 2 | C14: Assess document quality, data classification and source ownership | D14: Data-source assessment | E14: AI / RAG Engineer / App SMEs | F14: 1.5 | G14: 3 | H14: =WORKDAY(MAX($I$13),1,Holidays) -> 46324 | I14: =WORKDAY(H14,G14-1,Holidays) -> 46328 | J14: =IF(StatusDate<H14,0,MIN(1,NETWORKDAYS(H14,StatusDate,Holidays)/G14)) -> 1 | K14: 1 | L14: =K14-J14 -> 0 | M14: =IF(K14>=1,"Complete",IF(StatusDate>I14,"Overdue",IF(K14>0,IF(K14<J14-0.1,"Behind","In Progress"),IF(StatusDate>H14,"Late Start","Not Started")))) -> Complete | N14: 2 | O14: =G14*N14 -> 6 | P14: =O14*BlendedRate -> 1.92 | Q14: =P14*J14 -> 1.92 | R14: =P14*K14 -> 1.92 | S14: 1.84 | T14: ="S"&(INT((H14-ProjectStart)/SprintLen)+1) -> S1 | V14: =IF(AND($H14<=V$6+6,$I14>=V$6),1,"") | W14: =IF(AND($H14<=W$6+6,$I14>=W$6),1,"") -> 1 | X14: =IF(AND($H14<=X$6+6,$I14>=X$6),1,"") -> 1 | Y14: =IF(AND($H14<=Y$6+6,$I14>=Y$6),1,"") | Z14: =IF(AND($H14<=Z$6+6,$I14>=Z$6),1,"") | AA14: =IF(AND($H14<=AA$6+6,$I14>=AA$6),1,"") | AB14: =IF(AND($H14<=AB$6+6,$I14>=AB$6),1,"") | AC14: =IF(AND($H14<=AC$6+6,$I14>=AC$6),1,"") | ... AP14: =IF(AND($H14<=AP$6+6,$I14>=AP$6),1,"")
A15: 1.7 | B15: 2 | C15: Design Azure AI Foundry and application architecture | D15: Architecture diagram | E15: Solution Architect | F15: 1.4 | G15: 3 | H15: =WORKDAY(MAX($I$12),1,Holidays) -> 46324 | I15: =WORKDAY(H15,G15-1,Holidays) -> 46328 | J15: =IF(StatusDate<H15,0,MIN(1,NETWORKDAYS(H15,StatusDate,Holidays)/G15)) -> 1 | K15: 1 | L15: =K15-J15 -> 0 | M15: =IF(K15>=1,"Complete",IF(StatusDate>I15,"Overdue",IF(K15>0,IF(K15<J15-0.1,"Behind","In Progress"),IF(StatusDate>H15,"Late Start","Not Started")))) -> Complete | N15: 2 | O15: =G15*N15 -> 6 | P15: =O15*BlendedRate -> 1.92 | Q15: =P15*J15 -> 1.92 | R15: =P15*K15 -> 1.92 | S15: 1.84 | T15: ="S"&(INT((H15-ProjectStart)/SprintLen)+1) -> S1 | V15: =IF(AND($H15<=V$6+6,$I15>=V$6),1,"") | W15: =IF(AND($H15<=W$6+6,$I15>=W$6),1,"") -> 1 | X15: =IF(AND($H15<=X$6+6,$I15>=X$6),1,"") -> 1 | Y15: =IF(AND($H15<=Y$6+6,$I15>=Y$6),1,"") | Z15: =IF(AND($H15<=Z$6+6,$I15>=Z$6),1,"") | AA15: =IF(AND($H15<=AA$6+6,$I15>=AA$6),1,"") | AB15: =IF(AND($H15<=AB$6+6,$I15>=AB$6),1,"") | AC15: =IF(AND($H15<=AC$6+6,$I15>=AC$6),1,"") | ... AP15: =IF(AND($H15<=AP$6+6,$I15>=AP$6),1,"")
A16: 1.8 | B16: 2 | C16: Define RAG, Foundry IQ and MCP interaction patterns | D16: Integration design | E16: Solution Architect | F16: 1.7, 1.6 | G16: 2 | H16: =WORKDAY(MAX($I$15,$I$14),1,Holidays) -> 46329 | I16: =WORKDAY(H16,G16-1,Holidays) -> 46330 | J16: =IF(StatusDate<H16,0,MIN(1,NETWORKDAYS(H16,StatusDate,Holidays)/G16)) -> 1 | K16: 1 | L16: =K16-J16 -> 0 | M16: =IF(K16>=1,"Complete",IF(StatusDate>I16,"Overdue",IF(K16>0,IF(K16<J16-0.1,"Behind","In Progress"),IF(StatusDate>H16,"Late Start","Not Started")))) -> Complete | N16: 2 | O16: =G16*N16 -> 4 | P16: =O16*BlendedRate -> 1.28 | Q16: =P16*J16 -> 1.28 | R16: =P16*K16 -> 1.28 | S16: 1.23 | T16: ="S"&(INT((H16-ProjectStart)/SprintLen)+1) -> S2 | V16: =IF(AND($H16<=V$6+6,$I16>=V$6),1,"") | W16: =IF(AND($H16<=W$6+6,$I16>=W$6),1,"") | X16: =IF(AND($H16<=X$6+6,$I16>=X$6),1,"") -> 1 | Y16: =IF(AND($H16<=Y$6+6,$I16>=Y$6),1,"") | Z16: =IF(AND($H16<=Z$6+6,$I16>=Z$6),1,"") | AA16: =IF(AND($H16<=AA$6+6,$I16>=AA$6),1,"") | AB16: =IF(AND($H16<=AB$6+6,$I16>=AB$6),1,"") | AC16: =IF(AND($H16<=AC$6+6,$I16>=AC$6),1,"") | ... AP16: =IF(AND($H16<=AP$6+6,$I16>=AP$6),1,"")
A17: 1.9 | B17: 2 | C17: Design identity, access, network and secrets management | D17: Security design | E17: Security Engineer | F17: 1.7 | G17: 2 | H17: =WORKDAY(MAX($I$15),1,Holidays) -> 46329 | I17: =WORKDAY(H17,G17-1,Holidays) -> 46330 | J17: =IF(StatusDate<H17,0,MIN(1,NETWORKDAYS(H17,StatusDate,Holidays)/G17)) -> 1 | K17: 1 | L17: =K17-J17 -> 0 | M17: =IF(K17>=1,"Complete",IF(StatusDate>I17,"Overdue",IF(K17>0,IF(K17<J17-0.1,"Behind","In Progress"),IF(StatusDate>H17,"Late Start","Not Started")))) -> Complete | N17: 1 | O17: =G17*N17 -> 2 | P17: =O17*BlendedRate -> 0.64 | Q17: =P17*J17 -> 0.64 | R17: =P17*K17 -> 0.64 | S17: 0.61 | T17: ="S"&(INT((H17-ProjectStart)/SprintLen)+1) -> S2 | V17: =IF(AND($H17<=V$6+6,$I17>=V$6),1,"") | W17: =IF(AND($H17<=W$6+6,$I17>=W$6),1,"") | X17: =IF(AND($H17<=X$6+6,$I17>=X$6),1,"") -> 1 | Y17: =IF(AND($H17<=Y$6+6,$I17>=Y$6),1,"") | Z17: =IF(AND($H17<=Z$6+6,$I17>=Z$6),1,"") | AA17: =IF(AND($H17<=AA$6+6,$I17>=AA$6),1,"") | AB17: =IF(AND($H17<=AB$6+6,$I17>=AB$6),1,"") | AC17: =IF(AND($H17<=AC$6+6,$I17>=AC$6),1,"") | ... AP17: =IF(AND($H17<=AP$6+6,$I17>=AP$6),1,"")
A18: 1.10 | B18: 2 | C18: Create backlog, sprint plan, risks and acceptance criteria | D18: Delivery plan | E18: Project Manager | F18: 1.8, 1.9 | G18: 2 | H18: =WORKDAY(MAX($I$16,$I$17),1,Holidays) -> 46331 | I18: =WORKDAY(H18,G18-1,Holidays) -> 46332 | J18: =IF(StatusDate<H18,0,MIN(1,NETWORKDAYS(H18,StatusDate,Holidays)/G18)) -> 1 | K18: 1 | L18: =K18-J18 -> 0 | M18: =IF(K18>=1,"Complete",IF(StatusDate>I18,"Overdue",IF(K18>0,IF(K18<J18-0.1,"Behind","In Progress"),IF(StatusDate>H18,"Late Start","Not Started")))) -> Complete | N18: 2 | O18: =G18*N18 -> 4 | P18: =O18*BlendedRate -> 1.28 | Q18: =P18*J18 -> 1.28 | R18: =P18*K18 -> 1.28 | S18: 1.23 | T18: ="S"&(INT((H18-ProjectStart)/SprintLen)+1) -> S2 | V18: =IF(AND($H18<=V$6+6,$I18>=V$6),1,"") | W18: =IF(AND($H18<=W$6+6,$I18>=W$6),1,"") | X18: =IF(AND($H18<=X$6+6,$I18>=X$6),1,"") -> 1 | Y18: =IF(AND($H18<=Y$6+6,$I18>=Y$6),1,"") | Z18: =IF(AND($H18<=Z$6+6,$I18>=Z$6),1,"") | AA18: =IF(AND($H18<=AA$6+6,$I18>=AA$6),1,"") | AB18: =IF(AND($H18<=AB$6+6,$I18>=AB$6),1,"") | AC18: =IF(AND($H18<=AC$6+6,$I18>=AC$6),1,"") | ... AP18: =IF(AND($H18<=AP$6+6,$I18>=AP$6),1,"")
A19: M1 | B19: 2 | C19: ◆ Milestone M1 — Architecture approved | D19: Signed-off requirements and design | E19: Project Manager / Sponsor | F19: End of Week 4 | G19: 0 | H19: =I19 -> 46342 | I19: =WORKDAY(ProjectStart-1,20,Holidays) -> 46342 | J19: =IF(StatusDate>=I19,1,0) -> 1 | K19: 1 | L19: =K19-J19 -> 0 | M19: =IF(K19>=1,"Complete",IF(StatusDate>I19,"Overdue",IF(K19>0,IF(K19<J19-0.1,"Behind","In Progress"),IF(StatusDate>H19,"Late Start","Not Started")))) -> Complete | T19: ="S"&(INT((H19-ProjectStart)/SprintLen)+1) -> S3 | U19: Gate: all phase deliverables complete before sign-off | V19: =IF(AND($I19>=V$6,$I19<=V$6+6),"◆","") | W19: =IF(AND($I19>=W$6,$I19<=W$6+6),"◆","") | X19: =IF(AND($I19>=X$6,$I19<=X$6+6),"◆","") | Y19: =IF(AND($I19>=Y$6,$I19<=Y$6+6),"◆","") | Z19: =IF(AND($I19>=Z$6,$I19<=Z$6+6),"◆","") -> ◆ | AA19: =IF(AND($I19>=AA$6,$I19<=AA$6+6),"◆","") | AB19: =IF(AND($I19>=AB$6,$I19<=AB$6+6),"◆","") | AC19: =IF(AND($I19>=AC$6,$I19<=AC$6+6),"◆","") | ... AP19: =IF(AND($I19>=AP$6,$I19<=AP$6+6),"◆","")
A20: 2 | B20: 1 | C20: Month 2 — AI Foundation & Knowledge Retrieval | D20: Milestone M2: AI assistant MVP | E20: Project Manager | G20: =NETWORKDAYS(H20,I20,Holidays) -> 20 | H20: =MIN(H21:H31) -> 46343 | I20: =MAX(I21:I31) -> 46371 | J20: =IF(P20=0,0,Q20/P20) -> 1 | K20: =IF(P20=0,0,R20/P20) -> 1 | L20: =K20-J20 -> 0 | M20: =IF(K20>=1,"Complete",IF(StatusDate>I20,"Overdue",IF(K20>0,IF(K20<J20-0.1,"Behind","In Progress"),IF(StatusDate>H20,"Late Start","Not Started")))) -> Complete | N20: =MAX(N21:N31) -> 3 | O20: =SUM(O21:O31) -> 54 | P20: =SUM(P21:P31) -> 17.28 | Q20: =SUM(Q21:Q31) -> 17.28 | R20: =SUM(R21:R31) -> 17.28 | S20: =SUM(S21:S31) -> 17.9 | U20: Exit: A user can ask questions about approved sample documentation and receive relevant, source-grounded answers through the chat interface. | V20: =IF(AND($H20<=V$6+6,$I20>=V$6),1,"") | W20: =IF(AND($H20<=W$6+6,$I20>=W$6),1,"") | X20: =IF(AND($H20<=X$6+6,$I20>=X$6),1,"") | Y20: =IF(AND($H20<=Y$6+6,$I20>=Y$6),1,"") | Z20: =IF(AND($H20<=Z$6+6,$I20>=Z$6),1,"") -> 1 | AA20: =IF(AND($H20<=AA$6+6,$I20>=AA$6),1,"") -> 1 | AB20: =IF(AND($H20<=AB$6+6,$I20>=AB$6),1,"") -> 1 | AC20: =IF(AND($H20<=AC$6+6,$I20>=AC$6),1,"") -> 1 | ... AP20: =IF(AND($H20<=AP$6+6,$I20>=AP$6),1,"")
A21: 2.1 | B21: 2 | C21: Provision approved Azure development resources | D21: Development environment | E21: DevOps Engineer | F21: M1 | G21: 2 | H21: =WORKDAY(MAX($I$19),1,Holidays) -> 46343 | I21: =WORKDAY(H21,G21-1,Holidays) -> 46344 | J21: =IF(StatusDate<H21,0,MIN(1,NETWORKDAYS(H21,StatusDate,Holidays)/G21)) -> 1 | K21: 1 | L21: =K21-J21 -> 0 | M21: =IF(K21>=1,"Complete",IF(StatusDate>I21,"Overdue",IF(K21>0,IF(K21<J21-0.1,"Behind","In Progress"),IF(StatusDate>H21,"Late Start","Not Started")))) -> Complete | N21: 1 | O21: =G21*N21 -> 2 | P21: =O21*BlendedRate -> 0.64 | Q21: =P21*J21 -> 0.64 | R21: =P21*K21 -> 0.64 | S21: 0.65 | T21: ="S"&(INT((H21-ProjectStart)/SprintLen)+1) -> S3 | V21: =IF(AND($H21<=V$6+6,$I21>=V$6),1,"") | W21: =IF(AND($H21<=W$6+6,$I21>=W$6),1,"") | X21: =IF(AND($H21<=X$6+6,$I21>=X$6),1,"") | Y21: =IF(AND($H21<=Y$6+6,$I21>=Y$6),1,"") | Z21: =IF(AND($H21<=Z$6+6,$I21>=Z$6),1,"") -> 1 | AA21: =IF(AND($H21<=AA$6+6,$I21>=AA$6),1,"") | AB21: =IF(AND($H21<=AB$6+6,$I21>=AB$6),1,"") | AC21: =IF(AND($H21<=AC$6+6,$I21>=AC$6),1,"") | ... AP21: =IF(AND($H21<=AP$6+6,$I21>=AP$6),1,"")
A22: 2.2 | B22: 2 | C22: Configure AI Foundry project and model access | D22: Foundry environment | E22: AI / RAG Engineer | F22: 2.1 | G22: 2 | H22: =WORKDAY(MAX($I$21),1,Holidays) -> 46345 | I22: =WORKDAY(H22,G22-1,Holidays) -> 46346 | J22: =IF(StatusDate<H22,0,MIN(1,NETWORKDAYS(H22,StatusDate,Holidays)/G22)) -> 1 | K22: 1 | L22: =K22-J22 -> 0 | M22: =IF(K22>=1,"Complete",IF(StatusDate>I22,"Overdue",IF(K22>0,IF(K22<J22-0.1,"Behind","In Progress"),IF(StatusDate>H22,"Late Start","Not Started")))) -> Complete | N22: 2 | O22: =G22*N22 -> 4 | P22: =O22*BlendedRate -> 1.28 | Q22: =P22*J22 -> 1.28 | R22: =P22*K22 -> 1.28 | S22: 1.31 | T22: ="S"&(INT((H22-ProjectStart)/SprintLen)+1) -> S3 | V22: =IF(AND($H22<=V$6+6,$I22>=V$6),1,"") | W22: =IF(AND($H22<=W$6+6,$I22>=W$6),1,"") | X22: =IF(AND($H22<=X$6+6,$I22>=X$6),1,"") | Y22: =IF(AND($H22<=Y$6+6,$I22>=Y$6),1,"") | Z22: =IF(AND($H22<=Z$6+6,$I22>=Z$6),1,"") -> 1 | AA22: =IF(AND($H22<=AA$6+6,$I22>=AA$6),1,"") | AB22: =IF(AND($H22<=AB$6+6,$I22>=AB$6),1,"") | AC22: =IF(AND($H22<=AC$6+6,$I22>=AC$6),1,"") | ... AP22: =IF(AND($H22<=AP$6+6,$I22>=AP$6),1,"")
A23: 2.3 | B23: 2 | C23: Validate GPT-5 availability, deployment and inference | D23: Model integration | E23: AI / RAG Engineer | F23: 2.2 | G23: 2 | H23: =WORKDAY(MAX($I$22),1,Holidays) -> 46349 | I23: =WORKDAY(H23,G23-1,Holidays) -> 46351 | J23: =IF(StatusDate<H23,0,MIN(1,NETWORKDAYS(H23,StatusDate,Holidays)/G23)) -> 1 | K23: 1 | L23: =K23-J23 -> 0 | M23: =IF(K23>=1,"Complete",IF(StatusDate>I23,"Overdue",IF(K23>0,IF(K23<J23-0.1,"Behind","In Progress"),IF(StatusDate>H23,"Late Start","Not Started")))) -> Complete | N23: 2 | O23: =G23*N23 -> 4 | P23: =O23*BlendedRate -> 1.28 | Q23: =P23*J23 -> 1.28 | R23: =P23*K23 -> 1.28 | S23: 1.31 | T23: ="S"&(INT((H23-ProjectStart)/SprintLen)+1) -> S3 | V23: =IF(AND($H23<=V$6+6,$I23>=V$6),1,"") | W23: =IF(AND($H23<=W$6+6,$I23>=W$6),1,"") | X23: =IF(AND($H23<=X$6+6,$I23>=X$6),1,"") | Y23: =IF(AND($H23<=Y$6+6,$I23>=Y$6),1,"") | Z23: =IF(AND($H23<=Z$6+6,$I23>=Z$6),1,"") | AA23: =IF(AND($H23<=AA$6+6,$I23>=AA$6),1,"") -> 1 | AB23: =IF(AND($H23<=AB$6+6,$I23>=AB$6),1,"") | AC23: =IF(AND($H23<=AC$6+6,$I23>=AC$6),1,"") | ... AP23: =IF(AND($H23<=AP$6+6,$I23>=AP$6),1,"")
A24: 2.4 | B24: 2 | C24: Evaluate GPT_Image-2 availability and visual-generation use cases | D24: Image capability proof of concept | E24: AI / RAG Engineer | F24: 2.3 | G24: 1 | H24: =WORKDAY(MAX($I$23),1,Holidays) -> 46352 | I24: =WORKDAY(H24,G24-1,Holidays) -> 46352 | J24: =IF(StatusDate<H24,0,MIN(1,NETWORKDAYS(H24,StatusDate,Holidays)/G24)) -> 1 | K24: 1 | L24: =K24-J24 -> 0 | M24: =IF(K24>=1,"Complete",IF(StatusDate>I24,"Overdue",IF(K24>0,IF(K24<J24-0.1,"Behind","In Progress"),IF(StatusDate>H24,"Late Start","Not Started")))) -> Complete | N24: 1 | O24: =G24*N24 -> 1 | P24: =O24*BlendedRate -> 0.32 | Q24: =P24*J24 -> 0.32 | R24: =P24*K24 -> 0.32 | S24: 0.33 | T24: ="S"&(INT((H24-ProjectStart)/SprintLen)+1) -> S3 | V24: =IF(AND($H24<=V$6+6,$I24>=V$6),1,"") | W24: =IF(AND($H24<=W$6+6,$I24>=W$6),1,"") | X24: =IF(AND($H24<=X$6+6,$I24>=X$6),1,"") | Y24: =IF(AND($H24<=Y$6+6,$I24>=Y$6),1,"") | Z24: =IF(AND($H24<=Z$6+6,$I24>=Z$6),1,"") | AA24: =IF(AND($H24<=AA$6+6,$I24>=AA$6),1,"") -> 1 | AB24: =IF(AND($H24<=AB$6+6,$I24>=AB$6),1,"") | AC24: =IF(AND($H24<=AC$6+6,$I24>=AC$6),1,"") | ... AP24: =IF(AND($H24<=AP$6+6,$I24>=AP$6),1,"")
A25: 2.5 | B25: 2 | C25: Prepare sample SAP, Oracle, QA and testing documents | D25: Curated test corpus | E25: App SMEs / AI / RAG Engineer | F25: M1 | G25: 3 | H25: =WORKDAY(MAX($I$19),1,Holidays) -> 46343 | I25: =WORKDAY(H25,G25-1,Holidays) -> 46345 | J25: =IF(StatusDate<H25,0,MIN(1,NETWORKDAYS(H25,StatusDate,Holidays)/G25)) -> 1 | K25: 1 | L25: =K25-J25 -> 0 | M25: =IF(K25>=1,"Complete",IF(StatusDate>I25,"Overdue",IF(K25>0,IF(K25<J25-0.1,"Behind","In Progress"),IF(StatusDate>H25,"Late Start","Not Started")))) -> Complete | N25: 3 | O25: =G25*N25 -> 9 | P25: =O25*BlendedRate -> 2.88 | Q25: =P25*J25 -> 2.88 | R25: =P25*K25 -> 2.88 | S25: 2.94 | T25: ="S"&(INT((H25-ProjectStart)/SprintLen)+1) -> S3 | V25: =IF(AND($H25<=V$6+6,$I25>=V$6),1,"") | W25: =IF(AND($H25<=W$6+6,$I25>=W$6),1,"") | X25: =IF(AND($H25<=X$6+6,$I25>=X$6),1,"") | Y25: =IF(AND($H25<=Y$6+6,$I25>=Y$6),1,"") | Z25: =IF(AND($H25<=Z$6+6,$I25>=Z$6),1,"") -> 1 | AA25: =IF(AND($H25<=AA$6+6,$I25>=AA$6),1,"") | AB25: =IF(AND($H25<=AB$6+6,$I25>=AB$6),1,"") | AC25: =IF(AND($H25<=AC$6+6,$I25>=AC$6),1,"") | ... AP25: =IF(AND($H25<=AP$6+6,$I25>=AP$6),1,"")
A26: 2.6 | B26: 2 | C26: Configure Foundry IQ knowledge sources and retrieval | D26: Knowledge retrieval pipeline | E26: AI / RAG Engineer | F26: 2.3, 2.5 | G26: 4 | H26: =WORKDAY(MAX($I$23,$I$25),1,Holidays) -> 46352 | I26: =WORKDAY(H26,G26-1,Holidays) -> 46357 | J26: =IF(StatusDate<H26,0,MIN(1,NETWORKDAYS(H26,StatusDate,Holidays)/G26)) -> 1 | K26: 1 | L26: =K26-J26 -> 0 | M26: =IF(K26>=1,"Complete",IF(StatusDate>I26,"Overdue",IF(K26>0,IF(K26<J26-0.1,"Behind","In Progress"),IF(StatusDate>H26,"Late Start","Not Started")))) -> Complete | N26: 2 | O26: =G26*N26 -> 8 | P26: =O26*BlendedRate -> 2.56 | Q26: =P26*J26 -> 2.56 | R26: =P26*K26 -> 2.56 | S26: 2.87 | T26: ="S"&(INT((H26-ProjectStart)/SprintLen)+1) -> S3 | V26: =IF(AND($H26<=V$6+6,$I26>=V$6),1,"") | W26: =IF(AND($H26<=W$6+6,$I26>=W$6),1,"") | X26: =IF(AND($H26<=X$6+6,$I26>=X$6),1,"") | Y26: =IF(AND($H26<=Y$6+6,$I26>=Y$6),1,"") | Z26: =IF(AND($H26<=Z$6+6,$I26>=Z$6),1,"") | AA26: =IF(AND($H26<=AA$6+6,$I26>=AA$6),1,"") -> 1 | AB26: =IF(AND($H26<=AB$6+6,$I26>=AB$6),1,"") -> 1 | AC26: =IF(AND($H26<=AC$6+6,$I26>=AC$6),1,"") | ... AP26: =IF(AND($H26<=AP$6+6,$I26>=AP$6),1,"")
A27: 2.7 | B27: 2 | C27: Implement chunking, indexing and metadata strategy | D27: Searchable knowledge base | E27: AI / RAG Engineer | F27: 2.6 | G27: 3 | H27: =WORKDAY(MAX($I$26),1,Holidays) -> 46358 | I27: =WORKDAY(H27,G27-1,Holidays) -> 46360 | J27: =IF(StatusDate<H27,0,MIN(1,NETWORKDAYS(H27,StatusDate,Holidays)/G27)) -> 1 | K27: 1 | L27: =K27-J27 -> 0 | M27: =IF(K27>=1,"Complete",IF(StatusDate>I27,"Overdue",IF(K27>0,IF(K27<J27-0.1,"Behind","In Progress"),IF(StatusDate>H27,"Late Start","Not Started")))) -> Complete | N27: 2 | O27: =G27*N27 -> 6 | P27: =O27*BlendedRate -> 1.92 | Q27: =P27*J27 -> 1.92 | R27: =P27*K27 -> 1.92 | S27: 1.96 | T27: ="S"&(INT((H27-ProjectStart)/SprintLen)+1) -> S4 | V27: =IF(AND($H27<=V$6+6,$I27>=V$6),1,"") | W27: =IF(AND($H27<=W$6+6,$I27>=W$6),1,"") | X27: =IF(AND($H27<=X$6+6,$I27>=X$6),1,"") | Y27: =IF(AND($H27<=Y$6+6,$I27>=Y$6),1,"") | Z27: =IF(AND($H27<=Z$6+6,$I27>=Z$6),1,"") | AA27: =IF(AND($H27<=AA$6+6,$I27>=AA$6),1,"") | AB27: =IF(AND($H27<=AB$6+6,$I27>=AB$6),1,"") -> 1 | AC27: =IF(AND($H27<=AC$6+6,$I27>=AC$6),1,"") | ... AP27: =IF(AND($H27<=AP$6+6,$I27>=AP$6),1,"")
A28: 2.8 | B28: 2 | C28: Implement grounded answers, citations and source references | D28: RAG response workflow | E28: AI / RAG Engineer | F28: 2.7 | G28: 3 | H28: =WORKDAY(MAX($I$27),1,Holidays) -> 46363 | I28: =WORKDAY(H28,G28-1,Holidays) -> 46365 | J28: =IF(StatusDate<H28,0,MIN(1,NETWORKDAYS(H28,StatusDate,Holidays)/G28)) -> 1 | K28: 1 | L28: =K28-J28 -> 0 | M28: =IF(K28>=1,"Complete",IF(StatusDate>I28,"Overdue",IF(K28>0,IF(K28<J28-0.1,"Behind","In Progress"),IF(StatusDate>H28,"Late Start","Not Started")))) -> Complete | N28: 2 | O28: =G28*N28 -> 6 | P28: =O28*BlendedRate -> 1.92 | Q28: =P28*J28 -> 1.92 | R28: =P28*K28 -> 1.92 | S28: 1.96 | T28: ="S"&(INT((H28-ProjectStart)/SprintLen)+1) -> S4 | V28: =IF(AND($H28<=V$6+6,$I28>=V$6),1,"") | W28: =IF(AND($H28<=W$6+6,$I28>=W$6),1,"") | X28: =IF(AND($H28<=X$6+6,$I28>=X$6),1,"") | Y28: =IF(AND($H28<=Y$6+6,$I28>=Y$6),1,"") | Z28: =IF(AND($H28<=Z$6+6,$I28>=Z$6),1,"") | AA28: =IF(AND($H28<=AA$6+6,$I28>=AA$6),1,"") | AB28: =IF(AND($H28<=AB$6+6,$I28>=AB$6),1,"") | AC28: =IF(AND($H28<=AC$6+6,$I28>=AC$6),1,"") -> 1 | ... AP28: =IF(AND($H28<=AP$6+6,$I28>=AP$6),1,"")
A29: 2.9 | B29: 2 | C29: Build chat UI, conversation flow and application navigation | D29: Web chat prototype | E29: Frontend Engineer | F29: 2.3 | G29: 4 | H29: =WORKDAY(MAX($I$23),1,Holidays) -> 46352 | I29: =WORKDAY(H29,G29-1,Holidays) -> 46357 | J29: =IF(StatusDate<H29,0,MIN(1,NETWORKDAYS(H29,StatusDate,Holidays)/G29)) -> 1 | K29: 1 | L29: =K29-J29 -> 0 | M29: =IF(K29>=1,"Complete",IF(StatusDate>I29,"Overdue",IF(K29>0,IF(K29<J29-0.1,"Behind","In Progress"),IF(StatusDate>H29,"Late Start","Not Started")))) -> Complete | N29: 2 | O29: =G29*N29 -> 8 | P29: =O29*BlendedRate -> 2.56 | Q29: =P29*J29 -> 2.56 | R29: =P29*K29 -> 2.56 | S29: 2.61 | T29: ="S"&(INT((H29-ProjectStart)/SprintLen)+1) -> S3 | V29: =IF(AND($H29<=V$6+6,$I29>=V$6),1,"") | W29: =IF(AND($H29<=W$6+6,$I29>=W$6),1,"") | X29: =IF(AND($H29<=X$6+6,$I29>=X$6),1,"") | Y29: =IF(AND($H29<=Y$6+6,$I29>=Y$6),1,"") | Z29: =IF(AND($H29<=Z$6+6,$I29>=Z$6),1,"") | AA29: =IF(AND($H29<=AA$6+6,$I29>=AA$6),1,"") -> 1 | AB29: =IF(AND($H29<=AB$6+6,$I29>=AB$6),1,"") -> 1 | AC29: =IF(AND($H29<=AC$6+6,$I29>=AC$6),1,"") | ... AP29: =IF(AND($H29<=AP$6+6,$I29>=AP$6),1,"")
A30: 2.10 | B30: 2 | C30: Add logging, error handling and baseline evaluation | D30: Baseline evaluation report | E30: QA Engineer / AI / RAG Engineer | F30: 2.8, 2.9 | G30: 3 | H30: =WORKDAY(MAX($I$28,$I$29),1,Holidays) -> 46366 | I30: =WORKDAY(H30,G30-1,Holidays) -> 46370 | J30: =IF(StatusDate<H30,0,MIN(1,NETWORKDAYS(H30,StatusDate,Holidays)/G30)) -> 1 | K30: 1 | L30: =K30-J30 -> 0 | M30: =IF(K30>=1,"Complete",IF(StatusDate>I30,"Overdue",IF(K30>0,IF(K30<J30-0.1,"Behind","In Progress"),IF(StatusDate>H30,"Late Start","Not Started")))) -> Complete | N30: 2 | O30: =G30*N30 -> 6 | P30: =O30*BlendedRate -> 1.92 | Q30: =P30*J30 -> 1.92 | R30: =P30*K30 -> 1.92 | S30: 1.96 | T30: ="S"&(INT((H30-ProjectStart)/SprintLen)+1) -> S4 | V30: =IF(AND($H30<=V$6+6,$I30>=V$6),1,"") | W30: =IF(AND($H30<=W$6+6,$I30>=W$6),1,"") | X30: =IF(AND($H30<=X$6+6,$I30>=X$6),1,"") | Y30: =IF(AND($H30<=Y$6+6,$I30>=Y$6),1,"") | Z30: =IF(AND($H30<=Z$6+6,$I30>=Z$6),1,"") | AA30: =IF(AND($H30<=AA$6+6,$I30>=AA$6),1,"") | AB30: =IF(AND($H30<=AB$6+6,$I30>=AB$6),1,"") | AC30: =IF(AND($H30<=AC$6+6,$I30>=AC$6),1,"") -> 1 | ... AP30: =IF(AND($H30<=AP$6+6,$I30>=AP$6),1,"")
A31: M2 | B31: 2 | C31: ◆ Milestone M2 — AI assistant MVP | D31: Grounded answers from approved documents | E31: Project Manager / Sponsor | F31: End of Week 8 | G31: 0 | H31: =I31 -> 46371 | I31: =WORKDAY(ProjectStart-1,40,Holidays) -> 46371 | J31: =IF(StatusDate>=I31,1,0) -> 1 | K31: 1 | L31: =K31-J31 -> 0 | M31: =IF(K31>=1,"Complete",IF(StatusDate>I31,"Overdue",IF(K31>0,IF(K31<J31-0.1,"Behind","In Progress"),IF(StatusDate>H31,"Late Start","Not Started")))) -> Complete | T31: ="S"&(INT((H31-ProjectStart)/SprintLen)+1) -> S5 | U31: Gate: all phase deliverables complete before sign-off | V31: =IF(AND($I31>=V$6,$I31<=V$6+6),"◆","") | W31: =IF(AND($I31>=W$6,$I31<=W$6+6),"◆","") | X31: =IF(AND($I31>=X$6,$I31<=X$6+6),"◆","") | Y31: =IF(AND($I31>=Y$6,$I31<=Y$6+6),"◆","") | Z31: =IF(AND($I31>=Z$6,$I31<=Z$6+6),"◆","") | AA31: =IF(AND($I31>=AA$6,$I31<=AA$6+6),"◆","") | AB31: =IF(AND($I31>=AB$6,$I31<=AB$6+6),"◆","") | AC31: =IF(AND($I31>=AC$6,$I31<=AC$6+6),"◆","") | ... AP31: =IF(AND($I31>=AP$6,$I31<=AP$6+6),"◆","")
A32: 3 | B32: 1 | C32: Month 3 — MCP & Enterprise Integration | D32: Milestone M3: Application integrations | E32: Project Manager | G32: =NETWORKDAYS(H32,I32,Holidays) -> 20 | H32: =MIN(H33:H43) -> 46372 | I32: =MAX(I33:I43) -> 46401 | J32: =IF(P32=0,0,Q32/P32) -> 1 | K32: =IF(P32=0,0,R32/P32) -> 0.84459459 | L32: =K32-J32 -> -0.15540541 | M32: =IF(K32>=1,"Complete",IF(StatusDate>I32,"Overdue",IF(K32>0,IF(K32<J32-0.1,"Behind","In Progress"),IF(StatusDate>H32,"Late Start","Not Started")))) -> Overdue | N32: =MAX(N33:N43) -> 3 | O32: =SUM(O33:O43) -> 74 | P32: =SUM(P33:P43) -> 23.68 | Q32: =SUM(Q33:Q43) -> 23.68 | R32: =SUM(R33:R43) -> 20 | S32: =SUM(S33:S43) -> 22.28 | U32: Exit: The assistant answers knowledge questions and executes approved, read-only operations against available test integrations (SAP/Oracle scope subject to API access, licensing and environment readiness). | V32: =IF(AND($H32<=V$6+6,$I32>=V$6),1,"") | W32: =IF(AND($H32<=W$6+6,$I32>=W$6),1,"") | X32: =IF(AND($H32<=X$6+6,$I32>=X$6),1,"") | Y32: =IF(AND($H32<=Y$6+6,$I32>=Y$6),1,"") | Z32: =IF(AND($H32<=Z$6+6,$I32>=Z$6),1,"") | AA32: =IF(AND($H32<=AA$6+6,$I32>=AA$6),1,"") | AB32: =IF(AND($H32<=AB$6+6,$I32>=AB$6),1,"") | AC32: =IF(AND($H32<=AC$6+6,$I32>=AC$6),1,"") | ... AP32: =IF(AND($H32<=AP$6+6,$I32>=AP$6),1,"")
A33: 3.1 | B33: 2 | C33: Define MCP server/client architecture and tool contracts | D33: MCP design specification | E33: Backend / MCP Engineer | F33: M2 | G33: 3 | H33: =WORKDAY(MAX($I$31),1,Holidays) -> 46372 | I33: =WORKDAY(H33,G33-1,Holidays) -> 46374 | J33: =IF(StatusDate<H33,0,MIN(1,NETWORKDAYS(H33,StatusDate,Holidays)/G33)) -> 1 | K33: 1 | L33: =K33-J33 -> 0 | M33: =IF(K33>=1,"Complete",IF(StatusDate>I33,"Overdue",IF(K33>0,IF(K33<J33-0.1,"Behind","In Progress"),IF(StatusDate>H33,"Late Start","Not Started")))) -> Complete | N33: 2 | O33: =G33*N33 -> 6 | P33: =O33*BlendedRate -> 1.92 | Q33: =P33*J33 -> 1.92 | R33: =P33*K33 -> 1.92 | S33: 2 | T33: ="S"&(INT((H33-ProjectStart)/SprintLen)+1) -> S5 | V33: =IF(AND($H33<=V$6+6,$I33>=V$6),1,"") | W33: =IF(AND($H33<=W$6+6,$I33>=W$6),1,"") | X33: =IF(AND($H33<=X$6+6,$I33>=X$6),1,"") | Y33: =IF(AND($H33<=Y$6+6,$I33>=Y$6),1,"") | Z33: =IF(AND($H33<=Z$6+6,$I33>=Z$6),1,"") | AA33: =IF(AND($H33<=AA$6+6,$I33>=AA$6),1,"") | AB33: =IF(AND($H33<=AB$6+6,$I33>=AB$6),1,"") | AC33: =IF(AND($H33<=AC$6+6,$I33>=AC$6),1,"") | ... AP33: =IF(AND($H33<=AP$6+6,$I33>=AP$6),1,"")
A34: 3.2 | B34: 2 | C34: Implement MCP connection and authentication | D34: Working MCP connection | E34: Backend / MCP Engineer | F34: 3.1 | G34: 4 | H34: =WORKDAY(MAX($I$33),1,Holidays) -> 46377 | I34: =WORKDAY(H34,G34-1,Holidays) -> 46380 | J34: =IF(StatusDate<H34,0,MIN(1,NETWORKDAYS(H34,StatusDate,Holidays)/G34)) -> 1 | K34: 1 | L34: =K34-J34 -> 0 | M34: =IF(K34>=1,"Complete",IF(StatusDate>I34,"Overdue",IF(K34>0,IF(K34<J34-0.1,"Behind","In Progress"),IF(StatusDate>H34,"Late Start","Not Started")))) -> Complete | N34: 2 | O34: =G34*N34 -> 8 | P34: =O34*BlendedRate -> 2.56 | Q34: =P34*J34 -> 2.56 | R34: =P34*K34 -> 2.56 | S34: 2.76 | T34: ="S"&(INT((H34-ProjectStart)/SprintLen)+1) -> S5 | V34: =IF(AND($H34<=V$6+6,$I34>=V$6),1,"") | W34: =IF(AND($H34<=W$6+6,$I34>=W$6),1,"") | X34: =IF(AND($H34<=X$6+6,$I34>=X$6),1,"") | Y34: =IF(AND($H34<=Y$6+6,$I34>=Y$6),1,"") | Z34: =IF(AND($H34<=Z$6+6,$I34>=Z$6),1,"") | AA34: =IF(AND($H34<=AA$6+6,$I34>=AA$6),1,"") | AB34: =IF(AND($H34<=AB$6+6,$I34>=AB$6),1,"") | AC34: =IF(AND($H34<=AC$6+6,$I34>=AC$6),1,"") | ... AP34: =IF(AND($H34<=AP$6+6,$I34>=AP$6),1,"")
A35: 3.3 | B35: 2 | C35: Develop application discovery and status-query tools | D35: Read-only tool set | E35: Backend / MCP Engineer | F35: 3.2 | G35: 3 | H35: =WORKDAY(MAX($I$34),1,Holidays) -> 46384 | I35: =WORKDAY(H35,G35-1,Holidays) -> 46386 | J35: =IF(StatusDate<H35,0,MIN(1,NETWORKDAYS(H35,StatusDate,Holidays)/G35)) -> 1 | K35: 1 | L35: =K35-J35 -> 0 | M35: =IF(K35>=1,"Complete",IF(StatusDate>I35,"Overdue",IF(K35>0,IF(K35<J35-0.1,"Behind","In Progress"),IF(StatusDate>H35,"Late Start","Not Started")))) -> Complete | N35: 2 | O35: =G35*N35 -> 6 | P35: =O35*BlendedRate -> 1.92 | Q35: =P35*J35 -> 1.92 | R35: =P35*K35 -> 1.92 | S35: 2 | T35: ="S"&(INT((H35-ProjectStart)/SprintLen)+1) -> S6 | V35: =IF(AND($H35<=V$6+6,$I35>=V$6),1,"") | W35: =IF(AND($H35<=W$6+6,$I35>=W$6),1,"") | X35: =IF(AND($H35<=X$6+6,$I35>=X$6),1,"") | Y35: =IF(AND($H35<=Y$6+6,$I35>=Y$6),1,"") | Z35: =IF(AND($H35<=Z$6+6,$I35>=Z$6),1,"") | AA35: =IF(AND($H35<=AA$6+6,$I35>=AA$6),1,"") | AB35: =IF(AND($H35<=AB$6+6,$I35>=AB$6),1,"") | AC35: =IF(AND($H35<=AC$6+6,$I35>=AC$6),1,"") | ... AP35: =IF(AND($H35<=AP$6+6,$I35>=AP$6),1,"")
A36: 3.4 | B36: 2 | C36: Integrate SAP through approved APIs or connectors | D36: SAP integration proof of concept | E36: Backend / MCP Engineer / SAP SME | F36: 3.2 | G36: 4 | H36: =WORKDAY(MAX($I$34),1,Holidays) -> 46384 | I36: =WORKDAY(H36,G36-1,Holidays) -> 46387 | J36: =IF(StatusDate<H36,0,MIN(1,NETWORKDAYS(H36,StatusDate,Holidays)/G36)) -> 1 | K36: 1 | L36: =K36-J36 -> 0 | M36: =IF(K36>=1,"Complete",IF(StatusDate>I36,"Overdue",IF(K36>0,IF(K36<J36-0.1,"Behind","In Progress"),IF(StatusDate>H36,"Late Start","Not Started")))) -> Complete | N36: 3 | O36: =G36*N36 -> 12 | P36: =O36*BlendedRate -> 3.84 | Q36: =P36*J36 -> 3.84 | R36: =P36*K36 -> 3.84 | S36: 4.53 | T36: ="S"&(INT((H36-ProjectStart)/SprintLen)+1) -> S6 | V36: =IF(AND($H36<=V$6+6,$I36>=V$6),1,"") | W36: =IF(AND($H36<=W$6+6,$I36>=W$6),1,"") | X36: =IF(AND($H36<=X$6+6,$I36>=X$6),1,"") | Y36: =IF(AND($H36<=Y$6+6,$I36>=Y$6),1,"") | Z36: =IF(AND($H36<=Z$6+6,$I36>=Z$6),1,"") | AA36: =IF(AND($H36<=AA$6+6,$I36>=AA$6),1,"") | AB36: =IF(AND($H36<=AB$6+6,$I36>=AB$6),1,"") | AC36: =IF(AND($H36<=AC$6+6,$I36>=AC$6),1,"") | ... AP36: =IF(AND($H36<=AP$6+6,$I36>=AP$6),1,"")
A37: 3.5 | B37: 2 | C37: Integrate Oracle through approved APIs or connectors | D37: Oracle integration proof of concept | E37: Backend / MCP Engineer / Oracle SME | F37: 3.2 | G37: 4 | H37: =WORKDAY(MAX($I$34),1,Holidays) -> 46384 | I37: =WORKDAY(H37,G37-1,Holidays) -> 46387 | J37: =IF(StatusDate<H37,0,MIN(1,NETWORKDAYS(H37,StatusDate,Holidays)/G37)) -> 1 | K37: 0.7 | L37: =K37-J37 -> -0.3 | M37: =IF(K37>=1,"Complete",IF(StatusDate>I37,"Overdue",IF(K37>0,IF(K37<J37-0.1,"Behind","In Progress"),IF(StatusDate>H37,"Late Start","Not Started")))) -> Overdue | N37: 3 | O37: =G37*N37 -> 12 | P37: =O37*BlendedRate -> 3.84 | Q37: =P37*J37 -> 3.84 | R37: =P37*K37 -> 2.688 | S37: 3.63 | T37: ="S"&(INT((H37-ProjectStart)/SprintLen)+1) -> S6 | V37: =IF(AND($H37<=V$6+6,$I37>=V$6),1,"") | W37: =IF(AND($H37<=W$6+6,$I37>=W$6),1,"") | X37: =IF(AND($H37<=X$6+6,$I37>=X$6),1,"") | Y37: =IF(AND($H37<=Y$6+6,$I37>=Y$6),1,"") | Z37: =IF(AND($H37<=Z$6+6,$I37>=Z$6),1,"") | AA37: =IF(AND($H37<=AA$6+6,$I37>=AA$6),1,"") | AB37: =IF(AND($H37<=AB$6+6,$I37>=AB$6),1,"") | AC37: =IF(AND($H37<=AC$6+6,$I37>=AC$6),1,"") | ... AP37: =IF(AND($H37<=AP$6+6,$I37>=AP$6),1,"")
A38: 3.6 | B38: 2 | C38: Integrate QA and testing application interfaces | D38: QA/testing connector | E38: Backend / MCP Engineer / QA SME | F38: 3.2 | G38: 4 | H38: =WORKDAY(MAX($I$34),1,Holidays) -> 46384 | I38: =WORKDAY(H38,G38-1,Holidays) -> 46387 | J38: =IF(StatusDate<H38,0,MIN(1,NETWORKDAYS(H38,StatusDate,Holidays)/G38)) -> 1 | K38: 1 | L38: =K38-J38 -> 0 | M38: =IF(K38>=1,"Complete",IF(StatusDate>I38,"Overdue",IF(K38>0,IF(K38<J38-0.1,"Behind","In Progress"),IF(StatusDate>H38,"Late Start","Not Started")))) -> Complete | N38: 2 | O38: =G38*N38 -> 8 | P38: =O38*BlendedRate -> 2.56 | Q38: =P38*J38 -> 2.56 | R38: =P38*K38 -> 2.56 | S38: 2.66 | T38: ="S"&(INT((H38-ProjectStart)/SprintLen)+1) -> S6 | V38: =IF(AND($H38<=V$6+6,$I38>=V$6),1,"") | W38: =IF(AND($H38<=W$6+6,$I38>=W$6),1,"") | X38: =IF(AND($H38<=X$6+6,$I38>=X$6),1,"") | Y38: =IF(AND($H38<=Y$6+6,$I38>=Y$6),1,"") | Z38: =IF(AND($H38<=Z$6+6,$I38>=Z$6),1,"") | AA38: =IF(AND($H38<=AA$6+6,$I38>=AA$6),1,"") | AB38: =IF(AND($H38<=AB$6+6,$I38>=AB$6),1,"") | AC38: =IF(AND($H38<=AC$6+6,$I38>=AC$6),1,"") | ... AP38: =IF(AND($H38<=AP$6+6,$I38>=AP$6),1,"")
A39: 3.7 | B39: 2 | C39: Implement tool selection and parameter validation | D39: Tool-routing workflow | E39: AI / RAG Engineer | F39: 3.3 | G39: 3 | H39: =WORKDAY(MAX($I$35),1,Holidays) -> 46387 | I39: =WORKDAY(H39,G39-1,Holidays) -> 46392 | J39: =IF(StatusDate<H39,0,MIN(1,NETWORKDAYS(H39,StatusDate,Holidays)/G39)) -> 1 | K39: 1 | L39: =K39-J39 -> 0 | M39: =IF(K39>=1,"Complete",IF(StatusDate>I39,"Overdue",IF(K39>0,IF(K39<J39-0.1,"Behind","In Progress"),IF(StatusDate>H39,"Late Start","Not Started")))) -> Complete | N39: 2 | O39: =G39*N39 -> 6 | P39: =O39*BlendedRate -> 1.92 | Q39: =P39*J39 -> 1.92 | R39: =P39*K39 -> 1.92 | S39: 2 | T39: ="S"&(INT((H39-ProjectStart)/SprintLen)+1) -> S6 | V39: =IF(AND($H39<=V$6+6,$I39>=V$6),1,"") | W39: =IF(AND($H39<=W$6+6,$I39>=W$6),1,"") | X39: =IF(AND($H39<=X$6+6,$I39>=X$6),1,"") | Y39: =IF(AND($H39<=Y$6+6,$I39>=Y$6),1,"") | Z39: =IF(AND($H39<=Z$6+6,$I39>=Z$6),1,"") | AA39: =IF(AND($H39<=AA$6+6,$I39>=AA$6),1,"") | AB39: =IF(AND($H39<=AB$6+6,$I39>=AB$6),1,"") | AC39: =IF(AND($H39<=AC$6+6,$I39>=AC$6),1,"") | ... AP39: =IF(AND($H39<=AP$6+6,$I39>=AP$6),1,"")
A40: 3.8 | B40: 2 | C40: Add permission checks, timeouts, retries and error responses | D40: Resilient integration layer | E40: Backend / MCP Engineer | F40: 3.4, 3.5, 3.6 | G40: 3 | H40: =WORKDAY(MAX($I$36,$I$37,$I$38),1,Holidays) -> 46391 | I40: =WORKDAY(H40,G40-1,Holidays) -> 46393 | J40: =IF(StatusDate<H40,0,MIN(1,NETWORKDAYS(H40,StatusDate,Holidays)/G40)) -> 1 | K40: 0.6 | L40: =K40-J40 -> -0.4 | M40: =IF(K40>=1,"Complete",IF(StatusDate>I40,"Overdue",IF(K40>0,IF(K40<J40-0.1,"Behind","In Progress"),IF(StatusDate>H40,"Late Start","Not Started")))) -> Overdue | N40: 2 | O40: =G40*N40 -> 6 | P40: =O40*BlendedRate -> 1.92 | Q40: =P40*J40 -> 1.92 | R40: =P40*K40 -> 1.152 | S40: 1.2 | T40: ="S"&(INT((H40-ProjectStart)/SprintLen)+1) -> S6 | V40: =IF(AND($H40<=V$6+6,$I40>=V$6),1,"") | W40: =IF(AND($H40<=W$6+6,$I40>=W$6),1,"") | X40: =IF(AND($H40<=X$6+6,$I40>=X$6),1,"") | Y40: =IF(AND($H40<=Y$6+6,$I40>=Y$6),1,"") | Z40: =IF(AND($H40<=Z$6+6,$I40>=Z$6),1,"") | AA40: =IF(AND($H40<=AA$6+6,$I40>=AA$6),1,"") | AB40: =IF(AND($H40<=AB$6+6,$I40>=AB$6),1,"") | AC40: =IF(AND($H40<=AC$6+6,$I40>=AC$6),1,"") | ... AP40: =IF(AND($H40<=AP$6+6,$I40>=AP$6),1,"")
A41: 3.9 | B41: 2 | C41: Test retrieval-plus-tool workflows end to end | D41: Integration test report | E41: QA Engineer | F41: 3.7, 3.8 | G41: 3 | H41: =WORKDAY(MAX($I$39,$I$40),1,Holidays) -> 46394 | I41: =WORKDAY(H41,G41-1,Holidays) -> 46398 | J41: =IF(StatusDate<H41,0,MIN(1,NETWORKDAYS(H41,StatusDate,Holidays)/G41)) -> 1 | K41: 0.5 | L41: =K41-J41 -> -0.5 | M41: =IF(K41>=1,"Complete",IF(StatusDate>I41,"Overdue",IF(K41>0,IF(K41<J41-0.1,"Behind","In Progress"),IF(StatusDate>H41,"Late Start","Not Started")))) -> Overdue | N41: 3 | O41: =G41*N41 -> 9 | P41: =O41*BlendedRate -> 2.88 | Q41: =P41*J41 -> 2.88 | R41: =P41*K41 -> 1.44 | S41: 1.5 | T41: ="S"&(INT((H41-ProjectStart)/SprintLen)+1) -> S6 | V41: =IF(AND($H41<=V$6+6,$I41>=V$6),1,"") | W41: =IF(AND($H41<=W$6+6,$I41>=W$6),1,"") | X41: =IF(AND($H41<=X$6+6,$I41>=X$6),1,"") | Y41: =IF(AND($H41<=Y$6+6,$I41>=Y$6),1,"") | Z41: =IF(AND($H41<=Z$6+6,$I41>=Z$6),1,"") | AA41: =IF(AND($H41<=AA$6+6,$I41>=AA$6),1,"") | AB41: =IF(AND($H41<=AB$6+6,$I41>=AB$6),1,"") | AC41: =IF(AND($H41<=AC$6+6,$I41>=AC$6),1,"") | ... AP41: =IF(AND($H41<=AP$6+6,$I41>=AP$6),1,"")
A42: 3.10 | B42: 2 | C42: Add traceable tool execution summaries | D42: Tool audit records | E42: Backend / MCP Engineer | F42: 3.9 | G42: 1 | H42: =WORKDAY(MAX($I$41),1,Holidays) -> 46399 | I42: =WORKDAY(H42,G42-1,Holidays) -> 46399 | J42: =IF(StatusDate<H42,0,MIN(1,NETWORKDAYS(H42,StatusDate,Holidays)/G42)) -> 1 | K42: 0 | L42: =K42-J42 -> -1 | M42: =IF(K42>=1,"Complete",IF(StatusDate>I42,"Overdue",IF(K42>0,IF(K42<J42-0.1,"Behind","In Progress"),IF(StatusDate>H42,"Late Start","Not Started")))) -> Overdue | N42: 1 | O42: =G42*N42 -> 1 | P42: =O42*BlendedRate -> 0.32 | Q42: =P42*J42 -> 0.32 | R42: =P42*K42 -> 0 | S42: 0 | T42: ="S"&(INT((H42-ProjectStart)/SprintLen)+1) -> S7 | V42: =IF(AND($H42<=V$6+6,$I42>=V$6),1,"") | W42: =IF(AND($H42<=W$6+6,$I42>=W$6),1,"") | X42: =IF(AND($H42<=X$6+6,$I42>=X$6),1,"") | Y42: =IF(AND($H42<=Y$6+6,$I42>=Y$6),1,"") | Z42: =IF(AND($H42<=Z$6+6,$I42>=Z$6),1,"") | AA42: =IF(AND($H42<=AA$6+6,$I42>=AA$6),1,"") | AB42: =IF(AND($H42<=AB$6+6,$I42>=AB$6),1,"") | AC42: =IF(AND($H42<=AC$6+6,$I42>=AC$6),1,"") | ... AP42: =IF(AND($H42<=AP$6+6,$I42>=AP$6),1,"")
A43: M3 | B43: 2 | C43: ◆ Milestone M3 — Application integrations | D43: Demonstrable end-to-end test workflows | E43: Project Manager / Sponsor | F43: End of Week 12 | G43: 0 | H43: =I43 -> 46401 | I43: =WORKDAY(ProjectStart-1,60,Holidays) -> 46401 | J43: =IF(StatusDate>=I43,1,0) -> 1 | K43: 0 | L43: =K43-J43 -> -1 | M43: =IF(K43>=1,"Complete",IF(StatusDate>I43,"Overdue",IF(K43>0,IF(K43<J43-0.1,"Behind","In Progress"),IF(StatusDate>H43,"Late Start","Not Started")))) -> Overdue | T43: ="S"&(INT((H43-ProjectStart)/SprintLen)+1) -> S7 | U43: Gate: all phase deliverables complete before sign-off | V43: =IF(AND($I43>=V$6,$I43<=V$6+6),"◆","") | W43: =IF(AND($I43>=W$6,$I43<=W$6+6),"◆","") | X43: =IF(AND($I43>=X$6,$I43<=X$6+6),"◆","") | Y43: =IF(AND($I43>=Y$6,$I43<=Y$6+6),"◆","") | Z43: =IF(AND($I43>=Z$6,$I43<=Z$6+6),"◆","") | AA43: =IF(AND($I43>=AA$6,$I43<=AA$6+6),"◆","") | AB43: =IF(AND($I43>=AB$6,$I43<=AB$6+6),"◆","") | AC43: =IF(AND($I43>=AC$6,$I43<=AC$6+6),"◆","") | ... AP43: =IF(AND($I43>=AP$6,$I43<=AP$6+6),"◆","")
A44: 4 | B44: 1 | C44: Month 4 — Security, Testing & Quality | D44: Milestone M4: Release candidate | E44: Project Manager | G44: =NETWORKDAYS(H44,I44,Holidays) -> 20 | H44: =MIN(H45:H55) -> 46402 | I44: =MAX(I45:I55) -> 46430 | J44: =IF(P44=0,0,Q44/P44) -> 0.081081081 | K44: =IF(P44=0,0,R44/P44) -> 0.091891892 | L44: =K44-J44 -> 0.010810811 | M44: =IF(K44>=1,"Complete",IF(StatusDate>I44,"Overdue",IF(K44>0,IF(K44<J44-0.1,"Behind","In Progress"),IF(StatusDate>H44,"Late Start","Not Started")))) -> In Progress | N44: =MAX(N45:N55) -> 4 | O44: =SUM(O45:O55) -> 74 | P44: =SUM(P45:P55) -> 23.68 | Q44: =SUM(Q45:Q55) -> 1.92 | R44: =SUM(R45:R55) -> 2.176 | S44: =SUM(S45:S55) -> 2.18 | U44: Exit: Critical security and functional defects are resolved, agreed evaluation thresholds are met, and release risks are documented. | V44: =IF(AND($H44<=V$6+6,$I44>=V$6),1,"") | W44: =IF(AND($H44<=W$6+6,$I44>=W$6),1,"") | X44: =IF(AND($H44<=X$6+6,$I44>=X$6),1,"") | Y44: =IF(AND($H44<=Y$6+6,$I44>=Y$6),1,"") | Z44: =IF(AND($H44<=Z$6+6,$I44>=Z$6),1,"") | AA44: =IF(AND($H44<=AA$6+6,$I44>=AA$6),1,"") | AB44: =IF(AND($H44<=AB$6+6,$I44>=AB$6),1,"") | AC44: =IF(AND($H44<=AC$6+6,$I44>=AC$6),1,"") | ... AP44: =IF(AND($H44<=AP$6+6,$I44>=AP$6),1,"")
A45: 4.1 | B45: 2 | C45: Configure Microsoft Entra ID authentication and role-based access | D45: Identity and role controls | E45: Security Engineer | F45: M3 | G45: 3 | H45: =WORKDAY(MAX($I$43),1,Holidays) -> 46402 | I45: =WORKDAY(H45,G45-1,Holidays) -> 46406 | J45: =IF(StatusDate<H45,0,MIN(1,NETWORKDAYS(H45,StatusDate,Holidays)/G45)) -> 0.33333333 | K45: 0.3 | L45: =K45-J45 -> -0.033333333 | M45: =IF(K45>=1,"Complete",IF(StatusDate>I45,"Overdue",IF(K45>0,IF(K45<J45-0.1,"Behind","In Progress"),IF(StatusDate>H45,"Late Start","Not Started")))) -> In Progress | N45: 2 | O45: =G45*N45 -> 6 | P45: =O45*BlendedRate -> 1.92 | Q45: =P45*J45 -> 0.64 | R45: =P45*K45 -> 0.576 | S45: 0.58 | T45: ="S"&(INT((H45-ProjectStart)/SprintLen)+1) -> S7 | V45: =IF(AND($H45<=V$6+6,$I45>=V$6),1,"") | W45: =IF(AND($H45<=W$6+6,$I45>=W$6),1,"") | X45: =IF(AND($H45<=X$6+6,$I45>=X$6),1,"") | Y45: =IF(AND($H45<=Y$6+6,$I45>=Y$6),1,"") | Z45: =IF(AND($H45<=Z$6+6,$I45>=Z$6),1,"") | AA45: =IF(AND($H45<=AA$6+6,$I45>=AA$6),1,"") | AB45: =IF(AND($H45<=AB$6+6,$I45>=AB$6),1,"") | AC45: =IF(AND($H45<=AC$6+6,$I45>=AC$6),1,"") | ... AP45: =IF(AND($H45<=AP$6+6,$I45>=AP$6),1,"")
A46: 4.2 | B46: 2 | C46: Configure secrets management and secure configuration | D46: Secrets-management setup | E46: DevOps Engineer | F46: M3 | G46: 2 | H46: =WORKDAY(MAX($I$43),1,Holidays) -> 46402 | I46: =WORKDAY(H46,G46-1,Holidays) -> 46405 | J46: =IF(StatusDate<H46,0,MIN(1,NETWORKDAYS(H46,StatusDate,Holidays)/G46)) -> 0.5 | K46: 1 | L46: =K46-J46 -> 0.5 | M46: =IF(K46>=1,"Complete",IF(StatusDate>I46,"Overdue",IF(K46>0,IF(K46<J46-0.1,"Behind","In Progress"),IF(StatusDate>H46,"Late Start","Not Started")))) -> Complete | N46: 1 | O46: =G46*N46 -> 2 | P46: =O46*BlendedRate -> 0.64 | Q46: =P46*J46 -> 0.32 | R46: =P46*K46 -> 0.64 | S46: 0.64 | T46: ="S"&(INT((H46-ProjectStart)/SprintLen)+1) -> S7 | V46: =IF(AND($H46<=V$6+6,$I46>=V$6),1,"") | W46: =IF(AND($H46<=W$6+6,$I46>=W$6),1,"") | X46: =IF(AND($H46<=X$6+6,$I46>=X$6),1,"") | Y46: =IF(AND($H46<=Y$6+6,$I46>=Y$6),1,"") | Z46: =IF(AND($H46<=Z$6+6,$I46>=Z$6),1,"") | AA46: =IF(AND($H46<=AA$6+6,$I46>=AA$6),1,"") | AB46: =IF(AND($H46<=AB$6+6,$I46>=AB$6),1,"") | AC46: =IF(AND($H46<=AC$6+6,$I46>=AC$6),1,"") | ... AP46: =IF(AND($H46<=AP$6+6,$I46>=AP$6),1,"")
A47: 4.3 | B47: 2 | C47: Enforce source-level and application-level authorization | D47: Access-control validation | E47: Security Engineer / Backend Engineer | F47: 4.1 | G47: 4 | H47: =WORKDAY(MAX($I$45),1,Holidays) -> 46407 | I47: =WORKDAY(H47,G47-1,Holidays) -> 46412 | J47: =IF(StatusDate<H47,0,MIN(1,NETWORKDAYS(H47,StatusDate,Holidays)/G47)) -> 0 | K47: 0 | L47: =K47-J47 -> 0 | M47: =IF(K47>=1,"Complete",IF(StatusDate>I47,"Overdue",IF(K47>0,IF(K47<J47-0.1,"Behind","In Progress"),IF(StatusDate>H47,"Late Start","Not Started")))) -> Not Started | N47: 2 | O47: =G47*N47 -> 8 | P47: =O47*BlendedRate -> 2.56 | Q47: =P47*J47 -> 0 | R47: =P47*K47 -> 0 | S47: 0 | T47: ="S"&(INT((H47-ProjectStart)/SprintLen)+1) -> S7 | V47: =IF(AND($H47<=V$6+6,$I47>=V$6),1,"") | W47: =IF(AND($H47<=W$6+6,$I47>=W$6),1,"") | X47: =IF(AND($H47<=X$6+6,$I47>=X$6),1,"") | Y47: =IF(AND($H47<=Y$6+6,$I47>=Y$6),1,"") | Z47: =IF(AND($H47<=Z$6+6,$I47>=Z$6),1,"") | AA47: =IF(AND($H47<=AA$6+6,$I47>=AA$6),1,"") | AB47: =IF(AND($H47<=AB$6+6,$I47>=AB$6),1,"") | AC47: =IF(AND($H47<=AC$6+6,$I47>=AC$6),1,"") | ... AP47: =IF(AND($H47<=AP$6+6,$I47>=AP$6),1,"")
A48: 4.4 | B48: 2 | C48: Test prompt injection, data leakage and unsafe tool requests | D48: AI security test report | E48: Security Engineer | F48: 4.3 | G48: 3 | H48: =WORKDAY(MAX($I$47),1,Holidays) -> 46414 | I48: =WORKDAY(H48,G48-1,Holidays) -> 46416 | J48: =IF(StatusDate<H48,0,MIN(1,NETWORKDAYS(H48,StatusDate,Holidays)/G48)) -> 0 | K48: 0 | L48: =K48-J48 -> 0 | M48: =IF(K48>=1,"Complete",IF(StatusDate>I48,"Overdue",IF(K48>0,IF(K48<J48-0.1,"Behind","In Progress"),IF(StatusDate>H48,"Late Start","Not Started")))) -> Not Started | N48: 2 | O48: =G48*N48 -> 6 | P48: =O48*BlendedRate -> 1.92 | Q48: =P48*J48 -> 0 | R48: =P48*K48 -> 0 | S48: 0 | T48: ="S"&(INT((H48-ProjectStart)/SprintLen)+1) -> S8 | V48: =IF(AND($H48<=V$6+6,$I48>=V$6),1,"") | W48: =IF(AND($H48<=W$6+6,$I48>=W$6),1,"") | X48: =IF(AND($H48<=X$6+6,$I48>=X$6),1,"") | Y48: =IF(AND($H48<=Y$6+6,$I48>=Y$6),1,"") | Z48: =IF(AND($H48<=Z$6+6,$I48>=Z$6),1,"") | AA48: =IF(AND($H48<=AA$6+6,$I48>=AA$6),1,"") | AB48: =IF(AND($H48<=AB$6+6,$I48>=AB$6),1,"") | AC48: =IF(AND($H48<=AC$6+6,$I48>=AC$6),1,"") | ... AP48: =IF(AND($H48<=AP$6+6,$I48>=AP$6),1,"")
A49: 4.5 | B49: 2 | C49: Evaluate answer correctness, grounding and citation quality | D49: AI evaluation report | E49: AI / RAG Engineer / QA Engineer | F49: M3 | G49: 4 | H49: =WORKDAY(MAX($I$43),1,Holidays) -> 46402 | I49: =WORKDAY(H49,G49-1,Holidays) -> 46407 | J49: =IF(StatusDate<H49,0,MIN(1,NETWORKDAYS(H49,StatusDate,Holidays)/G49)) -> 0.25 | K49: 0.25 | L49: =K49-J49 -> 0 | M49: =IF(K49>=1,"Complete",IF(StatusDate>I49,"Overdue",IF(K49>0,IF(K49<J49-0.1,"Behind","In Progress"),IF(StatusDate>H49,"Late Start","Not Started")))) -> In Progress | N49: 3 | O49: =G49*N49 -> 12 | P49: =O49*BlendedRate -> 3.84 | Q49: =P49*J49 -> 0.96 | R49: =P49*K49 -> 0.96 | S49: 0.96 | T49: ="S"&(INT((H49-ProjectStart)/SprintLen)+1) -> S7 | V49: =IF(AND($H49<=V$6+6,$I49>=V$6),1,"") | W49: =IF(AND($H49<=W$6+6,$I49>=W$6),1,"") | X49: =IF(AND($H49<=X$6+6,$I49>=X$6),1,"") | Y49: =IF(AND($H49<=Y$6+6,$I49>=Y$6),1,"") | Z49: =IF(AND($H49<=Z$6+6,$I49>=Z$6),1,"") | AA49: =IF(AND($H49<=AA$6+6,$I49>=AA$6),1,"") | AB49: =IF(AND($H49<=AB$6+6,$I49>=AB$6),1,"") | AC49: =IF(AND($H49<=AC$6+6,$I49>=AC$6),1,"") | ... AP49: =IF(AND($H49<=AP$6+6,$I49>=AP$6),1,"")
A50: 4.6 | B50: 2 | C50: Validate QA scenarios, edge cases and negative paths | D50: Functional QA report | E50: QA Engineer | F50: 4.5 | G50: 3 | H50: =WORKDAY(MAX($I$49),1,Holidays) -> 46408 | I50: =WORKDAY(H50,G50-1,Holidays) -> 46412 | J50: =IF(StatusDate<H50,0,MIN(1,NETWORKDAYS(H50,StatusDate,Holidays)/G50)) -> 0 | K50: 0 | L50: =K50-J50 -> 0 | M50: =IF(K50>=1,"Complete",IF(StatusDate>I50,"Overdue",IF(K50>0,IF(K50<J50-0.1,"Behind","In Progress"),IF(StatusDate>H50,"Late Start","Not Started")))) -> Not Started | N50: 2 | O50: =G50*N50 -> 6 | P50: =O50*BlendedRate -> 1.92 | Q50: =P50*J50 -> 0 | R50: =P50*K50 -> 0 | S50: 0 | T50: ="S"&(INT((H50-ProjectStart)/SprintLen)+1) -> S7 | V50: =IF(AND($H50<=V$6+6,$I50>=V$6),1,"") | W50: =IF(AND($H50<=W$6+6,$I50>=W$6),1,"") | X50: =IF(AND($H50<=X$6+6,$I50>=X$6),1,"") | Y50: =IF(AND($H50<=Y$6+6,$I50>=Y$6),1,"") | Z50: =IF(AND($H50<=Z$6+6,$I50>=Z$6),1,"") | AA50: =IF(AND($H50<=AA$6+6,$I50>=AA$6),1,"") | AB50: =IF(AND($H50<=AB$6+6,$I50>=AB$6),1,"") | AC50: =IF(AND($H50<=AC$6+6,$I50>=AC$6),1,"") | ... AP50: =IF(AND($H50<=AP$6+6,$I50>=AP$6),1,"")
A51: 4.7 | B51: 2 | C51: Test regression, integration and tool-call consistency | D51: Regression suite | E51: QA Engineer | F51: 4.6 | G51: 3 | H51: =WORKDAY(MAX($I$50),1,Holidays) -> 46414 | I51: =WORKDAY(H51,G51-1,Holidays) -> 46416 | J51: =IF(StatusDate<H51,0,MIN(1,NETWORKDAYS(H51,StatusDate,Holidays)/G51)) -> 0 | K51: 0 | L51: =K51-J51 -> 0 | M51: =IF(K51>=1,"Complete",IF(StatusDate>I51,"Overdue",IF(K51>0,IF(K51<J51-0.1,"Behind","In Progress"),IF(StatusDate>H51,"Late Start","Not Started")))) -> Not Started | N51: 2 | O51: =G51*N51 -> 6 | P51: =O51*BlendedRate -> 1.92 | Q51: =P51*J51 -> 0 | R51: =P51*K51 -> 0 | S51: 0 | T51: ="S"&(INT((H51-ProjectStart)/SprintLen)+1) -> S8 | V51: =IF(AND($H51<=V$6+6,$I51>=V$6),1,"") | W51: =IF(AND($H51<=W$6+6,$I51>=W$6),1,"") | X51: =IF(AND($H51<=X$6+6,$I51>=X$6),1,"") | Y51: =IF(AND($H51<=Y$6+6,$I51>=Y$6),1,"") | Z51: =IF(AND($H51<=Z$6+6,$I51>=Z$6),1,"") | AA51: =IF(AND($H51<=AA$6+6,$I51>=AA$6),1,"") | AB51: =IF(AND($H51<=AB$6+6,$I51>=AB$6),1,"") | AC51: =IF(AND($H51<=AC$6+6,$I51>=AC$6),1,"") | ... AP51: =IF(AND($H51<=AP$6+6,$I51>=AP$6),1,"")
A52: 4.8 | B52: 2 | C52: Measure response time, concurrency and failure recovery | D52: Performance report | E52: QA Engineer / DevOps Engineer | F52: 4.7 | G52: 3 | H52: =WORKDAY(MAX($I$51),1,Holidays) -> 46419 | I52: =WORKDAY(H52,G52-1,Holidays) -> 46421 | J52: =IF(StatusDate<H52,0,MIN(1,NETWORKDAYS(H52,StatusDate,Holidays)/G52)) -> 0 | K52: 0 | L52: =K52-J52 -> 0 | M52: =IF(K52>=1,"Complete",IF(StatusDate>I52,"Overdue",IF(K52>0,IF(K52<J52-0.1,"Behind","In Progress"),IF(StatusDate>H52,"Late Start","Not Started")))) -> Not Started | N52: 2 | O52: =G52*N52 -> 6 | P52: =O52*BlendedRate -> 1.92 | Q52: =P52*J52 -> 0 | R52: =P52*K52 -> 0 | S52: 0 | T52: ="S"&(INT((H52-ProjectStart)/SprintLen)+1) -> S8 | V52: =IF(AND($H52<=V$6+6,$I52>=V$6),1,"") | W52: =IF(AND($H52<=W$6+6,$I52>=W$6),1,"") | X52: =IF(AND($H52<=X$6+6,$I52>=X$6),1,"") | Y52: =IF(AND($H52<=Y$6+6,$I52>=Y$6),1,"") | Z52: =IF(AND($H52<=Z$6+6,$I52>=Z$6),1,"") | AA52: =IF(AND($H52<=AA$6+6,$I52>=AA$6),1,"") | AB52: =IF(AND($H52<=AB$6+6,$I52>=AB$6),1,"") | AC52: =IF(AND($H52<=AC$6+6,$I52>=AC$6),1,"") | ... AP52: =IF(AND($H52<=AP$6+6,$I52>=AP$6),1,"")
A53: 4.9 | B53: 2 | C53: Implement monitoring, tracing, audit logs and alerts | D53: Observability dashboard | E53: DevOps Engineer | F53: 4.2 | G53: 3 | H53: =WORKDAY(MAX($I$46),1,Holidays) -> 46406 | I53: =WORKDAY(H53,G53-1,Holidays) -> 46408 | J53: =IF(StatusDate<H53,0,MIN(1,NETWORKDAYS(H53,StatusDate,Holidays)/G53)) -> 0 | K53: 0 | L53: =K53-J53 -> 0 | M53: =IF(K53>=1,"Complete",IF(StatusDate>I53,"Overdue",IF(K53>0,IF(K53<J53-0.1,"Behind","In Progress"),IF(StatusDate>H53,"Late Start","Not Started")))) -> Not Started | N53: 2 | O53: =G53*N53 -> 6 | P53: =O53*BlendedRate -> 1.92 | Q53: =P53*J53 -> 0 | R53: =P53*K53 -> 0 | S53: 0 | T53: ="S"&(INT((H53-ProjectStart)/SprintLen)+1) -> S7 | V53: =IF(AND($H53<=V$6+6,$I53>=V$6),1,"") | W53: =IF(AND($H53<=W$6+6,$I53>=W$6),1,"") | X53: =IF(AND($H53<=X$6+6,$I53>=X$6),1,"") | Y53: =IF(AND($H53<=Y$6+6,$I53>=Y$6),1,"") | Z53: =IF(AND($H53<=Z$6+6,$I53>=Z$6),1,"") | AA53: =IF(AND($H53<=AA$6+6,$I53>=AA$6),1,"") | AB53: =IF(AND($H53<=AB$6+6,$I53>=AB$6),1,"") | AC53: =IF(AND($H53<=AC$6+6,$I53>=AC$6),1,"") | ... AP53: =IF(AND($H53<=AP$6+6,$I53>=AP$6),1,"")
A54: 4.10 | B54: 2 | C54: Resolve defects and prepare the release candidate | D54: Release candidate | E54: Engineering Team | F54: 4.4, 4.8, 4.9 | G54: 4 | H54: =WORKDAY(MAX($I$48,$I$52,$I$53),1,Holidays) -> 46422 | I54: =WORKDAY(H54,G54-1,Holidays) -> 46427 | J54: =IF(StatusDate<H54,0,MIN(1,NETWORKDAYS(H54,StatusDate,Holidays)/G54)) -> 0 | K54: 0 | L54: =K54-J54 -> 0 | M54: =IF(K54>=1,"Complete",IF(StatusDate>I54,"Overdue",IF(K54>0,IF(K54<J54-0.1,"Behind","In Progress"),IF(StatusDate>H54,"Late Start","Not Started")))) -> Not Started | N54: 4 | O54: =G54*N54 -> 16 | P54: =O54*BlendedRate -> 5.12 | Q54: =P54*J54 -> 0 | R54: =P54*K54 -> 0 | S54: 0 | T54: ="S"&(INT((H54-ProjectStart)/SprintLen)+1) -> S8 | V54: =IF(AND($H54<=V$6+6,$I54>=V$6),1,"") | W54: =IF(AND($H54<=W$6+6,$I54>=W$6),1,"") | X54: =IF(AND($H54<=X$6+6,$I54>=X$6),1,"") | Y54: =IF(AND($H54<=Y$6+6,$I54>=Y$6),1,"") | Z54: =IF(AND($H54<=Z$6+6,$I54>=Z$6),1,"") | AA54: =IF(AND($H54<=AA$6+6,$I54>=AA$6),1,"") | AB54: =IF(AND($H54<=AB$6+6,$I54>=AB$6),1,"") | AC54: =IF(AND($H54<=AC$6+6,$I54>=AC$6),1,"") | ... AP54: =IF(AND($H54<=AP$6+6,$I54>=AP$6),1,"")
A55: M4 | B55: 2 | C55: ◆ Milestone M4 — Release candidate | D55: Security, QA and evaluation reports | E55: Project Manager / Sponsor | F55: End of Week 16 | G55: 0 | H55: =I55 -> 46430 | I55: =WORKDAY(ProjectStart-1,80,Holidays) -> 46430 | J55: =IF(StatusDate>=I55,1,0) -> 0 | K55: 0 | L55: =K55-J55 -> 0 | M55: =IF(K55>=1,"Complete",IF(StatusDate>I55,"Overdue",IF(K55>0,IF(K55<J55-0.1,"Behind","In Progress"),IF(StatusDate>H55,"Late Start","Not Started")))) -> Not Started | T55: ="S"&(INT((H55-ProjectStart)/SprintLen)+1) -> S9 | U55: Gate: all phase deliverables complete before sign-off | V55: =IF(AND($I55>=V$6,$I55<=V$6+6),"◆","") | W55: =IF(AND($I55>=W$6,$I55<=W$6+6),"◆","") | X55: =IF(AND($I55>=X$6,$I55<=X$6+6),"◆","") | Y55: =IF(AND($I55>=Y$6,$I55<=Y$6+6),"◆","") | Z55: =IF(AND($I55>=Z$6,$I55<=Z$6+6),"◆","") | AA55: =IF(AND($I55>=AA$6,$I55<=AA$6+6),"◆","") | AB55: =IF(AND($I55>=AB$6,$I55<=AB$6+6),"◆","") | AC55: =IF(AND($I55>=AC$6,$I55<=AC$6+6),"◆","") | ... AP55: =IF(AND($I55>=AP$6,$I55<=AP$6+6),"◆","")
A56: 5 | B56: 1 | C56: Month 5 — UAT, Pilot, Deployment & Handover | D56: Milestone M5: Pilot accepted | E56: Project Manager | G56: =NETWORKDAYS(H56,I56,Holidays) -> 20 | H56: =MIN(H57:H68) -> 46433 | I56: =MAX(I57:I68) -> 46458 | J56: =IF(P56=0,0,Q56/P56) -> 0 | K56: =IF(P56=0,0,R56/P56) -> 0 | L56: =K56-J56 -> 0 | M56: =IF(K56>=1,"Complete",IF(StatusDate>I56,"Overdue",IF(K56>0,IF(K56<J56-0.1,"Behind","In Progress"),IF(StatusDate>H56,"Late Start","Not Started")))) -> Not Started | N56: =MAX(N57:N68) -> 4 | O56: =SUM(O57:O68) -> 75 | P56: =SUM(P57:P68) -> 24 | Q56: =SUM(Q57:Q68) -> 0 | R56: =SUM(R57:R68) -> 0 | S56: =SUM(S57:S68) -> 0 | U56: Exit: Business stakeholders accept the pilot results, operational ownership is assigned, and production deployment is approved or has a documented readiness decision. | V56: =IF(AND($H56<=V$6+6,$I56>=V$6),1,"") | W56: =IF(AND($H56<=W$6+6,$I56>=W$6),1,"") | X56: =IF(AND($H56<=X$6+6,$I56>=X$6),1,"") | Y56: =IF(AND($H56<=Y$6+6,$I56>=Y$6),1,"") | Z56: =IF(AND($H56<=Z$6+6,$I56>=Z$6),1,"") | AA56: =IF(AND($H56<=AA$6+6,$I56>=AA$6),1,"") | AB56: =IF(AND($H56<=AB$6+6,$I56>=AB$6),1,"") | AC56: =IF(AND($H56<=AC$6+6,$I56>=AC$6),1,"") | ... AP56: =IF(AND($H56<=AP$6+6,$I56>=AP$6),1,"") -> 1
A57: 5.1 | B57: 2 | C57: Prepare UAT scenarios and business acceptance criteria | D57: UAT plan | E57: Product Owner | F57: M4 | G57: 2 | H57: =WORKDAY(MAX($I$55),1,Holidays) -> 46433 | I57: =WORKDAY(H57,G57-1,Holidays) -> 46434 | J57: =IF(StatusDate<H57,0,MIN(1,NETWORKDAYS(H57,StatusDate,Holidays)/G57)) -> 0 | K57: 0 | L57: =K57-J57 -> 0 | M57: =IF(K57>=1,"Complete",IF(StatusDate>I57,"Overdue",IF(K57>0,IF(K57<J57-0.1,"Behind","In Progress"),IF(StatusDate>H57,"Late Start","Not Started")))) -> Not Started | N57: 2 | O57: =G57*N57 -> 4 | P57: =O57*BlendedRate -> 1.28 | Q57: =P57*J57 -> 0 | R57: =P57*K57 -> 0 | S57: 0 | T57: ="S"&(INT((H57-ProjectStart)/SprintLen)+1) -> S9 | V57: =IF(AND($H57<=V$6+6,$I57>=V$6),1,"") | W57: =IF(AND($H57<=W$6+6,$I57>=W$6),1,"") | X57: =IF(AND($H57<=X$6+6,$I57>=X$6),1,"") | Y57: =IF(AND($H57<=Y$6+6,$I57>=Y$6),1,"") | Z57: =IF(AND($H57<=Z$6+6,$I57>=Z$6),1,"") | AA57: =IF(AND($H57<=AA$6+6,$I57>=AA$6),1,"") | AB57: =IF(AND($H57<=AB$6+6,$I57>=AB$6),1,"") | AC57: =IF(AND($H57<=AC$6+6,$I57>=AC$6),1,"") | ... AP57: =IF(AND($H57<=AP$6+6,$I57>=AP$6),1,"")
A58: 5.2 | B58: 2 | C58: Conduct employee, QA and IT support user acceptance testing | D58: UAT results | E58: QA Engineer / Business Users | F58: 5.1 | G58: 4 | H58: =WORKDAY(MAX($I$57),1,Holidays) -> 46435 | I58: =WORKDAY(H58,G58-1,Holidays) -> 46440 | J58: =IF(StatusDate<H58,0,MIN(1,NETWORKDAYS(H58,StatusDate,Holidays)/G58)) -> 0 | K58: 0 | L58: =K58-J58 -> 0 | M58: =IF(K58>=1,"Complete",IF(StatusDate>I58,"Overdue",IF(K58>0,IF(K58<J58-0.1,"Behind","In Progress"),IF(StatusDate>H58,"Late Start","Not Started")))) -> Not Started | N58: 4 | O58: =G58*N58 -> 16 | P58: =O58*BlendedRate -> 5.12 | Q58: =P58*J58 -> 0 | R58: =P58*K58 -> 0 | S58: 0 | T58: ="S"&(INT((H58-ProjectStart)/SprintLen)+1) -> S9 | V58: =IF(AND($H58<=V$6+6,$I58>=V$6),1,"") | W58: =IF(AND($H58<=W$6+6,$I58>=W$6),1,"") | X58: =IF(AND($H58<=X$6+6,$I58>=X$6),1,"") | Y58: =IF(AND($H58<=Y$6+6,$I58>=Y$6),1,"") | Z58: =IF(AND($H58<=Z$6+6,$I58>=Z$6),1,"") | AA58: =IF(AND($H58<=AA$6+6,$I58>=AA$6),1,"") | AB58: =IF(AND($H58<=AB$6+6,$I58>=AB$6),1,"") | AC58: =IF(AND($H58<=AC$6+6,$I58>=AC$6),1,"") | ... AP58: =IF(AND($H58<=AP$6+6,$I58>=AP$6),1,"")
A59: 5.3 | B59: 2 | C59: Validate SAP, Oracle and QA workflows with system owners | D59: Business validation report | E59: App SMEs / System Owners | F59: 5.1 | G59: 3 | H59: =WORKDAY(MAX($I$57),1,Holidays) -> 46435 | I59: =WORKDAY(H59,G59-1,Holidays) -> 46437 | J59: =IF(StatusDate<H59,0,MIN(1,NETWORKDAYS(H59,StatusDate,Holidays)/G59)) -> 0 | K59: 0 | L59: =K59-J59 -> 0 | M59: =IF(K59>=1,"Complete",IF(StatusDate>I59,"Overdue",IF(K59>0,IF(K59<J59-0.1,"Behind","In Progress"),IF(StatusDate>H59,"Late Start","Not Started")))) -> Not Started | N59: 3 | O59: =G59*N59 -> 9 | P59: =O59*BlendedRate -> 2.88 | Q59: =P59*J59 -> 0 | R59: =P59*K59 -> 0 | S59: 0 | T59: ="S"&(INT((H59-ProjectStart)/SprintLen)+1) -> S9 | V59: =IF(AND($H59<=V$6+6,$I59>=V$6),1,"") | W59: =IF(AND($H59<=W$6+6,$I59>=W$6),1,"") | X59: =IF(AND($H59<=X$6+6,$I59>=X$6),1,"") | Y59: =IF(AND($H59<=Y$6+6,$I59>=Y$6),1,"") | Z59: =IF(AND($H59<=Z$6+6,$I59>=Z$6),1,"") | AA59: =IF(AND($H59<=AA$6+6,$I59>=AA$6),1,"") | AB59: =IF(AND($H59<=AB$6+6,$I59>=AB$6),1,"") | AC59: =IF(AND($H59<=AC$6+6,$I59>=AC$6),1,"") | ... AP59: =IF(AND($H59<=AP$6+6,$I59>=AP$6),1,"")
A60: 5.4 | B60: 2 | C60: Collect pilot feedback and prioritize defects | D60: Feedback backlog | E60: Product Owner | F60: 5.2, 5.3 | G60: 2 | H60: =WORKDAY(MAX($I$58,$I$59),1,Holidays) -> 46441 | I60: =WORKDAY(H60,G60-1,Holidays) -> 46442 | J60: =IF(StatusDate<H60,0,MIN(1,NETWORKDAYS(H60,StatusDate,Holidays)/G60)) -> 0 | K60: 0 | L60: =K60-J60 -> 0 | M60: =IF(K60>=1,"Complete",IF(StatusDate>I60,"Overdue",IF(K60>0,IF(K60<J60-0.1,"Behind","In Progress"),IF(StatusDate>H60,"Late Start","Not Started")))) -> Not Started | N60: 2 | O60: =G60*N60 -> 4 | P60: =O60*BlendedRate -> 1.28 | Q60: =P60*J60 -> 0 | R60: =P60*K60 -> 0 | S60: 0 | T60: ="S"&(INT((H60-ProjectStart)/SprintLen)+1) -> S10 | V60: =IF(AND($H60<=V$6+6,$I60>=V$6),1,"") | W60: =IF(AND($H60<=W$6+6,$I60>=W$6),1,"") | X60: =IF(AND($H60<=X$6+6,$I60>=X$6),1,"") | Y60: =IF(AND($H60<=Y$6+6,$I60>=Y$6),1,"") | Z60: =IF(AND($H60<=Z$6+6,$I60>=Z$6),1,"") | AA60: =IF(AND($H60<=AA$6+6,$I60>=AA$6),1,"") | AB60: =IF(AND($H60<=AB$6+6,$I60>=AB$6),1,"") | AC60: =IF(AND($H60<=AC$6+6,$I60>=AC$6),1,"") | ... AP60: =IF(AND($H60<=AP$6+6,$I60>=AP$6),1,"")
A61: 5.5 | B61: 2 | C61: Fix defects and perform final regression testing | D61: Approved build | E61: Engineering Team | F61: 5.4 | G61: 4 | H61: =WORKDAY(MAX($I$60),1,Holidays) -> 46443 | I61: =WORKDAY(H61,G61-1,Holidays) -> 46448 | J61: =IF(StatusDate<H61,0,MIN(1,NETWORKDAYS(H61,StatusDate,Holidays)/G61)) -> 0 | K61: 0 | L61: =K61-J61 -> 0 | M61: =IF(K61>=1,"Complete",IF(StatusDate>I61,"Overdue",IF(K61>0,IF(K61<J61-0.1,"Behind","In Progress"),IF(StatusDate>H61,"Late Start","Not Started")))) -> Not Started | N61: 4 | O61: =G61*N61 -> 16 | P61: =O61*BlendedRate -> 5.12 | Q61: =P61*J61 -> 0 | R61: =P61*K61 -> 0 | S61: 0 | T61: ="S"&(INT((H61-ProjectStart)/SprintLen)+1) -> S10 | V61: =IF(AND($H61<=V$6+6,$I61>=V$6),1,"") | W61: =IF(AND($H61<=W$6+6,$I61>=W$6),1,"") | X61: =IF(AND($H61<=X$6+6,$I61>=X$6),1,"") | Y61: =IF(AND($H61<=Y$6+6,$I61>=Y$6),1,"") | Z61: =IF(AND($H61<=Z$6+6,$I61>=Z$6),1,"") | AA61: =IF(AND($H61<=AA$6+6,$I61>=AA$6),1,"") | AB61: =IF(AND($H61<=AB$6+6,$I61>=AB$6),1,"") | AC61: =IF(AND($H61<=AC$6+6,$I61>=AC$6),1,"") | ... AP61: =IF(AND($H61<=AP$6+6,$I61>=AP$6),1,"")
A62: 5.6 | B62: 2 | C62: Prepare CI/CD pipeline and deployment configuration | D62: Deployment pipeline | E62: DevOps Engineer | F62: M4 | G62: 3 | H62: =WORKDAY(MAX($I$55),1,Holidays) -> 46433 | I62: =WORKDAY(H62,G62-1,Holidays) -> 46435 | J62: =IF(StatusDate<H62,0,MIN(1,NETWORKDAYS(H62,StatusDate,Holidays)/G62)) -> 0 | K62: 0 | L62: =K62-J62 -> 0 | M62: =IF(K62>=1,"Complete",IF(StatusDate>I62,"Overdue",IF(K62>0,IF(K62<J62-0.1,"Behind","In Progress"),IF(StatusDate>H62,"Late Start","Not Started")))) -> Not Started | N62: 2 | O62: =G62*N62 -> 6 | P62: =O62*BlendedRate -> 1.92 | Q62: =P62*J62 -> 0 | R62: =P62*K62 -> 0 | S62: 0 | T62: ="S"&(INT((H62-ProjectStart)/SprintLen)+1) -> S9 | V62: =IF(AND($H62<=V$6+6,$I62>=V$6),1,"") | W62: =IF(AND($H62<=W$6+6,$I62>=W$6),1,"") | X62: =IF(AND($H62<=X$6+6,$I62>=X$6),1,"") | Y62: =IF(AND($H62<=Y$6+6,$I62>=Y$6),1,"") | Z62: =IF(AND($H62<=Z$6+6,$I62>=Z$6),1,"") | AA62: =IF(AND($H62<=AA$6+6,$I62>=AA$6),1,"") | AB62: =IF(AND($H62<=AB$6+6,$I62>=AB$6),1,"") | AC62: =IF(AND($H62<=AC$6+6,$I62>=AC$6),1,"") | ... AP62: =IF(AND($H62<=AP$6+6,$I62>=AP$6),1,"")
A63: 5.7 | B63: 2 | C63: Validate environment configuration, access and rollback procedure | D63: Deployment checklist | E63: DevOps Engineer | F63: 5.5, 5.6 | G63: 2 | H63: =WORKDAY(MAX($I$61,$I$62),1,Holidays) -> 46449 | I63: =WORKDAY(H63,G63-1,Holidays) -> 46450 | J63: =IF(StatusDate<H63,0,MIN(1,NETWORKDAYS(H63,StatusDate,Holidays)/G63)) -> 0 | K63: 0 | L63: =K63-J63 -> 0 | M63: =IF(K63>=1,"Complete",IF(StatusDate>I63,"Overdue",IF(K63>0,IF(K63<J63-0.1,"Behind","In Progress"),IF(StatusDate>H63,"Late Start","Not Started")))) -> Not Started | N63: 2 | O63: =G63*N63 -> 4 | P63: =O63*BlendedRate -> 1.28 | Q63: =P63*J63 -> 0 | R63: =P63*K63 -> 0 | S63: 0 | T63: ="S"&(INT((H63-ProjectStart)/SprintLen)+1) -> S10 | V63: =IF(AND($H63<=V$6+6,$I63>=V$6),1,"") | W63: =IF(AND($H63<=W$6+6,$I63>=W$6),1,"") | X63: =IF(AND($H63<=X$6+6,$I63>=X$6),1,"") | Y63: =IF(AND($H63<=Y$6+6,$I63>=Y$6),1,"") | Z63: =IF(AND($H63<=Z$6+6,$I63>=Z$6),1,"") | AA63: =IF(AND($H63<=AA$6+6,$I63>=AA$6),1,"") | AB63: =IF(AND($H63<=AB$6+6,$I63>=AB$6),1,"") | AC63: =IF(AND($H63<=AC$6+6,$I63>=AC$6),1,"") | ... AP63: =IF(AND($H63<=AP$6+6,$I63>=AP$6),1,"")
A64: 5.8 | B64: 2 | C64: Deploy to the approved pilot environment | D64: Pilot deployment | E64: DevOps Engineer | F64: 5.7 | G64: 2 | H64: =WORKDAY(MAX($I$63),1,Holidays) -> 46451 | I64: =WORKDAY(H64,G64-1,Holidays) -> 46454 | J64: =IF(StatusDate<H64,0,MIN(1,NETWORKDAYS(H64,StatusDate,Holidays)/G64)) -> 0 | K64: 0 | L64: =K64-J64 -> 0 | M64: =IF(K64>=1,"Complete",IF(StatusDate>I64,"Overdue",IF(K64>0,IF(K64<J64-0.1,"Behind","In Progress"),IF(StatusDate>H64,"Late Start","Not Started")))) -> Not Started | N64: 2 | O64: =G64*N64 -> 4 | P64: =O64*BlendedRate -> 1.28 | Q64: =P64*J64 -> 0 | R64: =P64*K64 -> 0 | S64: 0 | T64: ="S"&(INT((H64-ProjectStart)/SprintLen)+1) -> S10 | V64: =IF(AND($H64<=V$6+6,$I64>=V$6),1,"") | W64: =IF(AND($H64<=W$6+6,$I64>=W$6),1,"") | X64: =IF(AND($H64<=X$6+6,$I64>=X$6),1,"") | Y64: =IF(AND($H64<=Y$6+6,$I64>=Y$6),1,"") | Z64: =IF(AND($H64<=Z$6+6,$I64>=Z$6),1,"") | AA64: =IF(AND($H64<=AA$6+6,$I64>=AA$6),1,"") | AB64: =IF(AND($H64<=AB$6+6,$I64>=AB$6),1,"") | AC64: =IF(AND($H64<=AC$6+6,$I64>=AC$6),1,"") | ... AP64: =IF(AND($H64<=AP$6+6,$I64>=AP$6),1,"") -> 1
A65: 5.9 | B65: 2 | C65: Conduct user onboarding and operational training | D65: User and operator guides | E65: Project Manager / Trainer | F65: 5.8 | G65: 2 | H65: =WORKDAY(MAX($I$64),1,Holidays) -> 46455 | I65: =WORKDAY(H65,G65-1,Holidays) -> 46456 | J65: =IF(StatusDate<H65,0,MIN(1,NETWORKDAYS(H65,StatusDate,Holidays)/G65)) -> 0 | K65: 0 | L65: =K65-J65 -> 0 | M65: =IF(K65>=1,"Complete",IF(StatusDate>I65,"Overdue",IF(K65>0,IF(K65<J65-0.1,"Behind","In Progress"),IF(StatusDate>H65,"Late Start","Not Started")))) -> Not Started | N65: 2 | O65: =G65*N65 -> 4 | P65: =O65*BlendedRate -> 1.28 | Q65: =P65*J65 -> 0 | R65: =P65*K65 -> 0 | S65: 0 | T65: ="S"&(INT((H65-ProjectStart)/SprintLen)+1) -> S11 | V65: =IF(AND($H65<=V$6+6,$I65>=V$6),1,"") | W65: =IF(AND($H65<=W$6+6,$I65>=W$6),1,"") | X65: =IF(AND($H65<=X$6+6,$I65>=X$6),1,"") | Y65: =IF(AND($H65<=Y$6+6,$I65>=Y$6),1,"") | Z65: =IF(AND($H65<=Z$6+6,$I65>=Z$6),1,"") | AA65: =IF(AND($H65<=AA$6+6,$I65>=AA$6),1,"") | AB65: =IF(AND($H65<=AB$6+6,$I65>=AB$6),1,"") | AC65: =IF(AND($H65<=AC$6+6,$I65>=AC$6),1,"") | ... AP65: =IF(AND($H65<=AP$6+6,$I65>=AP$6),1,"") -> 1
A66: 5.10 | B66: 2 | C66: Complete architecture, support and technical handover | D66: Handover package | E66: Solution Architect | F66: 5.8 | G66: 2 | H66: =WORKDAY(MAX($I$64),1,Holidays) -> 46455 | I66: =WORKDAY(H66,G66-1,Holidays) -> 46456 | J66: =IF(StatusDate<H66,0,MIN(1,NETWORKDAYS(H66,StatusDate,Holidays)/G66)) -> 0 | K66: 0 | L66: =K66-J66 -> 0 | M66: =IF(K66>=1,"Complete",IF(StatusDate>I66,"Overdue",IF(K66>0,IF(K66<J66-0.1,"Behind","In Progress"),IF(StatusDate>H66,"Late Start","Not Started")))) -> Not Started | N66: 2 | O66: =G66*N66 -> 4 | P66: =O66*BlendedRate -> 1.28 | Q66: =P66*J66 -> 0 | R66: =P66*K66 -> 0 | S66: 0 | T66: ="S"&(INT((H66-ProjectStart)/SprintLen)+1) -> S11 | V66: =IF(AND($H66<=V$6+6,$I66>=V$6),1,"") | W66: =IF(AND($H66<=W$6+6,$I66>=W$6),1,"") | X66: =IF(AND($H66<=X$6+6,$I66>=X$6),1,"") | Y66: =IF(AND($H66<=Y$6+6,$I66>=Y$6),1,"") | Z66: =IF(AND($H66<=Z$6+6,$I66>=Z$6),1,"") | AA66: =IF(AND($H66<=AA$6+6,$I66>=AA$6),1,"") | AB66: =IF(AND($H66<=AB$6+6,$I66>=AB$6),1,"") | AC66: =IF(AND($H66<=AC$6+6,$I66>=AC$6),1,"") | ... AP66: =IF(AND($H66<=AP$6+6,$I66>=AP$6),1,"") -> 1
A67: 5.11 | B67: 2 | C67: Review KPIs, acceptance criteria and outstanding risks | D67: Final project report | E67: Project Manager | F67: 5.9, 5.10 | G67: 2 | H67: =WORKDAY(MAX($I$65,$I$66),1,Holidays) -> 46457 | I67: =WORKDAY(H67,G67-1,Holidays) -> 46458 | J67: =IF(StatusDate<H67,0,MIN(1,NETWORKDAYS(H67,StatusDate,Holidays)/G67)) -> 0 | K67: 0 | L67: =K67-J67 -> 0 | M67: =IF(K67>=1,"Complete",IF(StatusDate>I67,"Overdue",IF(K67>0,IF(K67<J67-0.1,"Behind","In Progress"),IF(StatusDate>H67,"Late Start","Not Started")))) -> Not Started | N67: 2 | O67: =G67*N67 -> 4 | P67: =O67*BlendedRate -> 1.28 | Q67: =P67*J67 -> 0 | R67: =P67*K67 -> 0 | S67: 0 | T67: ="S"&(INT((H67-ProjectStart)/SprintLen)+1) -> S11 | V67: =IF(AND($H67<=V$6+6,$I67>=V$6),1,"") | W67: =IF(AND($H67<=W$6+6,$I67>=W$6),1,"") | X67: =IF(AND($H67<=X$6+6,$I67>=X$6),1,"") | Y67: =IF(AND($H67<=Y$6+6,$I67>=Y$6),1,"") | Z67: =IF(AND($H67<=Z$6+6,$I67>=Z$6),1,"") | AA67: =IF(AND($H67<=AA$6+6,$I67>=AA$6),1,"") | AB67: =IF(AND($H67<=AB$6+6,$I67>=AB$6),1,"") | AC67: =IF(AND($H67<=AC$6+6,$I67>=AC$6),1,"") | ... AP67: =IF(AND($H67<=AP$6+6,$I67>=AP$6),1,"") -> 1
A68: M5 | B68: 2 | C68: ◆ Milestone M5 — Pilot accepted | D68: UAT sign-off and handover | E68: Project Manager / Sponsor | F68: End of Week 20 | G68: 0 | H68: =I68 -> 46458 | I68: =WORKDAY(ProjectStart-1,100,Holidays) -> 46458 | J68: =IF(StatusDate>=I68,1,0) -> 0 | K68: 0 | L68: =K68-J68 -> 0 | M68: =IF(K68>=1,"Complete",IF(StatusDate>I68,"Overdue",IF(K68>0,IF(K68<J68-0.1,"Behind","In Progress"),IF(StatusDate>H68,"Late Start","Not Started")))) -> Not Started | T68: ="S"&(INT((H68-ProjectStart)/SprintLen)+1) -> S11 | U68: Gate: all phase deliverables complete before sign-off | V68: =IF(AND($I68>=V$6,$I68<=V$6+6),"◆","") | W68: =IF(AND($I68>=W$6,$I68<=W$6+6),"◆","") | X68: =IF(AND($I68>=X$6,$I68<=X$6+6),"◆","") | Y68: =IF(AND($I68>=Y$6,$I68<=Y$6+6),"◆","") | Z68: =IF(AND($I68>=Z$6,$I68<=Z$6+6),"◆","") | AA68: =IF(AND($I68>=AA$6,$I68<=AA$6+6),"◆","") | AB68: =IF(AND($I68>=AB$6,$I68<=AB$6+6),"◆","") | AC68: =IF(AND($I68>=AC$6,$I68<=AC$6+6),"◆","") | ... AP68: =IF(AND($I68>=AP$6,$I68<=AP$6+6),"◆","") -> ◆

Sheet Milestones
A1: Milestones & Phase Gates
A2: Baseline = end of each 4-week month · Forecast and Actual dates are inputs
A4: ID | B4: Milestone | C4: Target Week | D4: Baseline Date | E4: Forecast Date | F4: Actual Date | G4: Variance (work days) | H4: Status | I4: Acceptance Evidence | J4: Exit Criteria
A5: M1 | B5: Architecture approved | C5: Week 4 | D5: ='WBS Schedule'!I19 -> 46342 | E5: ='WBS Schedule'!I19 -> 46342 | F5: 46342 | G5: =IF(F5<>"",IF(F5>D5,NETWORKDAYS(D5,F5,Holidays)-1,-(NETWORKDAYS(F5,D5,Holidays)-1)),IF(E5>D5,NETWORKDAYS(D5,E5,Holidays)-1,-(NETWORKDAYS(E5,D5,Holidays)-1))) -> 0 | H5: =IF(F5<>"","Achieved",IF(G5>0,"At Risk",IF(StatusDate>D5,"Overdue","On Track"))) -> Achieved | I5: Signed-off requirements and design | J5: Stakeholders approve the MVP scope, architecture, security approach, initial use cases and access requirements.
A6: M2 | B6: AI assistant MVP | C6: Week 8 | D6: ='WBS Schedule'!I31 -> 46371 | E6: ='WBS Schedule'!I31 -> 46371 | F6: 46370 | G6: =IF(F6<>"",IF(F6>D6,NETWORKDAYS(D6,F6,Holidays)-1,-(NETWORKDAYS(F6,D6,Holidays)-1)),IF(E6>D6,NETWORKDAYS(D6,E6,Holidays)-1,-(NETWORKDAYS(E6,D6,Holidays)-1))) -> -1 | H6: =IF(F6<>"","Achieved",IF(G6>0,"At Risk",IF(StatusDate>D6,"Overdue","On Track"))) -> Achieved | I6: Grounded answers from approved documents | J6: A user can ask questions about approved sample documentation and receive relevant, source-grounded answers through the chat interface.
A7: M3 | B7: Application integrations | C7: Week 12 | D7: ='WBS Schedule'!I43 -> 46401 | E7: 46409 | G7: =IF(F7<>"",IF(F7>D7,NETWORKDAYS(D7,F7,Holidays)-1,-(NETWORKDAYS(F7,D7,Holidays)-1)),IF(E7>D7,NETWORKDAYS(D7,E7,Holidays)-1,-(NETWORKDAYS(E7,D7,Holidays)-1))) -> 6 | H7: =IF(F7<>"","Achieved",IF(G7>0,"At Risk",IF(StatusDate>D7,"Overdue","On Track"))) -> At Risk | I7: Demonstrable end-to-end test workflows | J7: The assistant answers knowledge questions and executes approved, read-only operations against available test integrations (SAP/Oracle scope subject to API access, licensing and environment readiness).
A8: M4 | B8: Release candidate | C8: Week 16 | D8: ='WBS Schedule'!I55 -> 46430 | E8: 46434 | G8: =IF(F8<>"",IF(F8>D8,NETWORKDAYS(D8,F8,Holidays)-1,-(NETWORKDAYS(F8,D8,Holidays)-1)),IF(E8>D8,NETWORKDAYS(D8,E8,Holidays)-1,-(NETWORKDAYS(E8,D8,Holidays)-1))) -> 2 | H8: =IF(F8<>"","Achieved",IF(G8>0,"At Risk",IF(StatusDate>D8,"Overdue","On Track"))) -> At Risk | I8: Security, QA and evaluation reports | J8: Critical security and functional defects are resolved, agreed evaluation thresholds are met, and release risks are documented.
A9: M5 | B9: Pilot accepted | C9: Week 20 | D9: ='WBS Schedule'!I68 -> 46458 | E9: 46458 | G9: =IF(F9<>"",IF(F9>D9,NETWORKDAYS(D9,F9,Holidays)-1,-(NETWORKDAYS(F9,D9,Holidays)-1)),IF(E9>D9,NETWORKDAYS(D9,E9,Holidays)-1,-(NETWORKDAYS(E9,D9,Holidays)-1))) -> 0 | H9: =IF(F9<>"","Achieved",IF(G9>0,"At Risk",IF(StatusDate>D9,"Overdue","On Track"))) -> On Track | I9: UAT sign-off and handover | J9: Business stakeholders accept the pilot results, operational ownership is assigned, and production deployment is approved or has a documented readiness decision.

Sheet Team & Resources
A1: Team Structure & Resourcing
A2: Blue values are editable · Cost = Headcount × Allocation × Rate × Working days
A4: Role | B4: Named Resources (demo) | C4: Headcount | D4: Allocation (FTE %) | E4: Day Rate (₹ L) | F4: Effective FTE | G4: Cost over Project (₹ L) | H4: Responsibilities
A5: Project Manager / Product Owner | B5: Ananya Rao; Vikram Desai | C5: 2 | D5: 1 | E5: 0.42 | F5: =C5*D5 -> 2 | G5: =F5*E5*'WBS Schedule'!$G$7 -> 84 | H5: Scope, priorities, stakeholders, risks and acceptance
A6: Solution Architect | B6: Karthik Iyer | C6: 1 | D6: 0.6 | E6: 0.45 | F6: =C6*D6 -> 0.6 | G6: =F6*E6*'WBS Schedule'!$G$7 -> 27 | H6: Architecture decisions, integration contracts, handover
A7: AI / RAG Engineer | B7: Priya Nair; Arjun Mehta | C7: 2 | D7: 1 | E7: 0.36 | F7: =C7*D7 -> 2 | G7: =F7*E7*'WBS Schedule'!$G$7 -> 72 | H7: GPT-5, Foundry IQ, prompts, retrieval and evaluation
A8: Backend / MCP Engineer | B8: Rohan Kulkarni; Sneha Joshi | C8: 2 | D8: 1 | E8: 0.32 | F8: =C8*D8 -> 2 | G8: =F8*E8*'WBS Schedule'!$G$7 -> 64 | H8: MCP tools, APIs, application connectors and orchestration
A9: Frontend Engineer | B9: Meera Pillai | C9: 1 | D9: 1 | E9: 0.28 | F9: =C9*D9 -> 1 | G9: =F9*E9*'WBS Schedule'!$G$7 -> 28 | H9: Chat UI, application dashboard and user experience
A10: QA Engineer | B10: Divya Shetty | C10: 1 | D10: 1 | E10: 0.26 | F10: =C10*D10 -> 1 | G10: =F10*E10*'WBS Schedule'!$G$7 -> 26 | H10: Test strategy, evaluation datasets, regression and UAT support
A11: Security Engineer | B11: Aditya Bose | C11: 1 | D11: 0.5 | E11: 0.38 | F11: =C11*D11 -> 0.5 | G11: =F11*E11*'WBS Schedule'!$G$7 -> 19 | H11: Entra ID, authorization, AI security testing
A12: DevOps Engineer | B12: Farhan Qureshi | C12: 1 | D12: 0.8 | E12: 0.3 | F12: =C12*D12 -> 0.8 | G12: =F12*E12*'WBS Schedule'!$G$7 -> 24 | H12: Azure provisioning, CI/CD, observability
A13: SAP / Oracle / QA Application SMEs | B13: SAP CoE; Oracle DBA team; QA tooling owners | C13: 3 | D13: 0.25 | E13: 0.35 | F13: =C13*D13 -> 0.75 | G13: =F13*E13*'WBS Schedule'!$G$7 -> 26.25 | H13: Use cases, API access, business validation
A14: Total | C14: =SUM(C5:C13) -> 14 | F14: =SUM(F5:F13) -> 10.65 | G14: =SUM(G5:G13) -> 370.25 | H14: Core team of ~10 named members plus shared SMEs (source plan: 7–10 core)

Sheet Workstreams
A1: Cross-Functional Workstreams
A2: Activities that span multiple phases; Start/End week are inputs
A4: Workstream | B4: Lead | C4: Start Week | D4: End Week | E4: Key Outputs | F4: W1 | G4: W2 | H4: W3 | I4: W4 | J4: W5 | K4: W6 | L4: W7 | M4: W8 | N4: W9 | O4: W10 | P4: W11 | Q4: W12 | R4: W13 | S4: W14 | T4: W15 | U4: W16 | V4: W17 | W4: W18 | X4: W19 | Y4: W20 | Z4: W21
A5: Project management | B5: Ananya Rao | C5: 1 | D5: 20 | E5: Sprint reviews, RAID log, status reports | F5: =IF(AND(1>=$C5,1<=$D5),1,"") -> 1 | G5: =IF(AND(2>=$C5,2<=$D5),1,"") -> 1 | H5: =IF(AND(3>=$C5,3<=$D5),1,"") -> 1 | I5: =IF(AND(4>=$C5,4<=$D5),1,"") -> 1 | J5: =IF(AND(5>=$C5,5<=$D5),1,"") -> 1 | K5: =IF(AND(6>=$C5,6<=$D5),1,"") -> 1 | L5: =IF(AND(7>=$C5,7<=$D5),1,"") -> 1 | M5: =IF(AND(8>=$C5,8<=$D5),1,"") -> 1 | N5: =IF(AND(9>=$C5,9<=$D5),1,"") -> 1 | O5: =IF(AND(10>=$C5,10<=$D5),1,"") -> 1 | P5: =IF(AND(11>=$C5,11<=$D5),1,"") -> 1 | Q5: =IF(AND(12>=$C5,12<=$D5),1,"") -> 1 | R5: =IF(AND(13>=$C5,13<=$D5),1,"") -> 1 | S5: =IF(AND(14>=$C5,14<=$D5),1,"") -> 1 | T5: =IF(AND(15>=$C5,15<=$D5),1,"") -> 1 | U5: =IF(AND(16>=$C5,16<=$D5),1,"") -> 1 | V5: =IF(AND(17>=$C5,17<=$D5),1,"") -> 1 | W5: =IF(AND(18>=$C5,18<=$D5),1,"") -> 1 | X5: =IF(AND(19>=$C5,19<=$D5),1,"") -> 1 | Y5: =IF(AND(20>=$C5,20<=$D5),1,"") -> 1 | Z5: =IF(AND(21>=$C5,21<=$D5),1,"")
A6: Architecture and engineering | B6: Karthik Iyer | C6: 1 | D6: 20 | E6: Architecture decisions, integration contracts | F6: =IF(AND(1>=$C6,1<=$D6),1,"") -> 1 | G6: =IF(AND(2>=$C6,2<=$D6),1,"") -> 1 | H6: =IF(AND(3>=$C6,3<=$D6),1,"") -> 1 | I6: =IF(AND(4>=$C6,4<=$D6),1,"") -> 1 | J6: =IF(AND(5>=$C6,5<=$D6),1,"") -> 1 | K6: =IF(AND(6>=$C6,6<=$D6),1,"") -> 1 | L6: =IF(AND(7>=$C6,7<=$D6),1,"") -> 1 | M6: =IF(AND(8>=$C6,8<=$D6),1,"") -> 1 | N6: =IF(AND(9>=$C6,9<=$D6),1,"") -> 1 | O6: =IF(AND(10>=$C6,10<=$D6),1,"") -> 1 | P6: =IF(AND(11>=$C6,11<=$D6),1,"") -> 1 | Q6: =IF(AND(12>=$C6,12<=$D6),1,"") -> 1 | R6: =IF(AND(13>=$C6,13<=$D6),1,"") -> 1 | S6: =IF(AND(14>=$C6,14<=$D6),1,"") -> 1 | T6: =IF(AND(15>=$C6,15<=$D6),1,"") -> 1 | U6: =IF(AND(16>=$C6,16<=$D6),1,"") -> 1 | V6: =IF(AND(17>=$C6,17<=$D6),1,"") -> 1 | W6: =IF(AND(18>=$C6,18<=$D6),1,"") -> 1 | X6: =IF(AND(19>=$C6,19<=$D6),1,"") -> 1 | Y6: =IF(AND(20>=$C6,20<=$D6),1,"") -> 1 | Z6: =IF(AND(21>=$C6,21<=$D6),1,"")
A7: Data and knowledge engineering | B7: Priya Nair | C7: 2 | D7: 12 | E7: Curated content, retrieval quality | F7: =IF(AND(1>=$C7,1<=$D7),1,"") | G7: =IF(AND(2>=$C7,2<=$D7),1,"") -> 1 | H7: =IF(AND(3>=$C7,3<=$D7),1,"") -> 1 | I7: =IF(AND(4>=$C7,4<=$D7),1,"") -> 1 | J7: =IF(AND(5>=$C7,5<=$D7),1,"") -> 1 | K7: =IF(AND(6>=$C7,6<=$D7),1,"") -> 1 | L7: =IF(AND(7>=$C7,7<=$D7),1,"") -> 1 | M7: =IF(AND(8>=$C7,8<=$D7),1,"") -> 1 | N7: =IF(AND(9>=$C7,9<=$D7),1,"") -> 1 | O7: =IF(AND(10>=$C7,10<=$D7),1,"") -> 1 | P7: =IF(AND(11>=$C7,11<=$D7),1,"") -> 1 | Q7: =IF(AND(12>=$C7,12<=$D7),1,"") -> 1 | R7: =IF(AND(13>=$C7,13<=$D7),1,"") | S7: =IF(AND(14>=$C7,14<=$D7),1,"") | T7: =IF(AND(15>=$C7,15<=$D7),1,"") | U7: =IF(AND(16>=$C7,16<=$D7),1,"") | V7: =IF(AND(17>=$C7,17<=$D7),1,"") | W7: =IF(AND(18>=$C7,18<=$D7),1,"") | X7: =IF(AND(19>=$C7,19<=$D7),1,"") | Y7: =IF(AND(20>=$C7,20<=$D7),1,"") | Z7: =IF(AND(21>=$C7,21<=$D7),1,"")
A8: AI and prompt engineering | B8: Arjun Mehta | C8: 5 | D8: 16 | E8: System instructions, grounded response flows | F8: =IF(AND(1>=$C8,1<=$D8),1,"") | G8: =IF(AND(2>=$C8,2<=$D8),1,"") | H8: =IF(AND(3>=$C8,3<=$D8),1,"") | I8: =IF(AND(4>=$C8,4<=$D8),1,"") | J8: =IF(AND(5>=$C8,5<=$D8),1,"") -> 1 | K8: =IF(AND(6>=$C8,6<=$D8),1,"") -> 1 | L8: =IF(AND(7>=$C8,7<=$D8),1,"") -> 1 | M8: =IF(AND(8>=$C8,8<=$D8),1,"") -> 1 | N8: =IF(AND(9>=$C8,9<=$D8),1,"") -> 1 | O8: =IF(AND(10>=$C8,10<=$D8),1,"") -> 1 | P8: =IF(AND(11>=$C8,11<=$D8),1,"") -> 1 | Q8: =IF(AND(12>=$C8,12<=$D8),1,"") -> 1 | R8: =IF(AND(13>=$C8,13<=$D8),1,"") -> 1 | S8: =IF(AND(14>=$C8,14<=$D8),1,"") -> 1 | T8: =IF(AND(15>=$C8,15<=$D8),1,"") -> 1 | U8: =IF(AND(16>=$C8,16<=$D8),1,"") -> 1 | V8: =IF(AND(17>=$C8,17<=$D8),1,"") | W8: =IF(AND(18>=$C8,18<=$D8),1,"") | X8: =IF(AND(19>=$C8,19<=$D8),1,"") | Y8: =IF(AND(20>=$C8,20<=$D8),1,"") | Z8: =IF(AND(21>=$C8,21<=$D8),1,"")
A9: MCP and API integration | B9: Rohan Kulkarni | C9: 8 | D9: 14 | E9: Tool servers, connectors, error handling | F9: =IF(AND(1>=$C9,1<=$D9),1,"") | G9: =IF(AND(2>=$C9,2<=$D9),1,"") | H9: =IF(AND(3>=$C9,3<=$D9),1,"") | I9: =IF(AND(4>=$C9,4<=$D9),1,"") | J9: =IF(AND(5>=$C9,5<=$D9),1,"") | K9: =IF(AND(6>=$C9,6<=$D9),1,"") | L9: =IF(AND(7>=$C9,7<=$D9),1,"") | M9: =IF(AND(8>=$C9,8<=$D9),1,"") -> 1 | N9: =IF(AND(9>=$C9,9<=$D9),1,"") -> 1 | O9: =IF(AND(10>=$C9,10<=$D9),1,"") -> 1 | P9: =IF(AND(11>=$C9,11<=$D9),1,"") -> 1 | Q9: =IF(AND(12>=$C9,12<=$D9),1,"") -> 1 | R9: =IF(AND(13>=$C9,13<=$D9),1,"") -> 1 | S9: =IF(AND(14>=$C9,14<=$D9),1,"") -> 1 | T9: =IF(AND(15>=$C9,15<=$D9),1,"") | U9: =IF(AND(16>=$C9,16<=$D9),1,"") | V9: =IF(AND(17>=$C9,17<=$D9),1,"") | W9: =IF(AND(18>=$C9,18<=$D9),1,"") | X9: =IF(AND(19>=$C9,19<=$D9),1,"") | Y9: =IF(AND(20>=$C9,20<=$D9),1,"") | Z9: =IF(AND(21>=$C9,21<=$D9),1,"")
A10: Security and responsible AI | B10: Aditya Bose | C10: 1 | D10: 20 | E10: Access reviews, threat assessments, auditability | F10: =IF(AND(1>=$C10,1<=$D10),1,"") -> 1 | G10: =IF(AND(2>=$C10,2<=$D10),1,"") -> 1 | H10: =IF(AND(3>=$C10,3<=$D10),1,"") -> 1 | I10: =IF(AND(4>=$C10,4<=$D10),1,"") -> 1 | J10: =IF(AND(5>=$C10,5<=$D10),1,"") -> 1 | K10: =IF(AND(6>=$C10,6<=$D10),1,"") -> 1 | L10: =IF(AND(7>=$C10,7<=$D10),1,"") -> 1 | M10: =IF(AND(8>=$C10,8<=$D10),1,"") -> 1 | N10: =IF(AND(9>=$C10,9<=$D10),1,"") -> 1 | O10: =IF(AND(10>=$C10,10<=$D10),1,"") -> 1 | P10: =IF(AND(11>=$C10,11<=$D10),1,"") -> 1 | Q10: =IF(AND(12>=$C10,12<=$D10),1,"") -> 1 | R10: =IF(AND(13>=$C10,13<=$D10),1,"") -> 1 | S10: =IF(AND(14>=$C10,14<=$D10),1,"") -> 1 | T10: =IF(AND(15>=$C10,15<=$D10),1,"") -> 1 | U10: =IF(AND(16>=$C10,16<=$D10),1,"") -> 1 | V10: =IF(AND(17>=$C10,17<=$D10),1,"") -> 1 | W10: =IF(AND(18>=$C10,18<=$D10),1,"") -> 1 | X10: =IF(AND(19>=$C10,19<=$D10),1,"") -> 1 | Y10: =IF(AND(20>=$C10,20<=$D10),1,"") -> 1 | Z10: =IF(AND(21>=$C10,21<=$D10),1,"")
A11: QA and evaluation | B11: Divya Shetty | C11: 5 | D11: 20 | E11: Test suites, evaluation datasets, defect reports | F11: =IF(AND(1>=$C11,1<=$D11),1,"") | G11: =IF(AND(2>=$C11,2<=$D11),1,"") | H11: =IF(AND(3>=$C11,3<=$D11),1,"") | I11: =IF(AND(4>=$C11,4<=$D11),1,"") | J11: =IF(AND(5>=$C11,5<=$D11),1,"") -> 1 | K11: =IF(AND(6>=$C11,6<=$D11),1,"") -> 1 | L11: =IF(AND(7>=$C11,7<=$D11),1,"") -> 1 | M11: =IF(AND(8>=$C11,8<=$D11),1,"") -> 1 | N11: =IF(AND(9>=$C11,9<=$D11),1,"") -> 1 | O11: =IF(AND(10>=$C11,10<=$D11),1,"") -> 1 | P11: =IF(AND(11>=$C11,11<=$D11),1,"") -> 1 | Q11: =IF(AND(12>=$C11,12<=$D11),1,"") -> 1 | R11: =IF(AND(13>=$C11,13<=$D11),1,"") -> 1 | S11: =IF(AND(14>=$C11,14<=$D11),1,"") -> 1 | T11: =IF(AND(15>=$C11,15<=$D11),1,"") -> 1 | U11: =IF(AND(16>=$C11,16<=$D11),1,"") -> 1 | V11: =IF(AND(17>=$C11,17<=$D11),1,"") -> 1 | W11: =IF(AND(18>=$C11,18<=$D11),1,"") -> 1 | X11: =IF(AND(19>=$C11,19<=$D11),1,"") -> 1 | Y11: =IF(AND(20>=$C11,20<=$D11),1,"") -> 1 | Z11: =IF(AND(21>=$C11,21<=$D11),1,"")
A12: DevOps and observability | B12: Farhan Qureshi | C12: 2 | D12: 20 | E12: CI/CD, telemetry, alerts, deployment procedures | F12: =IF(AND(1>=$C12,1<=$D12),1,"") | G12: =IF(AND(2>=$C12,2<=$D12),1,"") -> 1 | H12: =IF(AND(3>=$C12,3<=$D12),1,"") -> 1 | I12: =IF(AND(4>=$C12,4<=$D12),1,"") -> 1 | J12: =IF(AND(5>=$C12,5<=$D12),1,"") -> 1 | K12: =IF(AND(6>=$C12,6<=$D12),1,"") -> 1 | L12: =IF(AND(7>=$C12,7<=$D12),1,"") -> 1 | M12: =IF(AND(8>=$C12,8<=$D12),1,"") -> 1 | N12: =IF(AND(9>=$C12,9<=$D12),1,"") -> 1 | O12: =IF(AND(10>=$C12,10<=$D12),1,"") -> 1 | P12: =IF(AND(11>=$C12,11<=$D12),1,"") -> 1 | Q12: =IF(AND(12>=$C12,12<=$D12),1,"") -> 1 | R12: =IF(AND(13>=$C12,13<=$D12),1,"") -> 1 | S12: =IF(AND(14>=$C12,14<=$D12),1,"") -> 1 | T12: =IF(AND(15>=$C12,15<=$D12),1,"") -> 1 | U12: =IF(AND(16>=$C12,16<=$D12),1,"") -> 1 | V12: =IF(AND(17>=$C12,17<=$D12),1,"") -> 1 | W12: =IF(AND(18>=$C12,18<=$D12),1,"") -> 1 | X12: =IF(AND(19>=$C12,19<=$D12),1,"") -> 1 | Y12: =IF(AND(20>=$C12,20<=$D12),1,"") -> 1 | Z12: =IF(AND(21>=$C12,21<=$D12),1,"")
A13: Change management | B13: Ananya Rao | C13: 16 | D13: 20 | E13: Training, user feedback, support handover | F13: =IF(AND(1>=$C13,1<=$D13),1,"") | G13: =IF(AND(2>=$C13,2<=$D13),1,"") | H13: =IF(AND(3>=$C13,3<=$D13),1,"") | I13: =IF(AND(4>=$C13,4<=$D13),1,"") | J13: =IF(AND(5>=$C13,5<=$D13),1,"") | K13: =IF(AND(6>=$C13,6<=$D13),1,"") | L13: =IF(AND(7>=$C13,7<=$D13),1,"") | M13: =IF(AND(8>=$C13,8<=$D13),1,"") | N13: =IF(AND(9>=$C13,9<=$D13),1,"") | O13: =IF(AND(10>=$C13,10<=$D13),1,"") | P13: =IF(AND(11>=$C13,11<=$D13),1,"") | Q13: =IF(AND(12>=$C13,12<=$D13),1,"") | R13: =IF(AND(13>=$C13,13<=$D13),1,"") | S13: =IF(AND(14>=$C13,14<=$D13),1,"") | T13: =IF(AND(15>=$C13,15<=$D13),1,"") | U13: =IF(AND(16>=$C13,16<=$D13),1,"") -> 1 | V13: =IF(AND(17>=$C13,17<=$D13),1,"") -> 1 | W13: =IF(AND(18>=$C13,18<=$D13),1,"") -> 1 | X13: =IF(AND(19>=$C13,19<=$D13),1,"") -> 1 | Y13: =IF(AND(20>=$C13,20<=$D13),1,"") -> 1 | Z13: =IF(AND(21>=$C13,21<=$D13),1,"")

Sheet RACI
A1: RACI Matrix
A2: R = Responsible · A = Accountable · C = Consulted · I = Informed
A4: WBS Ref | B4: Deliverable Group | C4: Project Manager / PO | D4: Solution Architect | E4: AI / RAG Engineer | F4: Backend / MCP Engineer | G4: Frontend Engineer | H4: QA Engineer | I4: Security Engineer | J4: DevOps Engineer | K4: App SMEs (SAP/Oracle/QA) | L4: Business Sponsor
A5: 1.1–1.4 | B5: Charter, personas, use cases & requirements | C5: A/R | D5: C | E5: C | F5: C | G5: I | H5: C | I5: C | J5: I | K5: R | L5: A
A6: 1.5–1.6 | B6: Application inventory & data-source assessment | C6: A | D6: C | E6: R | F6: R | G6: I | H6: I | I6: C | J6: I | K6: R | L6: I
A7: 1.7–1.8 | B7: Solution architecture & RAG/MCP integration design | C7: A | D7: R | E7: C | F7: C | G7: C | H7: I | I7: C | J7: C | K7: C | L7: I
A8: 1.9 | B8: Security design (identity, network, secrets) | C8: A | D8: C | E8: I | F8: C | G8: I | H8: I | I8: R | J8: C | K8: I | L8: I
A9: 2.1–2.4 | B9: Azure / AI Foundry environment & model integration | C9: A | D9: C | E9: R | F9: I | G9: I | H9: I | I9: C | J9: R | K9: I | L9: I
A10: 2.5–2.8 | B10: Knowledge corpus, retrieval & grounded answers | C10: A | D10: C | E10: R | F10: I | G10: I | H10: C | I10: I | J10: I | K10: R | L10: I
A11: 2.9 | B11: Chat UI prototype | C11: A | D11: C | E11: C | F11: C | G11: R | H11: C | I11: I | J11: I | K11: I | L11: C
A12: 3.1–3.3 | B12: MCP architecture, connection & read-only tools | C12: A | D12: C | E12: C | F12: R | G12: I | H12: C | I12: C | J12: I | K12: I | L12: I
A13: 3.4–3.6 | B13: SAP / Oracle / QA connectors | C13: A | D13: C | E13: I | F13: R | G13: I | H13: C | I13: C | J13: I | K13: R | L13: I
A14: 3.7–3.10 | B14: Tool routing, resilience & audit trail | C14: A | D14: C | E14: R | F14: R | G14: I | H14: R | I14: C | J14: I | K14: I | L14: I
A15: 4.1–4.4 | B15: Identity, authorization & AI security testing | C15: A | D15: C | E15: C | F15: C | G15: I | H15: C | I15: R | J15: R | K15: I | L15: I
... A20: 5.9–5.11 | B20: Training, handover & final report | C20: A/R | D20: R | E20: C | F20: C | G20: C | H20: C | I20: C | J20: C | K20: C | L20: A

Sheet KPIs
A1: KPIs & Success Measures
A2: Demo values · Attainment = Current vs Target (capped at 120%) · Green ≥ 100%, Amber ≥ 90%, Red < 90%
A4: KPI | B4: Definition | C4: Measurement Method | D4: Direction | E4: Baseline | F4: Target | G4: Current | H4: Attainment | I4: RAG | J4: Trend | K4: Owner
A5: Answer groundedness | B5: % of answers fully supported by retrieved sources | C5: LLM-as-judge + human review, 250-question benchmark | D5: Higher | E5: 0.72 | F5: 0.9 | G5: 0.87 | H5: =MIN(1.2,IF(D5="Lower",IF(G5<=F5,1,F5/G5),IF(F5=0,1,G5/F5))) -> 0.96666667 | I5: =IF(H5>=1,"GREEN",IF(H5>=0.9,"AMBER","RED")) -> AMBER | J5: =IF(D5="Lower",IF(G5<E5,"▲ Improving",IF(G5=E5,"► Stable","▼ Worse")),IF(G5>E5,"▲ Improving",IF(G5=E5,"► Stable","▼ Worse"))) -> ▲ Improving | K5: Arjun Mehta
A6: Citation correctness | B6: % of citations pointing to the right source passage | C6: Manual audit of 100 sampled answers | D6: Higher | E6: 0.65 | F6: 0.95 | G6: 0.91 | H6: =MIN(1.2,IF(D6="Lower",IF(G6<=F6,1,F6/G6),IF(F6=0,1,G6/F6))) -> 0.95789474 | I6: =IF(H6>=1,"GREEN",IF(H6>=0.9,"AMBER","RED")) -> AMBER | J6: =IF(D6="Lower",IF(G6<E6,"▲ Improving",IF(G6=E6,"► Stable","▼ Worse")),IF(G6>E6,"▲ Improving",IF(G6=E6,"► Stable","▼ Worse"))) -> ▲ Improving | K6: Priya Nair
A7: Retrieval recall@5 | B7: Relevant document in top-5 results | C7: Benchmark question set vs gold labels | D7: Higher | E7: 0.64 | F7: 0.85 | G7: 0.88 | H7: =MIN(1.2,IF(D7="Lower",IF(G7<=F7,1,F7/G7),IF(F7=0,1,G7/F7))) -> 1.0352941 | I7: =IF(H7>=1,"GREEN",IF(H7>=0.9,"AMBER","RED")) -> GREEN | J7: =IF(D7="Lower",IF(G7<E7,"▲ Improving",IF(G7=E7,"► Stable","▼ Worse")),IF(G7>E7,"▲ Improving",IF(G7=E7,"► Stable","▼ Worse"))) -> ▲ Improving | K7: Priya Nair
A8: Tool-call success rate | B8: Successful, authorized MCP calls / total | C8: Tool audit records (test environment) | D8: Higher | E8: 0.9 | F8: 0.98 | G8: 0.955 | H8: =MIN(1.2,IF(D8="Lower",IF(G8<=F8,1,F8/G8),IF(F8=0,1,G8/F8))) -> 0.9744898 | I8: =IF(H8>=1,"GREEN",IF(H8>=0.9,"AMBER","RED")) -> AMBER | J8: =IF(D8="Lower",IF(G8<E8,"▲ Improving",IF(G8=E8,"► Stable","▼ Worse")),IF(G8>E8,"▲ Improving",IF(G8=E8,"► Stable","▼ Worse"))) -> ▲ Improving | K8: Rohan Kulkarni
A9: Unauthorized data access | B9: Incidents in defined security test scenarios | C9: Security test suite incl. prompt injection | D9: Lower | E9: 0 | F9: 0 | G9: 0 | H9: =MIN(1.2,IF(D9="Lower",IF(G9<=F9,1,F9/G9),IF(F9=0,1,G9/F9))) -> 1 | I9: =IF(H9>=1,"GREEN",IF(H9>=0.9,"AMBER","RED")) -> GREEN | J9: =IF(D9="Lower",IF(G9<E9,"▲ Improving",IF(G9=E9,"► Stable","▼ Worse")),IF(G9>E9,"▲ Improving",IF(G9=E9,"► Stable","▼ Worse"))) -> ► Stable | K9: Aditya Bose
A10: P95 response time (s) | B10: End-to-end latency at pilot concurrency | C10: Load test, 50 concurrent users | D10: Lower | E10: 11.2 | F10: 8 | G10: 6.4 | H10: =MIN(1.2,IF(D10="Lower",IF(G10<=F10,1,F10/G10),IF(F10=0,1,G10/F10))) -> 1 | I10: =IF(H10>=1,"GREEN",IF(H10>=0.9,"AMBER","RED")) -> GREEN | J10: =IF(D10="Lower",IF(G10<E10,"▲ Improving",IF(G10=E10,"► Stable","▼ Worse")),IF(G10>E10,"▲ Improving",IF(G10=E10,"► Stable","▼ Worse"))) -> ▲ Improving | K10: Farhan Qureshi
A11: User satisfaction (CSAT) | B11: Average rating from demo/pilot users (1–5) | C11: In-app feedback + pilot survey | D11: Higher | E11: 3.1 | F11: 4 | G11: 4.2 | H11: =MIN(1.2,IF(D11="Lower",IF(G11<=F11,1,F11/G11),IF(F11=0,1,G11/F11))) -> 1.05 | I11: =IF(H11>=1,"GREEN",IF(H11>=0.9,"AMBER","RED")) -> GREEN | J11: =IF(D11="Lower",IF(G11<E11,"▲ Improving",IF(G11=E11,"► Stable","▼ Worse")),IF(G11>E11,"▲ Improving",IF(G11=E11,"► Stable","▼ Worse"))) -> ▲ Improving | K11: Vikram Desai
A12: Manual lookup effort reduction | B12: Reduction in time spent searching documentation | C12: Time-and-motion study, QA & IT support | D12: Higher | E12: 0 | F12: 0.4 | G12: 0.32 | H12: =MIN(1.2,IF(D12="Lower",IF(G12<=F12,1,F12/G12),IF(F12=0,1,G12/F12))) -> 0.8 | I12: =IF(H12>=1,"GREEN",IF(H12>=0.9,"AMBER","RED")) -> RED | J12: =IF(D12="Lower",IF(G12<E12,"▲ Improving",IF(G12=E12,"► Stable","▼ Worse")),IF(G12>E12,"▲ Improving",IF(G12=E12,"► Stable","▼ Worse"))) -> ▲ Improving | K12: Vikram Desai

Sheet RAID Log
A1: RAID Log — Risks, Assumptions, Issues & Dependencies
A2: Score = Probability × Impact (1–5): High ≥ 15 · Medium 8–14 · Low ≤ 7
A4: ID | B4: Type | C4: Description | D4: Category | E4: Probability (1–5) | F4: Impact (1–5) | G4: Score | H4: Rating | I4: Mitigation / Response | J4: Owner | K4: Status
A5: R-01 | B5: Risk | C5: SAP/Oracle API access, licensing or non-production environments not available in time | D5: Integration | E5: 4 | F5: 5 | G5: =IF(AND(ISNUMBER(E5),ISNUMBER(F5)),E5*F5,"") -> 20 | H5: =IF(G5="","",IF(G5>=15,"High",IF(G5>=8,"Medium","Low"))) -> High | I5: Access requests raised Week 1; mock services; reduced M3 scope agreed if needed | J5: Ananya Rao | K5: Open
A6: R-02 | B6: Risk | C6: GPT-5, GPT_Image-2 or Foundry IQ not available/configurable in the target Azure region | D6: Technology | E6: 2 | F6: 4 | G6: =IF(AND(ISNUMBER(E6),ISNUMBER(F6)),E6*F6,"") -> 8 | H6: =IF(G6="","",IF(G6>=15,"High",IF(G6>=8,"Medium","Low"))) -> Medium | I6: Availability validated in Week 6; fallback model identified; GPT_Image-2 optional | J6: Arjun Mehta | K6: Mitigated
A7: R-03 | B7: Risk | C7: Poor document quality or unclear source ownership degrades retrieval and grounding | D7: Data | E7: 3 | F7: 4 | G7: =IF(AND(ISNUMBER(E7),ISNUMBER(F7)),E7*F7,"") -> 12 | H7: =IF(G7="","",IF(G7>=15,"High",IF(G7>=8,"Medium","Low"))) -> Medium | I7: Data-source assessment; curated corpus; content owners named per source | J7: Priya Nair | K7: Monitoring
A8: R-04 | B8: Risk | C8: Confidential production data ingested into development environment | D8: Security | E8: 2 | F8: 5 | G8: =IF(AND(ISNUMBER(E8),ISNUMBER(F8)),E8*F8,"") -> 10 | H8: =IF(G8="","",IF(G8>=15,"High",IF(G8>=8,"Medium","Low"))) -> Medium | I8: Approved sample data only; classification gate before ingestion | J8: Aditya Bose | K8: Monitoring
A9: R-05 | B9: Risk | C9: Prompt injection or unsafe tool invocation leads to data leakage | D9: Security | E9: 3 | F9: 5 | G9: =IF(AND(ISNUMBER(E9),ISNUMBER(F9)),E9*F9,"") -> 15 | H9: =IF(G9="","",IF(G9>=15,"High",IF(G9>=8,"Medium","Low"))) -> High | I9: Read-only MCP tools; parameter validation; permission checks; red-team tests in 4.4 | J9: Aditya Bose | K9: Open
A10: R-06 | B10: Risk | C10: Hallucination / evaluation thresholds not met by release candidate | D10: Quality | E10: 3 | F10: 4 | G10: =IF(AND(ISNUMBER(E10),ISNUMBER(F10)),E10*F10,"") -> 12 | H10: =IF(G10="","",IF(G10>=15,"High",IF(G10>=8,"Medium","Low"))) -> Medium | I10: Baseline evaluation Month 2; prompt & retrieval tuning; citation enforcement | J10: Arjun Mehta | K10: Open
A11: R-07 | B11: Risk | C11: Part-time SME availability delays validation and UAT | D11: Resourcing | E11: 4 | F11: 3 | G11: =IF(AND(ISNUMBER(E11),ISNUMBER(F11)),E11*F11,"") -> 12 | H11: =IF(G11="","",IF(G11>=15,"High",IF(G11>=8,"Medium","Low"))) -> Medium | I11: Fixed weekly SME slots; escalation via sponsor | J11: Ananya Rao | K11: Open
A12: R-08 | B12: Risk | C12: Scope creep into write operations or additional applications | D12: Scope | E12: 3 | F12: 4 | G12: =IF(AND(ISNUMBER(E12),ISNUMBER(F12)),E12*F12,"") -> 12 | H12: =IF(G12="","",IF(G12>=15,"High",IF(G12>=8,"Medium","Low"))) -> Medium | I12: Change control; write operations need separate security review | J12: Vikram Desai | K12: Monitoring
A13: R-09 | B13: Risk | C13: Response-time or concurrency targets not achieved | D13: Performance | E13: 2 | F13: 3 | G13: =IF(AND(ISNUMBER(E13),ISNUMBER(F13)),E13*F13,"") -> 6 | H13: =IF(G13="","",IF(G13>=15,"High",IF(G13>=8,"Medium","Low"))) -> Low | I13: Early performance spike; caching; deployment sizing | J13: Farhan Qureshi | K13: Mitigated
A14: R-10 | B14: Risk | C14: Low pilot adoption limits feedback and business case | D14: Change | E14: 2 | F14: 3 | G14: =IF(AND(ISNUMBER(E14),ISNUMBER(F14)),E14*F14,"") -> 6 | H14: =IF(G14="","",IF(G14>=15,"High",IF(G14>=8,"Medium","Low"))) -> Low | I14: Lead with QA & Testing Assistant use case; onboarding and training | J14: Vikram Desai | K14: Open
A15: I-01 | B15: Issue | C15: Oracle non-production sandbox access delayed ~2 weeks by licensing approval | D15: Integration | E15: 5 | F15: 4 | G15: =IF(AND(ISNUMBER(E15),ISNUMBER(F15)),E15*F15,"") -> 20 | H15: =IF(G15="","",IF(G15>=15,"High",IF(G15>=8,"Medium","Low"))) -> High | I15: Escalated to sponsor 06-Jan; mock Oracle service used; M3 re-forecast | J15: Ananya Rao | K15: Open
A16: I-02 | B16: Issue | C16: GPT-5 tokens-per-minute quota limits load testing | D16: Technology | E16: 4 | F16: 3 | G16: =IF(AND(ISNUMBER(E16),ISNUMBER(F16)),E16*F16,"") -> 12 | H16: =IF(G16="","",IF(G16>=15,"High",IF(G16>=8,"Medium","Low"))) -> Medium | I16: Quota increase requested with Microsoft; tests throttled meanwhile | J16: Farhan Qureshi | K16: Open
A17: I-03 | B17: Issue | C17: SAP connector effort above estimate (custom BAPI wrapper needed) | D17: Integration | E17: 5 | F17: 2 | G17: =IF(AND(ISNUMBER(E17),ISNUMBER(F17)),E17*F17,"") -> 10 | H17: =IF(G17="","",IF(G17>=15,"High",IF(G17>=8,"Medium","Low"))) -> Medium | I17: Change absorbed in contingency; CPI recovery plan for Month 4 | J17: Rohan Kulkarni | K17: Monitoring
A18: A-01 | B18: Assumption | C18: MVP uses read-only MCP tools only | D18: Scope | G18: =IF(AND(ISNUMBER(E18),ISNUMBER(F18)),E18*F18,"") | H18: =IF(G18="","",IF(G18>=15,"High",IF(G18>=8,"Medium","Low"))) | I18: Validated at M1 sign-off | J18: Vikram Desai | K18: Closed
A19: A-02 | B19: Assumption | C19: Pilot scope is a limited set of high-value SAP, Oracle and QA use cases | D19: Scope | G19: =IF(AND(ISNUMBER(E19),ISNUMBER(F19)),E19*F19,"") | H19: =IF(G19="","",IF(G19>=15,"High",IF(G19>=8,"Medium","Low"))) | I19: Confirmed in requirements (1.4) | J19: Vikram Desai | K19: Closed
A20: D-01 | B20: Dependency | C20: Approved non-production application access, API documentation and sample data | D20: Integration | G20: =IF(AND(ISNUMBER(E20),ISNUMBER(F20)),E20*F20,"") | H20: =IF(G20="","",IF(G20>=15,"High",IF(G20>=8,"Medium","Low"))) | I20: Tracked weekly in status meeting | J20: Ananya Rao | K20: Open
A21: D-02 | B21: Dependency | C21: Microsoft Entra ID configuration and identity team support | D21: Security | G21: =IF(AND(ISNUMBER(E21),ISNUMBER(F21)),E21*F21,"") | H21: =IF(G21="","",IF(G21>=15,"High",IF(G21>=8,"Medium","Low"))) | I21: Identity team engaged; slot booked Week 13 | J21: Aditya Bose | K21: Open
A22: D-03 | B22: Dependency | C22: Application-owner support for integration and business validation | D22: Resourcing | G22: =IF(AND(ISNUMBER(E22),ISNUMBER(F22)),E22*F22,"") | H22: =IF(G22="","",IF(G22>=15,"High",IF(G22>=8,"Medium","Low"))) | I22: SME plan agreed at kickoff | J22: Ananya Rao | K22: Monitoring

Sheet Holidays
A1: Non-Working Days
A2: Demo India holiday calendar — confirm against the client's HR calendar · all dates skip these
A4: # | B4: Date | C4: Description
A5: 1 | B5: 46335 | C5: Diwali (demo)
A6: 2 | B6: 46350 | C6: Guru Nanak Jayanti (demo)
A7: 3 | B7: 46381 | C7: Christmas Day
A8: 4 | B8: 46388 | C8: New Year's Day
A9: 5 | B9: 46413 | C9: Republic Day
A10: 6
A11: 7
A12: 8
A13: 9
A14: 10
A15: 11
A16: 12
A17: 13
A18: 14
A19: 15
A20: 16
A21: 17
... A34: 30

Sheet Weekly Status Log
A1: Weekly Status Log (EVM)
A2: Cumulative values as reported at each week-end · blue = reported inputs · SPI = EV/PV · CPI = EV/AC
A4: Week | B4: Week Ending | C4: Planned Value (PV ₹ L) | D4: Earned Value (EV ₹ L) | E4: Actual Cost (AC ₹ L) | F4: SPI | G4: CPI | H4: Activities Remaining | I4: RAG | J4: Key Commentary
A5: 1 | B5: ='Chart Data'!C5 -> 46318 | C5: ='Chart Data'!D5 -> 6.08 | D5: 6.1 | E5: 6.1 | F5: =IF(D5="","",IF(C5=0,1,D5/C5)) -> 1.0032895 | G5: =IF(OR(D5="",E5=""),"",IF(E5=0,1,D5/E5)) -> 1 | H5: 48 | I5: GREEN | J5: Kickoff held; charter and stakeholder map approved; personas drafted
A6: 2 | B6: ='Chart Data'!C6 -> 46325 | C6: ='Chart Data'!D6 -> 12.48 | D6: 12.1 | E6: 12.1 | F6: =IF(D6="","",IF(C6=0,1,D6/C6)) -> 0.96955128 | G6: =IF(OR(D6="",E6=""),"",IF(E6=0,1,D6/E6)) -> 1 | H6: 47 | I6: GREEN | J6: 28 use cases captured across SAP, Oracle, QA; NFR workshop completed
A7: 3 | B7: ='Chart Data'!C7 -> 46332 | C7: ='Chart Data'!D7 -> 16.96 | D7: 16.8 | E7: 16.7 | F7: =IF(D7="","",IF(C7=0,1,D7/C7)) -> 0.99056604 | G7: =IF(OR(D7="",E7=""),"",IF(E7=0,1,D7/E7)) -> 1.005988 | H7: 42 | I7: GREEN | J7: Requirements spec baselined; API & MCP tool inventory 80% complete
A8: 4 | B8: ='Chart Data'!C8 -> 46339 | C8: ='Chart Data'!D8 -> 16.96 | D8: 17 | E8: 16.7 | F8: =IF(D8="","",IF(C8=0,1,D8/C8)) -> 1.0023585 | G8: =IF(OR(D8="",E8=""),"",IF(E8=0,1,D8/E8)) -> 1.0179641 | H8: 41 | I8: GREEN | J8: Diwali week; architecture and data-source assessment in progress
A9: 5 | B9: ='Chart Data'!C9 -> 46346 | C9: ='Chart Data'!D9 -> 21.76 | D9: 22 | E9: 21.8 | F9: =IF(D9="","",IF(C9=0,1,D9/C9)) -> 1.0110294 | G9: =IF(OR(D9="",E9=""),"",IF(E9=0,1,D9/E9)) -> 1.0091743 | H9: 39 | I9: GREEN | J9: Architecture approved — M1 achieved 16-Nov; Azure dev subscription provisioned
A10: 6 | B10: ='Chart Data'!C10 -> 46353 | C10: ='Chart Data'!D10 -> 25.92 | D10: 25.9 | E10: 25.9 | F10: =IF(D10="","",IF(C10=0,1,D10/C10)) -> 0.9992284 | G10: =IF(OR(D10="",E10=""),"",IF(E10=0,1,D10/E10)) -> 1 | H10: 36 | I10: GREEN | J10: GPT-5 deployment validated in West Europe; curated corpus of 1,240 documents ready
A11: 7 | B11: ='Chart Data'!C11 -> 46360 | C11: ='Chart Data'!D11 -> 30.4 | D11: 30.4 | E11: 30.7 | F11: =IF(D11="","",IF(C11=0,1,D11/C11)) -> 1 | G11: =IF(OR(D11="",E11=""),"",IF(E11=0,1,D11/E11)) -> 0.99022801 | H11: 34 | I11: GREEN | J11: Foundry IQ indexing complete; first grounded answers with citations demonstrated
A12: 8 | B12: ='Chart Data'!C12 -> 46367 | C12: ='Chart Data'!D12 -> 33.6 | D12: 33.9 | E12: 34.6 | F12: =IF(D12="","",IF(C12=0,1,D12/C12)) -> 1.0089286 | G12: =IF(OR(D12="",E12=""),"",IF(E12=0,1,D12/E12)) -> 0.97976879 | H12: 32 | I12: GREEN | J12: Chat UI prototype live; baseline evaluation 81% groundedness
A13: 9 | B13: ='Chart Data'!C13 -> 46374 | C13: ='Chart Data'!D13 -> 36.16 | D13: 35.8 | E13: 36.9 | F13: =IF(D13="","",IF(C13=0,1,D13/C13)) -> 0.99004425 | G13: =IF(OR(D13="",E13=""),"",IF(E13=0,1,D13/E13)) -> 0.9701897 | H13: 31 | I13: GREEN | J13: M2 AI Assistant MVP achieved 14-Dec; MCP architecture and tool contracts agreed
A14: 10 | B14: ='Chart Data'!C14 -> 46381 | C14: ='Chart Data'!D14 -> 38.72 | D14: 37.9 | E14: 39.4 | F14: =IF(D14="","",IF(C14=0,1,D14/C14)) -> 0.97882231 | G14: =IF(OR(D14="",E14=""),"",IF(E14=0,1,D14/E14)) -> 0.96192893 | H14: 30 | I14: AMBER | J14: MCP auth working; SAP connector needs custom BAPI wrapper (I-03)
A15: 11 | B15: ='Chart Data'!C15 -> 46388 | C15: ='Chart Data'!D15 -> 51.52 | D15: 48.9 | E15: 52.3 | F15: =IF(D15="","",IF(C15=0,1,D15/C15)) -> 0.94914596 | G15: =IF(OR(D15="",E15=""),"",IF(E15=0,1,D15/E15)) -> 0.93499044 | H15: 27 | I15: AMBER | J15: Holiday week; SAP & QA connectors working; Oracle sandbox access blocked (I-01)
A16: 12 | B16: ='Chart Data'!C16 -> 46395 | C16: ='Chart Data'!D16 -> 56.64 | D16: 52.6 | E16: 57.4 | F16: =IF(D16="","",IF(C16=0,1,D16/C16)) -> 0.92867232 | G16: =IF(OR(D16="",E16=""),"",IF(E16=0,1,D16/E16)) -> 0.91637631 | H16: 25 | I16: AMBER | J16: Oracle access escalated to sponsor; mock Oracle service used; tool routing done
A17: 13 | B17: ='Chart Data'!C17 -> 46402 | C17: ='Chart Data'!D17 -> 59.84 | D17: 56.4 | E17: 58.6 | F17: =IF(D17="","",IF(C17=0,1,D17/C17)) -> 0.94251337 | G17: =IF(OR(D17="",E17=""),"",IF(E17=0,1,D17/E17)) -> 0.96245734 | H17: 24 | I17: AMBER | J17: M3 slipped — Oracle integration 70%, E2E tests 50%; Entra ID work started; secrets mgmt done early
A18: 14 | B18: ='Chart Data'!C18 -> 46409 | C18: ='Chart Data'!D18 -> 69.44 | F18: =IF(D18="","",IF(C18=0,1,D18/C18)) | G18: =IF(OR(D18="",E18=""),"",IF(E18=0,1,D18/E18))
A19: 15 | B19: ='Chart Data'!C19 -> 46416 | C19: ='Chart Data'!D19 -> 74.56 | F19: =IF(D19="","",IF(C19=0,1,D19/C19)) | G19: =IF(OR(D19="",E19=""),"",IF(E19=0,1,D19/E19))
A20: 16 | B20: ='Chart Data'!C20 -> 46423 | C20: ='Chart Data'!D20 -> 79.04 | F20: =IF(D20="","",IF(C20=0,1,D20/C20)) | G20: =IF(OR(D20="",E20=""),"",IF(E20=0,1,D20/E20))
A21: 17 | B21: ='Chart Data'!C21 -> 46430 | C21: ='Chart Data'!D21 -> 81.6 | F21: =IF(D21="","",IF(C21=0,1,D21/C21)) | G21: =IF(OR(D21="",E21=""),"",IF(E21=0,1,D21/E21))
A22: 18 | B22: ='Chart Data'!C22 -> 46437 | C22: ='Chart Data'!D22 -> 91.52 | F22: =IF(D22="","",IF(C22=0,1,D22/C22)) | G22: =IF(OR(D22="",E22=""),"",IF(E22=0,1,D22/E22))
A23: 19 | B23: ='Chart Data'!C23 -> 46444 | C23: ='Chart Data'!D23 -> 96.64 | F23: =IF(D23="","",IF(C23=0,1,D23/C23)) | G23: =IF(OR(D23="",E23=""),"",IF(E23=0,1,D23/E23))
A24: 20 | B24: ='Chart Data'!C24 -> 46451 | C24: ='Chart Data'!D24 -> 101.12 | F24: =IF(D24="","",IF(C24=0,1,D24/C24)) | G24: =IF(OR(D24="",E24=""),"",IF(E24=0,1,D24/E24))
A25: 21 | B25: ='Chart Data'!C25 -> 46458 | C25: ='Chart Data'!D25 -> 105.6 | F25: =IF(D25="","",IF(C25=0,1,D25/C25)) | G25: =IF(OR(D25="",E25=""),"",IF(E25=0,1,D25/E25))

Sheet Chart Data
A1: Chart Data
A2: Calculated series feeding the Dashboard charts — no inputs on this sheet
A4: Week | B4: Week Start | C4: Week End | D4: PV cum (₹ L) | E4: Planned Remaining | F4: FTE: M1 Discovery | G4: FTE: M2 AI Foundation | H4: FTE: M3 Integration | I4: FTE: M4 Security & QA | J4: FTE: M5 Pilot & Handover | K4: Target (1.0) | L4: Week Label
A5: 1 | B5: =ProjectStart-WEEKDAY(ProjectStart,3)+0 -> 46314 | C5: =B5+4 -> 46318 | D5: =SUM(B71:B121) -> 6.08 | E5: =COUNTIFS('WBS Schedule'!$B$7:$B$68,2,'WBS Schedule'!$G$7:$G$68,">0")-COUNTIFS('WBS Schedule'!$B$7:$B$68,2,'WBS Schedule'!$G$7:$G$68,">0",'WBS Schedule'!$I$7:$I$68,"<="&C5) -> 48 | F5: =SUMPRODUCT(('WBS Schedule'!V9:V18=1)*'WBS Schedule'!$N$9:$N$18) -> 8 | G5: =SUMPRODUCT(('WBS Schedule'!V21:V30=1)*'WBS Schedule'!$N$21:$N$30) -> 0 | H5: =SUMPRODUCT(('WBS Schedule'!V33:V42=1)*'WBS Schedule'!$N$33:$N$42) -> 0 | I5: =SUMPRODUCT(('WBS Schedule'!V45:V54=1)*'WBS Schedule'!$N$45:$N$54) -> 0 | J5: =SUMPRODUCT(('WBS Schedule'!V57:V67=1)*'WBS Schedule'!$N$57:$N$67) -> 0 | K5: 1 | L5: W1
A6: 2 | B6: =ProjectStart-WEEKDAY(ProjectStart,3)+7 -> 46321 | C6: =B6+4 -> 46325 | D6: =SUM(C71:C121) -> 12.48 | E6: =COUNTIFS('WBS Schedule'!$B$7:$B$68,2,'WBS Schedule'!$G$7:$G$68,">0")-COUNTIFS('WBS Schedule'!$B$7:$B$68,2,'WBS Schedule'!$G$7:$G$68,">0",'WBS Schedule'!$I$7:$I$68,"<="&C6) -> 46 | F6: =SUMPRODUCT(('WBS Schedule'!W9:W18=1)*'WBS Schedule'!$N$9:$N$18) -> 8 | G6: =SUMPRODUCT(('WBS Schedule'!W21:W30=1)*'WBS Schedule'!$N$21:$N$30) -> 0 | H6: =SUMPRODUCT(('WBS Schedule'!W33:W42=1)*'WBS Schedule'!$N$33:$N$42) -> 0 | I6: =SUMPRODUCT(('WBS Schedule'!W45:W54=1)*'WBS Schedule'!$N$45:$N$54) -> 0 | J6: =SUMPRODUCT(('WBS Schedule'!W57:W67=1)*'WBS Schedule'!$N$57:$N$67) -> 0 | K6: 1 | L6: W2
A7: 3 | B7: =ProjectStart-WEEKDAY(ProjectStart,3)+14 -> 46328 | C7: =B7+4 -> 46332 | D7: =SUM(D71:D121) -> 16.96 | E7: =COUNTIFS('WBS Schedule'!$B$7:$B$68,2,'WBS Schedule'!$G$7:$G$68,">0")-COUNTIFS('WBS Schedule'!$B$7:$B$68,2,'WBS Schedule'!$G$7:$G$68,">0",'WBS Schedule'!$I$7:$I$68,"<="&C7) -> 41 | F7: =SUMPRODUCT(('WBS Schedule'!X9:X18=1)*'WBS Schedule'!$N$9:$N$18) -> 9 | G7: =SUMPRODUCT(('WBS Schedule'!X21:X30=1)*'WBS Schedule'!$N$21:$N$30) -> 0 | H7: =SUMPRODUCT(('WBS Schedule'!X33:X42=1)*'WBS Schedule'!$N$33:$N$42) -> 0 | I7: =SUMPRODUCT(('WBS Schedule'!X45:X54=1)*'WBS Schedule'!$N$45:$N$54) -> 0 | J7: =SUMPRODUCT(('WBS Schedule'!X57:X67=1)*'WBS Schedule'!$N$57:$N$67) -> 0 | K7: 1 | L7: W3
A8: 4 | B8: =ProjectStart-WEEKDAY(ProjectStart,3)+21 -> 46335 | C8: =B8+4 -> 46339 | D8: =SUM(E71:E121) -> 16.96 | E8: =COUNTIFS('WBS Schedule'!$B$7:$B$68,2,'WBS Schedule'!$G$7:$G$68,">0")-COUNTIFS('WBS Schedule'!$B$7:$B$68,2,'WBS Schedule'!$G$7:$G$68,">0",'WBS Schedule'!$I$7:$I$68,"<="&C8) -> 41 | F8: =SUMPRODUCT(('WBS Schedule'!Y9:Y18=1)*'WBS Schedule'!$N$9:$N$18) -> 0 | G8: =SUMPRODUCT(('WBS Schedule'!Y21:Y30=1)*'WBS Schedule'!$N$21:$N$30) -> 0 | H8: =SUMPRODUCT(('WBS Schedule'!Y33:Y42=1)*'WBS Schedule'!$N$33:$N$42) -> 0 | I8: =SUMPRODUCT(('WBS Schedule'!Y45:Y54=1)*'WBS Schedule'!$N$45:$N$54) -> 0 | J8: =SUMPRODUCT(('WBS Schedule'!Y57:Y67=1)*'WBS Schedule'!$N$57:$N$67) -> 0 | K8: 1 | L8: W4
A9: 5 | B9: =ProjectStart-WEEKDAY(ProjectStart,3)+28 -> 46342 | C9: =B9+4 -> 46346 | D9: =SUM(F71:F121) -> 21.76 | E9: =COUNTIFS('WBS Schedule'!$B$7:$B$68,2,'WBS Schedule'!$G$7:$G$68,">0")-COUNTIFS('WBS Schedule'!$B$7:$B$68,2,'WBS Schedule'!$G$7:$G$68,">0",'WBS Schedule'!$I$7:$I$68,"<="&C9) -> 38 | F9: =SUMPRODUCT(('WBS Schedule'!Z9:Z18=1)*'WBS Schedule'!$N$9:$N$18) -> 0 | G9: =SUMPRODUCT(('WBS Schedule'!Z21:Z30=1)*'WBS Schedule'!$N$21:$N$30) -> 6 | H9: =SUMPRODUCT(('WBS Schedule'!Z33:Z42=1)*'WBS Schedule'!$N$33:$N$42) -> 0 | I9: =SUMPRODUCT(('WBS Schedule'!Z45:Z54=1)*'WBS Schedule'!$N$45:$N$54) -> 0 | J9: =SUMPRODUCT(('WBS Schedule'!Z57:Z67=1)*'WBS Schedule'!$N$57:$N$67) -> 0 | K9: 1 | L9: W5
A10: 6 | B10: =ProjectStart-WEEKDAY(ProjectStart,3)+35 -> 46349 | C10: =B10+4 -> 46353 | D10: =SUM(G71:G121) -> 25.92 | E10: =COUNTIFS('WBS Schedule'!$B$7:$B$68,2,'WBS Schedule'!$G$7:$G$68,">0")-COUNTIFS('WBS Schedule'!$B$7:$B$68,2,'WBS Schedule'!$G$7:$G$68,">0",'WBS Schedule'!$I$7:$I$68,"<="&C10) -> 36 | F10: =SUMPRODUCT(('WBS Schedule'!AA9:AA18=1)*'WBS Schedule'!$N$9:$N$18) -> 0 | G10: =SUMPRODUCT(('WBS Schedule'!AA21:AA30=1)*'WBS Schedule'!$N$21:$N$30) -> 7 | H10: =SUMPRODUCT(('WBS Schedule'!AA33:AA42=1)*'WBS Schedule'!$N$33:$N$42) -> 0 | I10: =SUMPRODUCT(('WBS Schedule'!AA45:AA54=1)*'WBS Schedule'!$N$45:$N$54) -> 0 | J10: =SUMPRODUCT(('WBS Schedule'!AA57:AA67=1)*'WBS Schedule'!$N$57:$N$67) -> 0 | K10: 1 | L10: W6
A11: 7 | B11: =ProjectStart-WEEKDAY(ProjectStart,3)+42 -> 46356 | C11: =B11+4 -> 46360 | D11: =SUM(H71:H121) -> 30.4 | E11: =COUNTIFS('WBS Schedule'!$B$7:$B$68,2,'WBS Schedule'!$G$7:$G$68,">0")-COUNTIFS('WBS Schedule'!$B$7:$B$68,2,'WBS Schedule'!$G$7:$G$68,">0",'WBS Schedule'!$I$7:$I$68,"<="&C11) -> 33 | F11: =SUMPRODUCT(('WBS Schedule'!AB9:AB18=1)*'WBS Schedule'!$N$9:$N$18) -> 0 | G11: =SUMPRODUCT(('WBS Schedule'!AB21:AB30=1)*'WBS Schedule'!$N$21:$N$30) -> 6 | H11: =SUMPRODUCT(('WBS Schedule'!AB33:AB42=1)*'WBS Schedule'!$N$33:$N$42) -> 0 | I11: =SUMPRODUCT(('WBS Schedule'!AB45:AB54=1)*'WBS Schedule'!$N$45:$N$54) -> 0 | J11: =SUMPRODUCT(('WBS Schedule'!AB57:AB67=1)*'WBS Schedule'!$N$57:$N$67) -> 0 | K11: 1 | L11: W7
A12: 8 | B12: =ProjectStart-WEEKDAY(ProjectStart,3)+49 -> 46363 | C12: =B12+4 -> 46367 | D12: =SUM(I71:I121) -> 33.6 | E12: =COUNTIFS('WBS Schedule'!$B$7:$B$68,2,'WBS Schedule'!$G$7:$G$68,">0")-COUNTIFS('WBS Schedule'!$B$7:$B$68,2,'WBS Schedule'!$G$7:$G$68,">0",'WBS Schedule'!$I$7:$I$68,"<="&C12) -> 32 | F12: =SUMPRODUCT(('WBS Schedule'!AC9:AC18=1)*'WBS Schedule'!$N$9:$N$18) -> 0 | G12: =SUMPRODUCT(('WBS Schedule'!AC21:AC30=1)*'WBS Schedule'!$N$21:$N$30) -> 4 | H12: =SUMPRODUCT(('WBS Schedule'!AC33:AC42=1)*'WBS Schedule'!$N$33:$N$42) -> 0 | I12: =SUMPRODUCT(('WBS Schedule'!AC45:AC54=1)*'WBS Schedule'!$N$45:$N$54) -> 0 | J12: =SUMPRODUCT(('WBS Schedule'!AC57:AC67=1)*'WBS Schedule'!$N$57:$N$67) -> 0 | K12: 1 | L12: W8
A13: 9 | B13: =ProjectStart-WEEKDAY(ProjectStart,3)+56 -> 46370 | C13: =B13+4 -> 46374 | D13: =SUM(J71:J121) -> 36.16 | E13: =COUNTIFS('WBS Schedule'!$B$7:$B$68,2,'WBS Schedule'!$G$7:$G$68,">0")-COUNTIFS('WBS Schedule'!$B$7:$B$68,2,'WBS Schedule'!$G$7:$G$68,">0",'WBS Schedule'!$I$7:$I$68,"<="&C13) -> 30 | F13: =SUMPRODUCT(('WBS Schedule'!AD9:AD18=1)*'WBS Schedule'!$N$9:$N$18) -> 0 | G13: =SUMPRODUCT(('WBS Schedule'!AD21:AD30=1)*'WBS Schedule'!$N$21:$N$30) -> 2 | H13: =SUMPRODUCT(('WBS Schedule'!AD33:AD42=1)*'WBS Schedule'!$N$33:$N$42) -> 2 | I13: =SUMPRODUCT(('WBS Schedule'!AD45:AD54=1)*'WBS Schedule'!$N$45:$N$54) -> 0 | J13: =SUMPRODUCT(('WBS Schedule'!AD57:AD67=1)*'WBS Schedule'!$N$57:$N$67) -> 0 | K13: 1 | L13: W9
A14: 10 | B14: =ProjectStart-WEEKDAY(ProjectStart,3)+63 -> 46377 | C14: =B14+4 -> 46381 | D14: =SUM(K71:K121) -> 38.72 | E14: =COUNTIFS('WBS Schedule'!$B$7:$B$68,2,'WBS Schedule'!$G$7:$G$68,">0")-COUNTIFS('WBS Schedule'!$B$7:$B$68,2,'WBS Schedule'!$G$7:$G$68,">0",'WBS Schedule'!$I$7:$I$68,"<="&C14) -> 29 | F14: =SUMPRODUCT(('WBS Schedule'!AE9:AE18=1)*'WBS Schedule'!$N$9:$N$18) -> 0 | G14: =SUMPRODUCT(('WBS Schedule'!AE21:AE30=1)*'WBS Schedule'!$N$21:$N$30) -> 0 | H14: =SUMPRODUCT(('WBS Schedule'!AE33:AE42=1)*'WBS Schedule'!$N$33:$N$42) -> 2 | I14: =SUMPRODUCT(('WBS Schedule'!AE45:AE54=1)*'WBS Schedule'!$N$45:$N$54) -> 0 | J14: =SUMPRODUCT(('WBS Schedule'!AE57:AE67=1)*'WBS Schedule'!$N$57:$N$67) -> 0 | K14: 1 | L14: W10
A15: 11 | B15: =ProjectStart-WEEKDAY(ProjectStart,3)+70 -> 46384 | C15: =B15+4 -> 46388 | D15: =SUM(L71:L121) -> 51.52 | E15: =COUNTIFS('WBS Schedule'!$B$7:$B$68,2,'WBS Schedule'!$G$7:$G$68,">0")-COUNTIFS('WBS Schedule'!$B$7:$B$68,2,'WBS Schedule'!$G$7:$G$68,">0",'WBS Schedule'!$I$7:$I$68,"<="&C15) -> 25 | F15: =SUMPRODUCT(('WBS Schedule'!AF9:AF18=1)*'WBS Schedule'!$N$9:$N$18) -> 0 | G15: =SUMPRODUCT(('WBS Schedule'!AF21:AF30=1)*'WBS Schedule'!$N$21:$N$30) -> 0 | H15: =SUMPRODUCT(('WBS Schedule'!AF33:AF42=1)*'WBS Schedule'!$N$33:$N$42) -> 12 | I15: =SUMPRODUCT(('WBS Schedule'!AF45:AF54=1)*'WBS Schedule'!$N$45:$N$54) -> 0 | J15: =SUMPRODUCT(('WBS Schedule'!AF57:AF67=1)*'WBS Schedule'!$N$57:$N$67) -> 0 | K15: 1 | L15: W11
A16: 12 | B16: =ProjectStart-WEEKDAY(ProjectStart,3)+77 -> 46391 | C16: =B16+4 -> 46395 | D16: =SUM(M71:M121) -> 56.64 | E16: =COUNTIFS('WBS Schedule'!$B$7:$B$68,2,'WBS Schedule'!$G$7:$G$68,">0")-COUNTIFS('WBS Schedule'!$B$7:$B$68,2,'WBS Schedule'!$G$7:$G$68,">0",'WBS Schedule'!$I$7:$I$68,"<="&C16) -> 23 | F16: =SUMPRODUCT(('WBS Schedule'!AG9:AG18=1)*'WBS Schedule'!$N$9:$N$18) -> 0 | G16: =SUMPRODUCT(('WBS Schedule'!AG21:AG30=1)*'WBS Schedule'!$N$21:$N$30) -> 0 | H16: =SUMPRODUCT(('WBS Schedule'!AG33:AG42=1)*'WBS Schedule'!$N$33:$N$42) -> 7 | I16: =SUMPRODUCT(('WBS Schedule'!AG45:AG54=1)*'WBS Schedule'!$N$45:$N$54) -> 0 | J16: =SUMPRODUCT(('WBS Schedule'!AG57:AG67=1)*'WBS Schedule'!$N$57:$N$67) -> 0 | K16: 1 | L16: W12
A17: 13 | B17: =ProjectStart-WEEKDAY(ProjectStart,3)+84 -> 46398 | C17: =B17+4 -> 46402 | D17: =SUM(N71:N121) -> 59.84 | E17: =COUNTIFS('WBS Schedule'!$B$7:$B$68,2,'WBS Schedule'!$G$7:$G$68,">0")-COUNTIFS('WBS Schedule'!$B$7:$B$68,2,'WBS Schedule'!$G$7:$G$68,">0",'WBS Schedule'!$I$7:$I$68,"<="&C17) -> 21 | F17: =SUMPRODUCT(('WBS Schedule'!AH9:AH18=1)*'WBS Schedule'!$N$9:$N$18) -> 0 | G17: =SUMPRODUCT(('WBS Schedule'!AH21:AH30=1)*'WBS Schedule'!$N$21:$N$30) -> 0 | H17: =SUMPRODUCT(('WBS Schedule'!AH33:AH42=1)*'WBS Schedule'!$N$33:$N$42) -> 4 | I17: =SUMPRODUCT(('WBS Schedule'!AH45:AH54=1)*'WBS Schedule'!$N$45:$N$54) -> 6 | J17: =SUMPRODUCT(('WBS Schedule'!AH57:AH67=1)*'WBS Schedule'!$N$57:$N$67) -> 0 | K17: 1 | L17: W13
A18: 14 | B18: =ProjectStart-WEEKDAY(ProjectStart,3)+91 -> 46405 | C18: =B18+4 -> 46409 | D18: =SUM(O71:O121) -> 69.44 | E18: =COUNTIFS('WBS Schedule'!$B$7:$B$68,2,'WBS Schedule'!$G$7:$G$68,">0")-COUNTIFS('WBS Schedule'!$B$7:$B$68,2,'WBS Schedule'!$G$7:$G$68,">0",'WBS Schedule'!$I$7:$I$68,"<="&C18) -> 17 | F18: =SUMPRODUCT(('WBS Schedule'!AI9:AI18=1)*'WBS Schedule'!$N$9:$N$18) -> 0 | G18: =SUMPRODUCT(('WBS Schedule'!AI21:AI30=1)*'WBS Schedule'!$N$21:$N$30) -> 0 | H18: =SUMPRODUCT(('WBS Schedule'!AI33:AI42=1)*'WBS Schedule'!$N$33:$N$42) -> 0 | I18: =SUMPRODUCT(('WBS Schedule'!AI45:AI54=1)*'WBS Schedule'!$N$45:$N$54) -> 12 | J18: =SUMPRODUCT(('WBS Schedule'!AI57:AI67=1)*'WBS Schedule'!$N$57:$N$67) -> 0 | K18: 1 | L18: W14
A19: 15 | B19: =ProjectStart-WEEKDAY(ProjectStart,3)+98 -> 46412 | C19: =B19+4 -> 46416 | D19: =SUM(P71:P121) -> 74.56 | E19: =COUNTIFS('WBS Schedule'!$B$7:$B$68,2,'WBS Schedule'!$G$7:$G$68,">0")-COUNTIFS('WBS Schedule'!$B$7:$B$68,2,'WBS Schedule'!$G$7:$G$68,">0",'WBS Schedule'!$I$7:$I$68,"<="&C19) -> 13 | F19: =SUMPRODUCT(('WBS Schedule'!AJ9:AJ18=1)*'WBS Schedule'!$N$9:$N$18) -> 0 | G19: =SUMPRODUCT(('WBS Schedule'!AJ21:AJ30=1)*'WBS Schedule'!$N$21:$N$30) -> 0 | H19: =SUMPRODUCT(('WBS Schedule'!AJ33:AJ42=1)*'WBS Schedule'!$N$33:$N$42) -> 0 | I19: =SUMPRODUCT(('WBS Schedule'!AJ45:AJ54=1)*'WBS Schedule'!$N$45:$N$54) -> 8 | J19: =SUMPRODUCT(('WBS Schedule'!AJ57:AJ67=1)*'WBS Schedule'!$N$57:$N$67) -> 0 | K19: 1 | L19: W15
A20: 16 | B20: =ProjectStart-WEEKDAY(ProjectStart,3)+105 -> 46419 | C20: =B20+4 -> 46423 | D20: =SUM(Q71:Q121) -> 79.04 | E20: =COUNTIFS('WBS Schedule'!$B$7:$B$68,2,'WBS Schedule'!$G$7:$G$68,">0")-COUNTIFS('WBS Schedule'!$B$7:$B$68,2,'WBS Schedule'!$G$7:$G$68,">0",'WBS Schedule'!$I$7:$I$68,"<="&C20) -> 12 | F20: =SUMPRODUCT(('WBS Schedule'!AK9:AK18=1)*'WBS Schedule'!$N$9:$N$18) -> 0 | G20: =SUMPRODUCT(('WBS Schedule'!AK21:AK30=1)*'WBS Schedule'!$N$21:$N$30) -> 0 | H20: =SUMPRODUCT(('WBS Schedule'!AK33:AK42=1)*'WBS Schedule'!$N$33:$N$42) -> 0 | I20: =SUMPRODUCT(('WBS Schedule'!AK45:AK54=1)*'WBS Schedule'!$N$45:$N$54) -> 6 | J20: =SUMPRODUCT(('WBS Schedule'!AK57:AK67=1)*'WBS Schedule'!$N$57:$N$67) -> 0 | K20: 1 | L20: W16
A21: 17 | B21: =ProjectStart-WEEKDAY(ProjectStart,3)+112 -> 46426 | C21: =B21+4 -> 46430 | D21: =SUM(R71:R121) -> 81.6 | E21: =COUNTIFS('WBS Schedule'!$B$7:$B$68,2,'WBS Schedule'!$G$7:$G$68,">0")-COUNTIFS('WBS Schedule'!$B$7:$B$68,2,'WBS Schedule'!$G$7:$G$68,">0",'WBS Schedule'!$I$7:$I$68,"<="&C21) -> 11 | F21: =SUMPRODUCT(('WBS Schedule'!AL9:AL18=1)*'WBS Schedule'!$N$9:$N$18) -> 0 | G21: =SUMPRODUCT(('WBS Schedule'!AL21:AL30=1)*'WBS Schedule'!$N$21:$N$30) -> 0 | H21: =SUMPRODUCT(('WBS Schedule'!AL33:AL42=1)*'WBS Schedule'!$N$33:$N$42) -> 0 | I21: =SUMPRODUCT(('WBS Schedule'!AL45:AL54=1)*'WBS Schedule'!$N$45:$N$54) -> 4 | J21: =SUMPRODUCT(('WBS Schedule'!AL57:AL67=1)*'WBS Schedule'!$N$57:$N$67) -> 0 | K21: 1 | L21: W17
A22: 18 | B22: =ProjectStart-WEEKDAY(ProjectStart,3)+119 -> 46433 | C22: =B22+4 -> 46437 | D22: =SUM(S71:S121) -> 91.52 | E22: =COUNTIFS('WBS Schedule'!$B$7:$B$68,2,'WBS Schedule'!$G$7:$G$68,">0")-COUNTIFS('WBS Schedule'!$B$7:$B$68,2,'WBS Schedule'!$G$7:$G$68,">0",'WBS Schedule'!$I$7:$I$68,"<="&C22) -> 8 | F22: =SUMPRODUCT(('WBS Schedule'!AM9:AM18=1)*'WBS Schedule'!$N$9:$N$18) -> 0 | G22: =SUMPRODUCT(('WBS Schedule'!AM21:AM30=1)*'WBS Schedule'!$N$21:$N$30) -> 0 | H22: =SUMPRODUCT(('WBS Schedule'!AM33:AM42=1)*'WBS Schedule'!$N$33:$N$42) -> 0 | I22: =SUMPRODUCT(('WBS Schedule'!AM45:AM54=1)*'WBS Schedule'!$N$45:$N$54) -> 0 | J22: =SUMPRODUCT(('WBS Schedule'!AM57:AM67=1)*'WBS Schedule'!$N$57:$N$67) -> 11 | K22: 1 | L22: W18
A23: 19 | B23: =ProjectStart-WEEKDAY(ProjectStart,3)+126 -> 46440 | C23: =B23+4 -> 46444 | D23: =SUM(T71:T121) -> 96.64 | E23: =COUNTIFS('WBS Schedule'!$B$7:$B$68,2,'WBS Schedule'!$G$7:$G$68,">0")-COUNTIFS('WBS Schedule'!$B$7:$B$68,2,'WBS Schedule'!$G$7:$G$68,">0",'WBS Schedule'!$I$7:$I$68,"<="&C23) -> 6 | F23: =SUMPRODUCT(('WBS Schedule'!AN9:AN18=1)*'WBS Schedule'!$N$9:$N$18) -> 0 | G23: =SUMPRODUCT(('WBS Schedule'!AN21:AN30=1)*'WBS Schedule'!$N$21:$N$30) -> 0 | H23: =SUMPRODUCT(('WBS Schedule'!AN33:AN42=1)*'WBS Schedule'!$N$33:$N$42) -> 0 | I23: =SUMPRODUCT(('WBS Schedule'!AN45:AN54=1)*'WBS Schedule'!$N$45:$N$54) -> 0 | J23: =SUMPRODUCT(('WBS Schedule'!AN57:AN67=1)*'WBS Schedule'!$N$57:$N$67) -> 10 | K23: 1 | L23: W19
A24: 20 | B24: =ProjectStart-WEEKDAY(ProjectStart,3)+133 -> 46447 | C24: =B24+4 -> 46451 | D24: =SUM(U71:U121) -> 101.12 | E24: =COUNTIFS('WBS Schedule'!$B$7:$B$68,2,'WBS Schedule'!$G$7:$G$68,">0")-COUNTIFS('WBS Schedule'!$B$7:$B$68,2,'WBS Schedule'!$G$7:$G$68,">0",'WBS Schedule'!$I$7:$I$68,"<="&C24) -> 4 | F24: =SUMPRODUCT(('WBS Schedule'!AO9:AO18=1)*'WBS Schedule'!$N$9:$N$18) -> 0 | G24: =SUMPRODUCT(('WBS Schedule'!AO21:AO30=1)*'WBS Schedule'!$N$21:$N$30) -> 0 | H24: =SUMPRODUCT(('WBS Schedule'!AO33:AO42=1)*'WBS Schedule'!$N$33:$N$42) -> 0 | I24: =SUMPRODUCT(('WBS Schedule'!AO45:AO54=1)*'WBS Schedule'!$N$45:$N$54) -> 0 | J24: =SUMPRODUCT(('WBS Schedule'!AO57:AO67=1)*'WBS Schedule'!$N$57:$N$67) -> 8 | K24: 1 | L24: W20
A25: 21 | B25: =ProjectStart-WEEKDAY(ProjectStart,3)+140 -> 46454 | C25: =B25+4 -> 46458 | D25: =SUM(V71:V121) -> 105.6 | E25: =COUNTIFS('WBS Schedule'!$B$7:$B$68,2,'WBS Schedule'!$G$7:$G$68,">0")-COUNTIFS('WBS Schedule'!$B$7:$B$68,2,'WBS Schedule'!$G$7:$G$68,">0",'WBS Schedule'!$I$7:$I$68,"<="&C25) -> 0 | F25: =SUMPRODUCT(('WBS Schedule'!AP9:AP18=1)*'WBS Schedule'!$N$9:$N$18) -> 0 | G25: =SUMPRODUCT(('WBS Schedule'!AP21:AP30=1)*'WBS Schedule'!$N$21:$N$30) -> 0 | H25: =SUMPRODUCT(('WBS Schedule'!AP33:AP42=1)*'WBS Schedule'!$N$33:$N$42) -> 0 | I25: =SUMPRODUCT(('WBS Schedule'!AP45:AP54=1)*'WBS Schedule'!$N$45:$N$54) -> 0 | J25: =SUMPRODUCT(('WBS Schedule'!AP57:AP67=1)*'WBS Schedule'!$N$57:$N$67) -> 8 | K25: 1 | L25: W21
A28: Phase | B28: Planned % | C28: Actual % | D28: Budget (₹ L) | E28: Earned Value (₹ L) | F28: Actual Cost (₹ L) | G28: Start offset (days) | H28: Completed (days) | I28: Remaining (days) | J28: Status
A29: M1 Discovery | B29: ='WBS Schedule'!J8 -> 1 | C29: ='WBS Schedule'!K8 -> 1 | D29: ='WBS Schedule'!P8 -> 16.96 | E29: ='WBS Schedule'!R8 -> 16.96 | F29: ='WBS Schedule'!S8 -> 16.26 | G29: ='WBS Schedule'!H8-ProjectStart -> 0 | H29: =('WBS Schedule'!I8-'WBS Schedule'!H8+1)*C29 -> 29 | I29: =('WBS Schedule'!I8-'WBS Schedule'!H8+1)-H29 -> 0 | J29: ='WBS Schedule'!M8 -> Complete
A30: M2 AI Foundation | B30: ='WBS Schedule'!J20 -> 1 | C30: ='WBS Schedule'!K20 -> 1 | D30: ='WBS Schedule'!P20 -> 17.28 | E30: ='WBS Schedule'!R20 -> 17.28 | F30: ='WBS Schedule'!S20 -> 17.9 | G30: ='WBS Schedule'!H20-ProjectStart -> 29 | H30: =('WBS Schedule'!I20-'WBS Schedule'!H20+1)*C30 -> 29 | I30: =('WBS Schedule'!I20-'WBS Schedule'!H20+1)-H30 -> 0 | J30: ='WBS Schedule'!M20 -> Complete
A31: M3 Integration | B31: ='WBS Schedule'!J32 -> 1 | C31: ='WBS Schedule'!K32 -> 0.84459459 | D31: ='WBS Schedule'!P32 -> 23.68 | E31: ='WBS Schedule'!R32 -> 20 | F31: ='WBS Schedule'!S32 -> 22.28 | G31: ='WBS Schedule'!H32-ProjectStart -> 58 | H31: =('WBS Schedule'!I32-'WBS Schedule'!H32+1)*C31 -> 25.337838 | I31: =('WBS Schedule'!I32-'WBS Schedule'!H32+1)-H31 -> 4.6621622 | J31: ='WBS Schedule'!M32 -> Overdue
A32: M4 Security & QA | B32: ='WBS Schedule'!J44 -> 0.081081081 | C32: ='WBS Schedule'!K44 -> 0.091891892 | D32: ='WBS Schedule'!P44 -> 23.68 | E32: ='WBS Schedule'!R44 -> 2.176 | F32: ='WBS Schedule'!S44 -> 2.18 | G32: ='WBS Schedule'!H44-ProjectStart -> 88 | H32: =('WBS Schedule'!I44-'WBS Schedule'!H44+1)*C32 -> 2.6648649 | I32: =('WBS Schedule'!I44-'WBS Schedule'!H44+1)-H32 -> 26.335135 | J32: ='WBS Schedule'!M44 -> In Progress
A33: M5 Pilot & Handover | B33: ='WBS Schedule'!J56 -> 0 | C33: ='WBS Schedule'!K56 -> 0 | D33: ='WBS Schedule'!P56 -> 24 | E33: ='WBS Schedule'!R56 -> 0 | F33: ='WBS Schedule'!S56 -> 0 | G33: ='WBS Schedule'!H56-ProjectStart -> 119 | H33: =('WBS Schedule'!I56-'WBS Schedule'!H56+1)*C33 -> 0 | I33: =('WBS Schedule'!I56-'WBS Schedule'!H56+1)-H33 -> 26 | J33: ='WBS Schedule'!M56 -> Not Started
A36: Activity Status | B36: Count
A37: Complete | B37: =COUNTIFS('WBS Schedule'!$B$7:$B$68,2,'WBS Schedule'!$G$7:$G$68,">0",'WBS Schedule'!$M$7:$M$68,"Complete") -> 27
A38: In Progress | B38: =COUNTIFS('WBS Schedule'!$B$7:$B$68,2,'WBS Schedule'!$G$7:$G$68,">0",'WBS Schedule'!$M$7:$M$68,"In Progress") -> 2
A39: Behind | B39: =COUNTIFS('WBS Schedule'!$B$7:$B$68,2,'WBS Schedule'!$G$7:$G$68,">0",'WBS Schedule'!$M$7:$M$68,"Behind") -> 0
A40: Overdue | B40: =COUNTIFS('WBS Schedule'!$B$7:$B$68,2,'WBS Schedule'!$G$7:$G$68,">0",'WBS Schedule'!$M$7:$M$68,"Overdue") -> 4
A41: Late Start | B41: =COUNTIFS('WBS Schedule'!$B$7:$B$68,2,'WBS Schedule'!$G$7:$G$68,">0",'WBS Schedule'!$M$7:$M$68,"Late Start") -> 0
A42: Not Started | B42: =COUNTIFS('WBS Schedule'!$B$7:$B$68,2,'WBS Schedule'!$G$7:$G$68,">0",'WBS Schedule'!$M$7:$M$68,"Not Started") -> 18
A45: Open Risk Rating | B45: Count
A46: High | B46: =COUNTIFS('RAID Log'!$B$5:$B$22,"Risk",'RAID Log'!$H$5:$H$22,"High",'RAID Log'!$K$5:$K$22,"<>Closed") -> 2
A47: Medium | B47: =COUNTIFS('RAID Log'!$B$5:$B$22,"Risk",'RAID Log'!$H$5:$H$22,"Medium",'RAID Log'!$K$5:$K$22,"<>Closed") -> 6
A48: Low | B48: =COUNTIFS('RAID Log'!$B$5:$B$22,"Risk",'RAID Log'!$H$5:$H$22,"Low",'RAID Log'!$K$5:$K$22,"<>Closed") -> 2
A52: RAID Type | B52: Open | C52: Monitoring | D52: Mitigated | E52: Closed
A53: Risk | B53: =COUNTIFS('RAID Log'!$B$5:$B$22,"Risk",'RAID Log'!$K$5:$K$22,"Open") -> 5 | C53: =COUNTIFS('RAID Log'!$B$5:$B$22,"Risk",'RAID Log'!$K$5:$K$22,"Monitoring") -> 3 | D53: =COUNTIFS('RAID Log'!$B$5:$B$22,"Risk",'RAID Log'!$K$5:$K$22,"Mitigated") -> 2 | E53: =COUNTIFS('RAID Log'!$B$5:$B$22,"Risk",'RAID Log'!$K$5:$K$22,"Closed") -> 0
A54: Issue | B54: =COUNTIFS('RAID Log'!$B$5:$B$22,"Issue",'RAID Log'!$K$5:$K$22,"Open") -> 2 | C54: =COUNTIFS('RAID Log'!$B$5:$B$22,"Issue",'RAID Log'!$K$5:$K$22,"Monitoring") -> 1 | D54: =COUNTIFS('RAID Log'!$B$5:$B$22,"Issue",'RAID Log'!$K$5:$K$22,"Mitigated") -> 0 | E54: =COUNTIFS('RAID Log'!$B$5:$B$22,"Issue",'RAID Log'!$K$5:$K$22,"Closed") -> 0
A55: Assumption | B55: =COUNTIFS('RAID Log'!$B$5:$B$22,"Assumption",'RAID Log'!$K$5:$K$22,"Open") -> 0 | C55: =COUNTIFS('RAID Log'!$B$5:$B$22,"Assumption",'RAID Log'!$K$5:$K$22,"Monitoring") -> 0 | D55: =COUNTIFS('RAID Log'!$B$5:$B$22,"Assumption",'RAID Log'!$K$5:$K$22,"Mitigated") -> 0 | E55: =COUNTIFS('RAID Log'!$B$5:$B$22,"Assumption",'RAID Log'!$K$5:$K$22,"Closed") -> 2
A56: Dependency | B56: =COUNTIFS('RAID Log'!$B$5:$B$22,"Dependency",'RAID Log'!$K$5:$K$22,"Open") -> 2 | C56: =COUNTIFS('RAID Log'!$B$5:$B$22,"Dependency",'RAID Log'!$K$5:$K$22,"Monitoring") -> 1 | D56: =COUNTIFS('RAID Log'!$B$5:$B$22,"Dependency",'RAID Log'!$K$5:$K$22,"Mitigated") -> 0 | E56: =COUNTIFS('RAID Log'!$B$5:$B$22,"Dependency",'RAID Log'!$K$5:$K$22,"Closed") -> 0
A69: Helper — cumulative planned value by activity and week (₹ L)
A70: WBS ID | B70: W1 | C70: W2 | D70: W3 | E70: W4 | F70: W5 | G70: W6 | H70: W7 | I70: W8 | J70: W9 | K70: W10 | L70: W11 | M70: W12 | N70: W13 | O70: W14 | P70: W15 | Q70: W16 | R70: W17 | S70: W18 | T70: W19 | U70: W20 | V70: W21
A71: ='WBS Schedule'!A9 -> 1.1 | B71: =IF($C$5<'WBS Schedule'!$H$9,0,MIN(1,NETWORKDAYS('WBS Schedule'!$H$9,$C$5,Holidays)/'WBS Schedule'!$G$9))*'WBS Schedule'!$P$9 -> 1.92 | C71: =IF($C$6<'WBS Schedule'!$H$9,0,MIN(1,NETWORKDAYS('WBS Schedule'!$H$9,$C$6,Holidays)/'WBS Schedule'!$G$9))*'WBS Schedule'!$P$9 -> 1.92 | D71: =IF($C$7<'WBS Schedule'!$H$9,0,MIN(1,NETWORKDAYS('WBS Schedule'!$H$9,$C$7,Holidays)/'WBS Schedule'!$G$9))*'WBS Schedule'!$P$9 -> 1.92 | E71: =IF($C$8<'WBS Schedule'!$H$9,0,MIN(1,NETWORKDAYS('WBS Schedule'!$H$9,$C$8,Holidays)/'WBS Schedule'!$G$9))*'WBS Schedule'!$P$9 -> 1.92 | F71: =IF($C$9<'WBS Schedule'!$H$9,0,MIN(1,NETWORKDAYS('WBS Schedule'!$H$9,$C$9,Holidays)/'WBS Schedule'!$G$9))*'WBS Schedule'!$P$9 -> 1.92 | G71: =IF($C$10<'WBS Schedule'!$H$9,0,MIN(1,NETWORKDAYS('WBS Schedule'!$H$9,$C$10,Holidays)/'WBS Schedule'!$G$9))*'WBS Schedule'!$P$9 -> 1.92 | H71: =IF($C$11<'WBS Schedule'!$H$9,0,MIN(1,NETWORKDAYS('WBS Schedule'!$H$9,$C$11,Holidays)/'WBS Schedule'!$G$9))*'WBS Schedule'!$P$9 -> 1.92 | I71: =IF($C$12<'WBS Schedule'!$H$9,0,MIN(1,NETWORKDAYS('WBS Schedule'!$H$9,$C$12,Holidays)/'WBS Schedule'!$G$9))*'WBS Schedule'!$P$9 -> 1.92 | J71: =IF($C$13<'WBS Schedule'!$H$9,0,MIN(1,NETWORKDAYS('WBS Schedule'!$H$9,$C$13,Holidays)/'WBS Schedule'!$G$9))*'WBS Schedule'!$P$9 -> 1.92 | K71: =IF($C$14<'WBS Schedule'!$H$9,0,MIN(1,NETWORKDAYS('WBS Schedule'!$H$9,$C$14,Holidays)/'WBS Schedule'!$G$9))*'WBS Schedule'!$P$9 -> 1.92 | L71: =IF($C$15<'WBS Schedule'!$H$9,0,MIN(1,NETWORKDAYS('WBS Schedule'!$H$9,$C$15,Holidays)/'WBS Schedule'!$G$9))*'WBS Schedule'!$P$9 -> 1.92 | M71: =IF($C$16<'WBS Schedule'!$H$9,0,MIN(1,NETWORKDAYS('WBS Schedule'!$H$9,$C$16,Holidays)/'WBS Schedule'!$G$9))*'WBS Schedule'!$P$9 -> 1.92 | N71: =IF($C$17<'WBS Schedule'!$H$9,0,MIN(1,NETWORKDAYS('WBS Schedule'!$H$9,$C$17,Holidays)/'WBS Schedule'!$G$9))*'WBS Schedule'!$P$9 -> 1.92 | O71: =IF($C$18<'WBS Schedule'!$H$9,0,MIN(1,NETWORKDAYS('WBS Schedule'!$H$9,$C$18,Holidays)/'WBS Schedule'!$G$9))*'WBS Schedule'!$P$9 -> 1.92 | P71: =IF($C$19<'WBS Schedule'!$H$9,0,MIN(1,NETWORKDAYS('WBS Schedule'!$H$9,$C$19,Holidays)/'WBS Schedule'!$G$9))*'WBS Schedule'!$P$9 -> 1.92 | Q71: =IF($C$20<'WBS Schedule'!$H$9,0,MIN(1,NETWORKDAYS('WBS Schedule'!$H$9,$C$20,Holidays)/'WBS Schedule'!$G$9))*'WBS Schedule'!$P$9 -> 1.92 | R71: =IF($C$21<'WBS Schedule'!$H$9,0,MIN(1,NETWORKDAYS('WBS Schedule'!$H$9,$C$21,Holidays)/'WBS Schedule'!$G$9))*'WBS Schedule'!$P$9 -> 1.92 | S71: =IF($C$22<'WBS Schedule'!$H$9,0,MIN(1,NETWORKDAYS('WBS Schedule'!$H$9,$C$22,Holidays)/'WBS Schedule'!$G$9))*'WBS Schedule'!$P$9 -> 1.92 | T71: =IF($C$23<'WBS Schedule'!$H$9,0,MIN(1,NETWORKDAYS('WBS Schedule'!$H$9,$C$23,Holidays)/'WBS Schedule'!$G$9))*'WBS Schedule'!$P$9 -> 1.92 | U71: =IF($C$24<'WBS Schedule'!$H$9,0,MIN(1,NETWORKDAYS('WBS Schedule'!$H$9,$C$24,Holidays)/'WBS Schedule'!$G$9))*'WBS Schedule'!$P$9 -> 1.92 | V71: =IF($C$25<'WBS Schedule'!$H$9,0,MIN(1,NETWORKDAYS('WBS Schedule'!$H$9,$C$25,Holidays)/'WBS Schedule'!$G$9))*'WBS Schedule'!$P$9 -> 1.92
A72: ='WBS Schedule'!A10 -> 1.2 | B72: =IF($C$5<'WBS Schedule'!$H$10,0,MIN(1,NETWORKDAYS('WBS Schedule'!$H$10,$C$5,Holidays)/'WBS Schedule'!$G$10))*'WBS Schedule'!$P$10 -> 1.28 | C72: =IF($C$6<'WBS Schedule'!$H$10,0,MIN(1,NETWORKDAYS('WBS Schedule'!$H$10,$C$6,Holidays)/'WBS Schedule'!$G$10))*'WBS Schedule'!$P$10 -> 1.28 | D72: =IF($C$7<'WBS Schedule'!$H$10,0,MIN(1,NETWORKDAYS('WBS Schedule'!$H$10,$C$7,Holidays)/'WBS Schedule'!$G$10))*'WBS Schedule'!$P$10 -> 1.28 | E72: =IF($C$8<'WBS Schedule'!$H$10,0,MIN(1,NETWORKDAYS('WBS Schedule'!$H$10,$C$8,Holidays)/'WBS Schedule'!$G$10))*'WBS Schedule'!$P$10 -> 1.28 | F72: =IF($C$9<'WBS Schedule'!$H$10,0,MIN(1,NETWORKDAYS('WBS Schedule'!$H$10,$C$9,Holidays)/'WBS Schedule'!$G$10))*'WBS Schedule'!$P$10 -> 1.28 | G72: =IF($C$10<'WBS Schedule'!$H$10,0,MIN(1,NETWORKDAYS('WBS Schedule'!$H$10,$C$10,Holidays)/'WBS Schedule'!$G$10))*'WBS Schedule'!$P$10 -> 1.28 | H72: =IF($C$11<'WBS Schedule'!$H$10,0,MIN(1,NETWORKDAYS('WBS Schedule'!$H$10,$C$11,Holidays)/'WBS Schedule'!$G$10))*'WBS Schedule'!$P$10 -> 1.28 | I72: =IF($C$12<'WBS Schedule'!$H$10,0,MIN(1,NETWORKDAYS('WBS Schedule'!$H$10,$C$12,Holidays)/'WBS Schedule'!$G$10))*'WBS Schedule'!$P$10 -> 1.28 | J72: =IF($C$13<'WBS Schedule'!$H$10,0,MIN(1,NETWORKDAYS('WBS Schedule'!$H$10,$C$13,Holidays)/'WBS Schedule'!$G$10))*'WBS Schedule'!$P$10 -> 1.28 | K72: =IF($C$14<'WBS Schedule'!$H$10,0,MIN(1,NETWORKDAYS('WBS Schedule'!$H$10,$C$14,Holidays)/'WBS Schedule'!$G$10))*'WBS Schedule'!$P$10 -> 1.28 | L72: =IF($C$15<'WBS Schedule'!$H$10,0,MIN(1,NETWORKDAYS('WBS Schedule'!$H$10,$C$15,Holidays)/'WBS Schedule'!$G$10))*'WBS Schedule'!$P$10 -> 1.28 | M72: =IF($C$16<'WBS Schedule'!$H$10,0,MIN(1,NETWORKDAYS('WBS Schedule'!$H$10,$C$16,Holidays)/'WBS Schedule'!$G$10))*'WBS Schedule'!$P$10 -> 1.28 | N72: =IF($C$17<'WBS Schedule'!$H$10,0,MIN(1,NETWORKDAYS('WBS Schedule'!$H$10,$C$17,Holidays)/'WBS Schedule'!$G$10))*'WBS Schedule'!$P$10 -> 1.28 | O72: =IF($C$18<'WBS Schedule'!$H$10,0,MIN(1,NETWORKDAYS('WBS Schedule'!$H$10,$C$18,Holidays)/'WBS Schedule'!$G$10))*'WBS Schedule'!$P$10 -> 1.28 | P72: =IF($C$19<'WBS Schedule'!$H$10,0,MIN(1,NETWORKDAYS('WBS Schedule'!$H$10,$C$19,Holidays)/'WBS Schedule'!$G$10))*'WBS Schedule'!$P$10 -> 1.28 | Q72: =IF($C$20<'WBS Schedule'!$H$10,0,MIN(1,NETWORKDAYS('WBS Schedule'!$H$10,$C$20,Holidays)/'WBS Schedule'!$G$10))*'WBS Schedule'!$P$10 -> 1.28 | R72: =IF($C$21<'WBS Schedule'!$H$10,0,MIN(1,NETWORKDAYS('WBS Schedule'!$H$10,$C$21,Holidays)/'WBS Schedule'!$G$10))*'WBS Schedule'!$P$10 -> 1.28 | S72: =IF($C$22<'WBS Schedule'!$H$10,0,MIN(1,NETWORKDAYS('WBS Schedule'!$H$10,$C$22,Holidays)/'WBS Schedule'!$G$10))*'WBS Schedule'!$P$10 -> 1.28 | T72: =IF($C$23<'WBS Schedule'!$H$10,0,MIN(1,NETWORKDAYS('WBS Schedule'!$H$10,$C$23,Holidays)/'WBS Schedule'!$G$10))*'WBS Schedule'!$P$10 -> 1.28 | U72: =IF($C$24<'WBS Schedule'!$H$10,0,MIN(1,NETWORKDAYS('WBS Schedule'!$H$10,$C$24,Holidays)/'WBS Schedule'!$G$10))*'WBS Schedule'!$P$10 -> 1.28 | V72: =IF($C$25<'WBS Schedule'!$H$10,0,MIN(1,NETWORKDAYS('WBS Schedule'!$H$10,$C$25,Holidays)/'WBS Schedule'!$G$10))*'WBS Schedule'!$P$10 -> 1.28
A73: ='WBS Schedule'!A11 -> 1.3 | B73: =IF($C$5<'WBS Schedule'!$H$11,0,MIN(1,NETWORKDAYS('WBS Schedule'!$H$11,$C$5,Holidays)/'WBS Schedule'!$G$11))*'WBS Schedule'!$P$11 -> 2.88 | C73: =IF($C$6<'WBS Schedule'!$H$11,0,MIN(1,NETWORKDAYS('WBS Schedule'!$H$11,$C$6,Holidays)/'WBS Schedule'!$G$11))*'WBS Schedule'!$P$11 -> 2.88 | D73: =IF($C$7<'WBS Schedule'!$H$11,0,MIN(1,NETWORKDAYS('WBS Schedule'!$H$11,$C$7,Holidays)/'WBS Schedule'!$G$11))*'WBS Schedule'!$P$11 -> 2.88 | E73: =IF($C$8<'WBS Schedule'!$H$11,0,MIN(1,NETWORKDAYS('WBS Schedule'!$H$11,$C$8,Holidays)/'WBS Schedule'!$G$11))*'WBS Schedule'!$P$11 -> 2.88 | F73: =IF($C$9<'WBS Schedule'!$H$11,0,MIN(1,NETWORKDAYS('WBS Schedule'!$H$11,$C$9,Holidays)/'WBS Schedule'!$G$11))*'WBS Schedule'!$P$11 -> 2.88 | G73: =IF($C$10<'WBS Schedule'!$H$11,0,MIN(1,NETWORKDAYS('WBS Schedule'!$H$11,$C$10,Holidays)/'WBS Schedule'!$G$11))*'WBS Schedule'!$P$11 -> 2.88 | H73: =IF($C$11<'WBS Schedule'!$H$11,0,MIN(1,NETWORKDAYS('WBS Schedule'!$H$11,$C$11,Holidays)/'WBS Schedule'!$G$11))*'WBS Schedule'!$P$11 -> 2.88 | I73: =IF($C$12<'WBS Schedule'!$H$11,0,MIN(1,NETWORKDAYS('WBS Schedule'!$H$11,$C$12,Holidays)/'WBS Schedule'!$G$11))*'WBS Schedule'!$P$11 -> 2.88 | J73: =IF($C$13<'WBS Schedule'!$H$11,0,MIN(1,NETWORKDAYS('WBS Schedule'!$H$11,$C$13,Holidays)/'WBS Schedule'!$G$11))*'WBS Schedule'!$P$11 -> 2.88 | K73: =IF($C$14<'WBS Schedule'!$H$11,0,MIN(1,NETWORKDAYS('WBS Schedule'!$H$11,$C$14,Holidays)/'WBS Schedule'!$G$11))*'WBS Schedule'!$P$11 -> 2.88 | L73: =IF($C$15<'WBS Schedule'!$H$11,0,MIN(1,NETWORKDAYS('WBS Schedule'!$H$11,$C$15,Holidays)/'WBS Schedule'!$G$11))*'WBS Schedule'!$P$11 -> 2.88 | M73: =IF($C$16<'WBS Schedule'!$H$11,0,MIN(1,NETWORKDAYS('WBS Schedule'!$H$11,$C$16,Holidays)/'WBS Schedule'!$G$11))*'WBS Schedule'!$P$11 -> 2.88 | N73: =IF($C$17<'WBS Schedule'!$H$11,0,MIN(1,NETWORKDAYS('WBS Schedule'!$H$11,$C$17,Holidays)/'WBS Schedule'!$G$11))*'WBS Schedule'!$P$11 -> 2.88 | O73: =IF($C$18<'WBS Schedule'!$H$11,0,MIN(1,NETWORKDAYS('WBS Schedule'!$H$11,$C$18,Holidays)/'WBS Schedule'!$G$11))*'WBS Schedule'!$P$11 -> 2.88 | P73: =IF($C$19<'WBS Schedule'!$H$11,0,MIN(1,NETWORKDAYS('WBS Schedule'!$H$11,$C$19,Holidays)/'WBS Schedule'!$G$11))*'WBS Schedule'!$P$11 -> 2.88 | Q73: =IF($C$20<'WBS Schedule'!$H$11,0,MIN(1,NETWORKDAYS('WBS Schedule'!$H$11,$C$20,Holidays)/'WBS Schedule'!$G$11))*'WBS Schedule'!$P$11 -> 2.88 | R73: =IF($C$21<'WBS Schedule'!$H$11,0,MIN(1,NETWORKDAYS('WBS Schedule'!$H$11,$C$21,Holidays)/'WBS Schedule'!$G$11))*'WBS Schedule'!$P$11 -> 2.88 | S73: =IF($C$22<'WBS Schedule'!$H$11,0,MIN(1,NETWORKDAYS('WBS Schedule'!$H$11,$C$22,Holidays)/'WBS Schedule'!$G$11))*'WBS Schedule'!$P$11 -> 2.88 | T73: =IF($C$23<'WBS Schedule'!$H$11,0,MIN(1,NETWORKDAYS('WBS Schedule'!$H$11,$C$23,Holidays)/'WBS Schedule'!$G$11))*'WBS Schedule'!$P$11 -> 2.88 | U73: =IF($C$24<'WBS Schedule'!$H$11,0,MIN(1,NETWORKDAYS('WBS Schedule'!$H$11,$C$24,Holidays)/'WBS Schedule'!$G$11))*'WBS Schedule'!$P$11 -> 2.88 | V73: =IF($C$25<'WBS Schedule'!$H$11,0,MIN(1,NETWORKDAYS('WBS Schedule'!$H$11,$C$25,Holidays)/'WBS Schedule'!$G$11))*'WBS Schedule'!$P$11 -> 2.88
A74: ='WBS Schedule'!A12 -> 1.4 | B74: =IF($C$5<'WBS Schedule'!$H$12,0,MIN(1,NETWORKDAYS('WBS Schedule'!$H$12,$C$5,Holidays)/'WBS Schedule'!$G$12))*'WBS Schedule'!$P$12 -> 0 | C74: =IF($C$6<'WBS Schedule'!$H$12,0,MIN(1,NETWORKDAYS('WBS Schedule'!$H$12,$C$6,Holidays)/'WBS Schedule'!$G$12))*'WBS Schedule'!$P$12 -> 1.92 | D74: =IF($C$7<'WBS Schedule'!$H$12,0,MIN(1,NETWORKDAYS('WBS Schedule'!$H$12,$C$7,Holidays)/'WBS Schedule'!$G$12))*'WBS Schedule'!$P$12 -> 1.92 | E74: =IF($C$8<'WBS Schedule'!$H$12,0,MIN(1,NETWORKDAYS('WBS Schedule'!$H$12,$C$8,Holidays)/'WBS Schedule'!$G$12))*'WBS Schedule'!$P$12 -> 1.92 | F74: =IF($C$9<'WBS Schedule'!$H$12,0,MIN(1,NETWORKDAYS('WBS Schedule'!$H$12,$C$9,Holidays)/'WBS Schedule'!$G$12))*'WBS Schedule'!$P$12 -> 1.92 | G74: =IF($C$10<'WBS Schedule'!$H$12,0,MIN(1,NETWORKDAYS('WBS Schedule'!$H$12,$C$10,Holidays)/'WBS Schedule'!$G$12))*'WBS Schedule'!$P$12 -> 1.92 | H74: =IF($C$11<'WBS Schedule'!$H$12,0,MIN(1,NETWORKDAYS('WBS Schedule'!$H$12,$C$11,Holidays)/'WBS Schedule'!$G$12))*'WBS Schedule'!$P$12 -> 1.92 | I74: =IF($C$12<'WBS Schedule'!$H$12,0,MIN(1,NETWORKDAYS('WBS Schedule'!$H$12,$C$12,Holidays)/'WBS Schedule'!$G$12))*'WBS Schedule'!$P$12 -> 1.92 | J74: =IF($C$13<'WBS Schedule'!$H$12,0,MIN(1,NETWORKDAYS('WBS Schedule'!$H$12,$C$13,Holidays)/'WBS Schedule'!$G$12))*'WBS Schedule'!$P$12 -> 1.92 | K74: =IF($C$14<'WBS Schedule'!$H$12,0,MIN(1,NETWORKDAYS('WBS Schedule'!$H$12,$C$14,Holidays)/'WBS Schedule'!$G$12))*'WBS Schedule'!$P$12 -> 1.92 | L74: =IF($C$15<'WBS Schedule'!$H$12,0,MIN(1,NETWORKDAYS('WBS Schedule'!$H$12,$C$15,Holidays)/'WBS Schedule'!$G$12))*'WBS Schedule'!$P$12 -> 1.92 | M74: =IF($C$16<'WBS Schedule'!$H$12,0,MIN(1,NETWORKDAYS('WBS Schedule'!$H$12,$C$16,Holidays)/'WBS Schedule'!$G$12))*'WBS Schedule'!$P$12 -> 1.92 | N74: =IF($C$17<'WBS Schedule'!$H$12,0,MIN(1,NETWORKDAYS('WBS Schedule'!$H$12,$C$17,Holidays)/'WBS Schedule'!$G$12))*'WBS Schedule'!$P$12 -> 1.92 | O74: =IF($C$18<'WBS Schedule'!$H$12,0,MIN(1,NETWORKDAYS('WBS Schedule'!$H$12,$C$18,Holidays)/'WBS Schedule'!$G$12))*'WBS Schedule'!$P$12 -> 1.92 | P74: =IF($C$19<'WBS Schedule'!$H$12,0,MIN(1,NETWORKDAYS('WBS Schedule'!$H$12,$C$19,Holidays)/'WBS Schedule'!$G$12))*'WBS Schedule'!$P$12 -> 1.92 | Q74: =IF($C$20<'WBS Schedule'!$H$12,0,MIN(1,NETWORKDAYS('WBS Schedule'!$H$12,$C$20,Holidays)/'WBS Schedule'!$G$12))*'WBS Schedule'!$P$12 -> 1.92 | R74: =IF($C$21<'WBS Schedule'!$H$12,0,MIN(1,NETWORKDAYS('WBS Schedule'!$H$12,$C$21,Holidays)/'WBS Schedule'!$G$12))*'WBS Schedule'!$P$12 -> 1.92 | S74: =IF($C$22<'WBS Schedule'!$H$12,0,MIN(1,NETWORKDAYS('WBS Schedule'!$H$12,$C$22,Holidays)/'WBS Schedule'!$G$12))*'WBS Schedule'!$P$12 -> 1.92 | T74: =IF($C$23<'WBS Schedule'!$H$12,0,MIN(1,NETWORKDAYS('WBS Schedule'!$H$12,$C$23,Holidays)/'WBS Schedule'!$G$12))*'WBS Schedule'!$P$12 -> 1.92 | U74: =IF($C$24<'WBS Schedule'!$H$12,0,MIN(1,NETWORKDAYS('WBS Schedule'!$H$12,$C$24,Holidays)/'WBS Schedule'!$G$12))*'WBS Schedule'!$P$12 -> 1.92 | V74: =IF($C$25<'WBS Schedule'!$H$12,0,MIN(1,NETWORKDAYS('WBS Schedule'!$H$12,$C$25,Holidays)/'WBS Schedule'!$G$12))*'WBS Schedule'!$P$12 -> 1.92
A75: ='WBS Schedule'!A13 -> 1.5 | B75: =IF($C$5<'WBS Schedule'!$H$13,0,MIN(1,NETWORKDAYS('WBS Schedule'!$H$13,$C$5,Holidays)/'WBS Schedule'!$G$13))*'WBS Schedule'!$P$13 -> 0 | C75: =IF($C$6<'WBS Schedule'!$H$13,0,MIN(1,NETWORKDAYS('WBS Schedule'!$H$13,$C$6,Holidays)/'WBS Schedule'!$G$13))*'WBS Schedule'!$P$13 -> 1.92 | D75: =IF($C$7<'WBS Schedule'!$H$13,0,MIN(1,NETWORKDAYS('WBS Schedule'!$H$13,$C$7,Holidays)/'WBS Schedule'!$G$13))*'WBS Schedule'!$P$13 -> 1.92 | E75: =IF($C$8<'WBS Schedule'!$H$13,0,MIN(1,NETWORKDAYS('WBS Schedule'!$H$13,$C$8,Holidays)/'WBS Schedule'!$G$13))*'WBS Schedule'!$P$13 -> 1.92 | F75: =IF($C$9<'WBS Schedule'!$H$13,0,MIN(1,NETWORKDAYS('WBS Schedule'!$H$13,$C$9,Holidays)/'WBS Schedule'!$G$13))*'WBS Schedule'!$P$13 -> 1.92 | G75: =IF($C$10<'WBS Schedule'!$H$13,0,MIN(1,NETWORKDAYS('WBS Schedule'!$H$13,$C$10,Holidays)/'WBS Schedule'!$G$13))*'WBS Schedule'!$P$13 -> 1.92 | H75: =IF($C$11<'WBS Schedule'!$H$13,0,MIN(1,NETWORKDAYS('WBS Schedule'!$H$13,$C$11,Holidays)/'WBS Schedule'!$G$13))*'WBS Schedule'!$P$13 -> 1.92 | I75: =IF($C$12<'WBS Schedule'!$H$13,0,MIN(1,NETWORKDAYS('WBS Schedule'!$H$13,$C$12,Holidays)/'WBS Schedule'!$G$13))*'WBS Schedule'!$P$13 -> 1.92 | J75: =IF($C$13<'WBS Schedule'!$H$13,0,MIN(1,NETWORKDAYS('WBS Schedule'!$H$13,$C$13,Holidays)/'WBS Schedule'!$G$13))*'WBS Schedule'!$P$13 -> 1.92 | K75: =IF($C$14<'WBS Schedule'!$H$13,0,MIN(1,NETWORKDAYS('WBS Schedule'!$H$13,$C$14,Holidays)/'WBS Schedule'!$G$13))*'WBS Schedule'!$P$13 -> 1.92 | L75: =IF($C$15<'WBS Schedule'!$H$13,0,MIN(1,NETWORKDAYS('WBS Schedule'!$H$13,$C$15,Holidays)/'WBS Schedule'!$G$13))*'WBS Schedule'!$P$13 -> 1.92 | M75: =IF($C$16<'WBS Schedule'!$H$13,0,MIN(1,NETWORKDAYS('WBS Schedule'!$H$13,$C$16,Holidays)/'WBS Schedule'!$G$13))*'WBS Schedule'!$P$13 -> 1.92 | N75: =IF($C$17<'WBS Schedule'!$H$13,0,MIN(1,NETWORKDAYS('WBS Schedule'!$H$13,$C$17,Holidays)/'WBS Schedule'!$G$13))*'WBS Schedule'!$P$13 -> 1.92 | O75: =IF($C$18<'WBS Schedule'!$H$13,0,MIN(1,NETWORKDAYS('WBS Schedule'!$H$13,$C$18,Holidays)/'WBS Schedule'!$G$13))*'WBS Schedule'!$P$13 -> 1.92 | P75: =IF($C$19<'WBS Schedule'!$H$13,0,MIN(1,NETWORKDAYS('WBS Schedule'!$H$13,$C$19,Holidays)/'WBS Schedule'!$G$13))*'WBS Schedule'!$P$13 -> 1.92 | Q75: =IF($C$20<'WBS Schedule'!$H$13,0,MIN(1,NETWORKDAYS('WBS Schedule'!$H$13,$C$20,Holidays)/'WBS Schedule'!$G$13))*'WBS Schedule'!$P$13 -> 1.92 | R75: =IF($C$21<'WBS Schedule'!$H$13,0,MIN(1,NETWORKDAYS('WBS Schedule'!$H$13,$C$21,Holidays)/'WBS Schedule'!$G$13))*'WBS Schedule'!$P$13 -> 1.92 | S75: =IF($C$22<'WBS Schedule'!$H$13,0,MIN(1,NETWORKDAYS('WBS Schedule'!$H$13,$C$22,Holidays)/'WBS Schedule'!$G$13))*'WBS Schedule'!$P$13 -> 1.92 | T75: =IF($C$23<'WBS Schedule'!$H$13,0,MIN(1,NETWORKDAYS('WBS Schedule'!$H$13,$C$23,Holidays)/'WBS Schedule'!$G$13))*'WBS Schedule'!$P$13 -> 1.92 | U75: =IF($C$24<'WBS Schedule'!$H$13,0,MIN(1,NETWORKDAYS('WBS Schedule'!$H$13,$C$24,Holidays)/'WBS Schedule'!$G$13))*'WBS Schedule'!$P$13 -> 1.92 | V75: =IF($C$25<'WBS Schedule'!$H$13,0,MIN(1,NETWORKDAYS('WBS Schedule'!$H$13,$C$25,Holidays)/'WBS Schedule'!$G$13))*'WBS Schedule'!$P$13 -> 1.92
A76: ='WBS Schedule'!A14 -> 1.6 | B76: =IF($C$5<'WBS Schedule'!$H$14,0,MIN(1,NETWORKDAYS('WBS Schedule'!$H$14,$C$5,Holidays)/'WBS Schedule'!$G$14))*'WBS Schedule'!$P$14 -> 0 | C76: =IF($C$6<'WBS Schedule'!$H$14,0,MIN(1,NETWORKDAYS('WBS Schedule'!$H$14,$C$6,Holidays)/'WBS Schedule'!$G$14))*'WBS Schedule'!$P$14 -> 1.28 | D76: =IF($C$7<'WBS Schedule'!$H$14,0,MIN(1,NETWORKDAYS('WBS Schedule'!$H$14,$C$7,Holidays)/'WBS Schedule'!$G$14))*'WBS Schedule'!$P$14 -> 1.92 | E76: =IF($C$8<'WBS Schedule'!$H$14,0,MIN(1,NETWORKDAYS('WBS Schedule'!$H$14,$C$8,Holidays)/'WBS Schedule'!$G$14))*'WBS Schedule'!$P$14 -> 1.92 | F76: =IF($C$9<'WBS Schedule'!$H$14,0,MIN(1,NETWORKDAYS('WBS Schedule'!$H$14,$C$9,Holidays)/'WBS Schedule'!$G$14))*'WBS Schedule'!$P$14 -> 1.92 | G76: =IF($C$10<'WBS Schedule'!$H$14,0,MIN(1,NETWORKDAYS('WBS Schedule'!$H$14,$C$10,Holidays)/'WBS Schedule'!$G$14))*'WBS Schedule'!$P$14 -> 1.92 | H76: =IF($C$11<'WBS Schedule'!$H$14,0,MIN(1,NETWORKDAYS('WBS Schedule'!$H$14,$C$11,Holidays)/'WBS Schedule'!$G$14))*'WBS Schedule'!$P$14 -> 1.92 | I76: =IF($C$12<'WBS Schedule'!$H$14,0,MIN(1,NETWORKDAYS('WBS Schedule'!$H$14,$C$12,Holidays)/'WBS Schedule'!$G$14))*'WBS Schedule'!$P$14 -> 1.92 | J76: =IF($C$13<'WBS Schedule'!$H$14,0,MIN(1,NETWORKDAYS('WBS Schedule'!$H$14,$C$13,Holidays)/'WBS Schedule'!$G$14))*'WBS Schedule'!$P$14 -> 1.92 | K76: =IF($C$14<'WBS Schedule'!$H$14,0,MIN(1,NETWORKDAYS('WBS Schedule'!$H$14,$C$14,Holidays)/'WBS Schedule'!$G$14))*'WBS Schedule'!$P$14 -> 1.92 | L76: =IF($C$15<'WBS Schedule'!$H$14,0,MIN(1,NETWORKDAYS('WBS Schedule'!$H$14,$C$15,Holidays)/'WBS Schedule'!$G$14))*'WBS Schedule'!$P$14 -> 1.92 | M76: =IF($C$16<'WBS Schedule'!$H$14,0,MIN(1,NETWORKDAYS('WBS Schedule'!$H$14,$C$16,Holidays)/'WBS Schedule'!$G$14))*'WBS Schedule'!$P$14 -> 1.92 | N76: =IF($C$17<'WBS Schedule'!$H$14,0,MIN(1,NETWORKDAYS('WBS Schedule'!$H$14,$C$17,Holidays)/'WBS Schedule'!$G$14))*'WBS Schedule'!$P$14 -> 1.92 | O76: =IF($C$18<'WBS Schedule'!$H$14,0,MIN(1,NETWORKDAYS('WBS Schedule'!$H$14,$C$18,Holidays)/'WBS Schedule'!$G$14))*'WBS Schedule'!$P$14 -> 1.92 | P76: =IF($C$19<'WBS Schedule'!$H$14,0,MIN(1,NETWORKDAYS('WBS Schedule'!$H$14,$C$19,Holidays)/'WBS Schedule'!$G$14))*'WBS Schedule'!$P$14 -> 1.92 | Q76: =IF($C$20<'WBS Schedule'!$H$14,0,MIN(1,NETWORKDAYS('WBS Schedule'!$H$14,$C$20,Holidays)/'WBS Schedule'!$G$14))*'WBS Schedule'!$P$14 -> 1.92 | R76: =IF($C$21<'WBS Schedule'!$H$14,0,MIN(1,NETWORKDAYS('WBS Schedule'!$H$14,$C$21,Holidays)/'WBS Schedule'!$G$14))*'WBS Schedule'!$P$14 -> 1.92 | S76: =IF($C$22<'WBS Schedule'!$H$14,0,MIN(1,NETWORKDAYS('WBS Schedule'!$H$14,$C$22,Holidays)/'WBS Schedule'!$G$14))*'WBS Schedule'!$P$14 -> 1.92 | T76: =IF($C$23<'WBS Schedule'!$H$14,0,MIN(1,NETWORKDAYS('WBS Schedule'!$H$14,$C$23,Holidays)/'WBS Schedule'!$G$14))*'WBS Schedule'!$P$14 -> 1.92 | U76: =IF($C$24<'WBS Schedule'!$H$14,0,MIN(1,NETWORKDAYS('WBS Schedule'!$H$14,$C$24,Holidays)/'WBS Schedule'!$G$14))*'WBS Schedule'!$P$14 -> 1.92 | V76: =IF($C$25<'WBS Schedule'!$H$14,0,MIN(1,NETWORKDAYS('WBS Schedule'!$H$14,$C$25,Holidays)/'WBS Schedule'!$G$14))*'WBS Schedule'!$P$14 -> 1.92
A77: ='WBS Schedule'!A15 -> 1.7 | B77: =IF($C$5<'WBS Schedule'!$H$15,0,MIN(1,NETWORKDAYS('WBS Schedule'!$H$15,$C$5,Holidays)/'WBS Schedule'!$G$15))*'WBS Schedule'!$P$15 -> 0 | C77: =IF($C$6<'WBS Schedule'!$H$15,0,MIN(1,NETWORKDAYS('WBS Schedule'!$H$15,$C$6,Holidays)/'WBS Schedule'!$G$15))*'WBS Schedule'!$P$15 -> 1.28 | D77: =IF($C$7<'WBS Schedule'!$H$15,0,MIN(1,NETWORKDAYS('WBS Schedule'!$H$15,$C$7,Holidays)/'WBS Schedule'!$G$15))*'WBS Schedule'!$P$15 -> 1.92 | E77: =IF($C$8<'WBS Schedule'!$H$15,0,MIN(1,NETWORKDAYS('WBS Schedule'!$H$15,$C$8,Holidays)/'WBS Schedule'!$G$15))*'WBS Schedule'!$P$15 -> 1.92 | F77: =IF($C$9<'WBS Schedule'!$H$15,0,MIN(1,NETWORKDAYS('WBS Schedule'!$H$15,$C$9,Holidays)/'WBS Schedule'!$G$15))*'WBS Schedule'!$P$15 -> 1.92 | G77: =IF($C$10<'WBS Schedule'!$H$15,0,MIN(1,NETWORKDAYS('WBS Schedule'!$H$15,$C$10,Holidays)/'WBS Schedule'!$G$15))*'WBS Schedule'!$P$15 -> 1.92 | H77: =IF($C$11<'WBS Schedule'!$H$15,0,MIN(1,NETWORKDAYS('WBS Schedule'!$H$15,$C$11,Holidays)/'WBS Schedule'!$G$15))*'WBS Schedule'!$P$15 -> 1.92 | I77: =IF($C$12<'WBS Schedule'!$H$15,0,MIN(1,NETWORKDAYS('WBS Schedule'!$H$15,$C$12,Holidays)/'WBS Schedule'!$G$15))*'WBS Schedule'!$P$15 -> 1.92 | J77: =IF($C$13<'WBS Schedule'!$H$15,0,MIN(1,NETWORKDAYS('WBS Schedule'!$H$15,$C$13,Holidays)/'WBS Schedule'!$G$15))*'WBS Schedule'!$P$15 -> 1.92 | K77: =IF($C$14<'WBS Schedule'!$H$15,0,MIN(1,NETWORKDAYS('WBS Schedule'!$H$15,$C$14,Holidays)/'WBS Schedule'!$G$15))*'WBS Schedule'!$P$15 -> 1.92 | L77: =IF($C$15<'WBS Schedule'!$H$15,0,MIN(1,NETWORKDAYS('WBS Schedule'!$H$15,$C$15,Holidays)/'WBS Schedule'!$G$15))*'WBS Schedule'!$P$15 -> 1.92 | M77: =IF($C$16<'WBS Schedule'!$H$15,0,MIN(1,NETWORKDAYS('WBS Schedule'!$H$15,$C$16,Holidays)/'WBS Schedule'!$G$15))*'WBS Schedule'!$P$15 -> 1.92 | N77: =IF($C$17<'WBS Schedule'!$H$15,0,MIN(1,NETWORKDAYS('WBS Schedule'!$H$15,$C$17,Holidays)/'WBS Schedule'!$G$15))*'WBS Schedule'!$P$15 -> 1.92 | O77: =IF($C$18<'WBS Schedule'!$H$15,0,MIN(1,NETWORKDAYS('WBS Schedule'!$H$15,$C$18,Holidays)/'WBS Schedule'!$G$15))*'WBS Schedule'!$P$15 -> 1.92 | P77: =IF($C$19<'WBS Schedule'!$H$15,0,MIN(1,NETWORKDAYS('WBS Schedule'!$H$15,$C$19,Holidays)/'WBS Schedule'!$G$15))*'WBS Schedule'!$P$15 -> 1.92 | Q77: =IF($C$20<'WBS Schedule'!$H$15,0,MIN(1,NETWORKDAYS('WBS Schedule'!$H$15,$C$20,Holidays)/'WBS Schedule'!$G$15))*'WBS Schedule'!$P$15 -> 1.92 | R77: =IF($C$21<'WBS Schedule'!$H$15,0,MIN(1,NETWORKDAYS('WBS Schedule'!$H$15,$C$21,Holidays)/'WBS Schedule'!$G$15))*'WBS Schedule'!$P$15 -> 1.92 | S77: =IF($C$22<'WBS Schedule'!$H$15,0,MIN(1,NETWORKDAYS('WBS Schedule'!$H$15,$C$22,Holidays)/'WBS Schedule'!$G$15))*'WBS Schedule'!$P$15 -> 1.92 | T77: =IF($C$23<'WBS Schedule'!$H$15,0,MIN(1,NETWORKDAYS('WBS Schedule'!$H$15,$C$23,Holidays)/'WBS Schedule'!$G$15))*'WBS Schedule'!$P$15 -> 1.92 | U77: =IF($C$24<'WBS Schedule'!$H$15,0,MIN(1,NETWORKDAYS('WBS Schedule'!$H$15,$C$24,Holidays)/'WBS Schedule'!$G$15))*'WBS Schedule'!$P$15 -> 1.92 | V77: =IF($C$25<'WBS Schedule'!$H$15,0,MIN(1,NETWORKDAYS('WBS Schedule'!$H$15,$C$25,Holidays)/'WBS Schedule'!$G$15))*'WBS Schedule'!$P$15 -> 1.92
A78: ='WBS Schedule'!A16 -> 1.8 | B78: =IF($C$5<'WBS Schedule'!$H$16,0,MIN(1,NETWORKDAYS('WBS Schedule'!$H$16,$C$5,Holidays)/'WBS Schedule'!$G$16))*'WBS Schedule'!$P$16 -> 0 | C78: =IF($C$6<'WBS Schedule'!$H$16,0,MIN(1,NETWORKDAYS('WBS Schedule'!$H$16,$C$6,Holidays)/'WBS Schedule'!$G$16))*'WBS Schedule'!$P$16 -> 0 | D78: =IF($C$7<'WBS Schedule'!$H$16,0,MIN(1,NETWORKDAYS('WBS Schedule'!$H$16,$C$7,Holidays)/'WBS Schedule'!$G$16))*'WBS Schedule'!$P$16 -> 1.28 | E78: =IF($C$8<'WBS Schedule'!$H$16,0,MIN(1,NETWORKDAYS('WBS Schedule'!$H$16,$C$8,Holidays)/'WBS Schedule'!$G$16))*'WBS Schedule'!$P$16 -> 1.28 | F78: =IF($C$9<'WBS Schedule'!$H$16,0,MIN(1,NETWORKDAYS('WBS Schedule'!$H$16,$C$9,Holidays)/'WBS Schedule'!$G$16))*'WBS Schedule'!$P$16 -> 1.28 | G78: =IF($C$10<'WBS Schedule'!$H$16,0,MIN(1,NETWORKDAYS('WBS Schedule'!$H$16,$C$10,Holidays)/'WBS Schedule'!$G$16))*'WBS Schedule'!$P$16 -> 1.28 | H78: =IF($C$11<'WBS Schedule'!$H$16,0,MIN(1,NETWORKDAYS('WBS Schedule'!$H$16,$C$11,Holidays)/'WBS Schedule'!$G$16))*'WBS Schedule'!$P$16 -> 1.28 | I78: =IF($C$12<'WBS Schedule'!$H$16,0,MIN(1,NETWORKDAYS('WBS Schedule'!$H$16,$C$12,Holidays)/'WBS Schedule'!$G$16))*'WBS Schedule'!$P$16 -> 1.28 | J78: =IF($C$13<'WBS Schedule'!$H$16,0,MIN(1,NETWORKDAYS('WBS Schedule'!$H$16,$C$13,Holidays)/'WBS Schedule'!$G$16))*'WBS Schedule'!$P$16 -> 1.28 | K78: =IF($C$14<'WBS Schedule'!$H$16,0,MIN(1,NETWORKDAYS('WBS Schedule'!$H$16,$C$14,Holidays)/'WBS Schedule'!$G$16))*'WBS Schedule'!$P$16 -> 1.28 | L78: =IF($C$15<'WBS Schedule'!$H$16,0,MIN(1,NETWORKDAYS('WBS Schedule'!$H$16,$C$15,Holidays)/'WBS Schedule'!$G$16))*'WBS Schedule'!$P$16 -> 1.28 | M78: =IF($C$16<'WBS Schedule'!$H$16,0,MIN(1,NETWORKDAYS('WBS Schedule'!$H$16,$C$16,Holidays)/'WBS Schedule'!$G$16))*'WBS Schedule'!$P$16 -> 1.28 | N78: =IF($C$17<'WBS Schedule'!$H$16,0,MIN(1,NETWORKDAYS('WBS Schedule'!$H$16,$C$17,Holidays)/'WBS Schedule'!$G$16))*'WBS Schedule'!$P$16 -> 1.28 | O78: =IF($C$18<'WBS Schedule'!$H$16,0,MIN(1,NETWORKDAYS('WBS Schedule'!$H$16,$C$18,Holidays)/'WBS Schedule'!$G$16))*'WBS Schedule'!$P$16 -> 1.28 | P78: =IF($C$19<'WBS Schedule'!$H$16,0,MIN(1,NETWORKDAYS('WBS Schedule'!$H$16,$C$19,Holidays)/'WBS Schedule'!$G$16))*'WBS Schedule'!$P$16 -> 1.28 | Q78: =IF($C$20<'WBS Schedule'!$H$16,0,MIN(1,NETWORKDAYS('WBS Schedule'!$H$16,$C$20,Holidays)/'WBS Schedule'!$G$16))*'WBS Schedule'!$P$16 -> 1.28 | R78: =IF($C$21<'WBS Schedule'!$H$16,0,MIN(1,NETWORKDAYS('WBS Schedule'!$H$16,$C$21,Holidays)/'WBS Schedule'!$G$16))*'WBS Schedule'!$P$16 -> 1.28 | S78: =IF($C$22<'WBS Schedule'!$H$16,0,MIN(1,NETWORKDAYS('WBS Schedule'!$H$16,$C$22,Holidays)/'WBS Schedule'!$G$16))*'WBS Schedule'!$P$16 -> 1.28 | T78: =IF($C$23<'WBS Schedule'!$H$16,0,MIN(1,NETWORKDAYS('WBS Schedule'!$H$16,$C$23,Holidays)/'WBS Schedule'!$G$16))*'WBS Schedule'!$P$16 -> 1.28 | U78: =IF($C$24<'WBS Schedule'!$H$16,0,MIN(1,NETWORKDAYS('WBS Schedule'!$H$16,$C$24,Holidays)/'WBS Schedule'!$G$16))*'WBS Schedule'!$P$16 -> 1.28 | V78: =IF($C$25<'WBS Schedule'!$H$16,0,MIN(1,NETWORKDAYS('WBS Schedule'!$H$16,$C$25,Holidays)/'WBS Schedule'!$G$16))*'WBS Schedule'!$P$16 -> 1.28
A79: ='WBS Schedule'!A17 -> 1.9 | B79: =IF($C$5<'WBS Schedule'!$H$17,0,MIN(1,NETWORKDAYS('WBS Schedule'!$H$17,$C$5,Holidays)/'WBS Schedule'!$G$17))*'WBS Schedule'!$P$17 -> 0 | C79: =IF($C$6<'WBS Schedule'!$H$17,0,MIN(1,NETWORKDAYS('WBS Schedule'!$H$17,$C$6,Holidays)/'WBS Schedule'!$G$17))*'WBS Schedule'!$P$17 -> 0 | D79: =IF($C$7<'WBS Schedule'!$H$17,0,MIN(1,NETWORKDAYS('WBS Schedule'!$H$17,$C$7,Holidays)/'WBS Schedule'!$G$17))*'WBS Schedule'!$P$17 -> 0.64 | E79: =IF($C$8<'WBS Schedule'!$H$17,0,MIN(1,NETWORKDAYS('WBS Schedule'!$H$17,$C$8,Holidays)/'WBS Schedule'!$G$17))*'WBS Schedule'!$P$17 -> 0.64 | F79: =IF($C$9<'WBS Schedule'!$H$17,0,MIN(1,NETWORKDAYS('WBS Schedule'!$H$17,$C$9,Holidays)/'WBS Schedule'!$G$17))*'WBS Schedule'!$P$17 -> 0.64 | G79: =IF($C$10<'WBS Schedule'!$H$17,0,MIN(1,NETWORKDAYS('WBS Schedule'!$H$17,$C$10,Holidays)/'WBS Schedule'!$G$17))*'WBS Schedule'!$P$17 -> 0.64 | H79: =IF($C$11<'WBS Schedule'!$H$17,0,MIN(1,NETWORKDAYS('WBS Schedule'!$H$17,$C$11,Holidays)/'WBS Schedule'!$G$17))*'WBS Schedule'!$P$17 -> 0.64 | I79: =IF($C$12<'WBS Schedule'!$H$17,0,MIN(1,NETWORKDAYS('WBS Schedule'!$H$17,$C$12,Holidays)/'WBS Schedule'!$G$17))*'WBS Schedule'!$P$17 -> 0.64 | J79: =IF($C$13<'WBS Schedule'!$H$17,0,MIN(1,NETWORKDAYS('WBS Schedule'!$H$17,$C$13,Holidays)/'WBS Schedule'!$G$17))*'WBS Schedule'!$P$17 -> 0.64 | K79: =IF($C$14<'WBS Schedule'!$H$17,0,MIN(1,NETWORKDAYS('WBS Schedule'!$H$17,$C$14,Holidays)/'WBS Schedule'!$G$17))*'WBS Schedule'!$P$17 -> 0.64 | L79: =IF($C$15<'WBS Schedule'!$H$17,0,MIN(1,NETWORKDAYS('WBS Schedule'!$H$17,$C$15,Holidays)/'WBS Schedule'!$G$17))*'WBS Schedule'!$P$17 -> 0.64 | M79: =IF($C$16<'WBS Schedule'!$H$17,0,MIN(1,NETWORKDAYS('WBS Schedule'!$H$17,$C$16,Holidays)/'WBS Schedule'!$G$17))*'WBS Schedule'!$P$17 -> 0.64 | N79: =IF($C$17<'WBS Schedule'!$H$17,0,MIN(1,NETWORKDAYS('WBS Schedule'!$H$17,$C$17,Holidays)/'WBS Schedule'!$G$17))*'WBS Schedule'!$P$17 -> 0.64 | O79: =IF($C$18<'WBS Schedule'!$H$17,0,MIN(1,NETWORKDAYS('WBS Schedule'!$H$17,$C$18,Holidays)/'WBS Schedule'!$G$17))*'WBS Schedule'!$P$17 -> 0.64 | P79: =IF($C$19<'WBS Schedule'!$H$17,0,MIN(1,NETWORKDAYS('WBS Schedule'!$H$17,$C$19,Holidays)/'WBS Schedule'!$G$17))*'WBS Schedule'!$P$17 -> 0.64 | Q79: =IF($C$20<'WBS Schedule'!$H$17,0,MIN(1,NETWORKDAYS('WBS Schedule'!$H$17,$C$20,Holidays)/'WBS Schedule'!$G$17))*'WBS Schedule'!$P$17 -> 0.64 | R79: =IF($C$21<'WBS Schedule'!$H$17,0,MIN(1,NETWORKDAYS('WBS Schedule'!$H$17,$C$21,Holidays)/'WBS Schedule'!$G$17))*'WBS Schedule'!$P$17 -> 0.64 | S79: =IF($C$22<'WBS Schedule'!$H$17,0,MIN(1,NETWORKDAYS('WBS Schedule'!$H$17,$C$22,Holidays)/'WBS Schedule'!$G$17))*'WBS Schedule'!$P$17 -> 0.64 | T79: =IF($C$23<'WBS Schedule'!$H$17,0,MIN(1,NETWORKDAYS('WBS Schedule'!$H$17,$C$23,Holidays)/'WBS Schedule'!$G$17))*'WBS Schedule'!$P$17 -> 0.64 | U79: =IF($C$24<'WBS Schedule'!$H$17,0,MIN(1,NETWORKDAYS('WBS Schedule'!$H$17,$C$24,Holidays)/'WBS Schedule'!$G$17))*'WBS Schedule'!$P$17 -> 0.64 | V79: =IF($C$25<'WBS Schedule'!$H$17,0,MIN(1,NETWORKDAYS('WBS Schedule'!$H$17,$C$25,Holidays)/'WBS Schedule'!$G$17))*'WBS Schedule'!$P$17 -> 0.64
A80: ='WBS Schedule'!A18 -> 1.10 | B80: =IF($C$5<'WBS Schedule'!$H$18,0,MIN(1,NETWORKDAYS('WBS Schedule'!$H$18,$C$5,Holidays)/'WBS Schedule'!$G$18))*'WBS Schedule'!$P$18 -> 0 | C80: =IF($C$6<'WBS Schedule'!$H$18,0,MIN(1,NETWORKDAYS('WBS Schedule'!$H$18,$C$6,Holidays)/'WBS Schedule'!$G$18))*'WBS Schedule'!$P$18 -> 0 | D80: =IF($C$7<'WBS Schedule'!$H$18,0,MIN(1,NETWORKDAYS('WBS Schedule'!$H$18,$C$7,Holidays)/'WBS Schedule'!$G$18))*'WBS Schedule'!$P$18 -> 1.28 | E80: =IF($C$8<'WBS Schedule'!$H$18,0,MIN(1,NETWORKDAYS('WBS Schedule'!$H$18,$C$8,Holidays)/'WBS Schedule'!$G$18))*'WBS Schedule'!$P$18 -> 1.28 | F80: =IF($C$9<'WBS Schedule'!$H$18,0,MIN(1,NETWORKDAYS('WBS Schedule'!$H$18,$C$9,Holidays)/'WBS Schedule'!$G$18))*'WBS Schedule'!$P$18 -> 1.28 | G80: =IF($C$10<'WBS Schedule'!$H$18,0,MIN(1,NETWORKDAYS('WBS Schedule'!$H$18,$C$10,Holidays)/'WBS Schedule'!$G$18))*'WBS Schedule'!$P$18 -> 1.28 | H80: =IF($C$11<'WBS Schedule'!$H$18,0,MIN(1,NETWORKDAYS('WBS Schedule'!$H$18,$C$11,Holidays)/'WBS Schedule'!$G$18))*'WBS Schedule'!$P$18 -> 1.28 | I80: =IF($C$12<'WBS Schedule'!$H$18,0,MIN(1,NETWORKDAYS('WBS Schedule'!$H$18,$C$12,Holidays)/'WBS Schedule'!$G$18))*'WBS Schedule'!$P$18 -> 1.28 | J80: =IF($C$13<'WBS Schedule'!$H$18,0,MIN(1,NETWORKDAYS('WBS Schedule'!$H$18,$C$13,Holidays)/'WBS Schedule'!$G$18))*'WBS Schedule'!$P$18 -> 1.28 | K80: =IF($C$14<'WBS Schedule'!$H$18,0,MIN(1,NETWORKDAYS('WBS Schedule'!$H$18,$C$14,Holidays)/'WBS Schedule'!$G$18))*'WBS Schedule'!$P$18 -> 1.28 | L80: =IF($C$15<'WBS Schedule'!$H$18,0,MIN(1,NETWORKDAYS('WBS Schedule'!$H$18,$C$15,Holidays)/'WBS Schedule'!$G$18))*'WBS Schedule'!$P$18 -> 1.28 | M80: =IF($C$16<'WBS Schedule'!$H$18,0,MIN(1,NETWORKDAYS('WBS Schedule'!$H$18,$C$16,Holidays)/'WBS Schedule'!$G$18))*'WBS Schedule'!$P$18 -> 1.28 | N80: =IF($C$17<'WBS Schedule'!$H$18,0,MIN(1,NETWORKDAYS('WBS Schedule'!$H$18,$C$17,Holidays)/'WBS Schedule'!$G$18))*'WBS Schedule'!$P$18 -> 1.28 | O80: =IF($C$18<'WBS Schedule'!$H$18,0,MIN(1,NETWORKDAYS('WBS Schedule'!$H$18,$C$18,Holidays)/'WBS Schedule'!$G$18))*'WBS Schedule'!$P$18 -> 1.28 | P80: =IF($C$19<'WBS Schedule'!$H$18,0,MIN(1,NETWORKDAYS('WBS Schedule'!$H$18,$C$19,Holidays)/'WBS Schedule'!$G$18))*'WBS Schedule'!$P$18 -> 1.28 | Q80: =IF($C$20<'WBS Schedule'!$H$18,0,MIN(1,NETWORKDAYS('WBS Schedule'!$H$18,$C$20,Holidays)/'WBS Schedule'!$G$18))*'WBS Schedule'!$P$18 -> 1.28 | R80: =IF($C$21<'WBS Schedule'!$H$18,0,MIN(1,NETWORKDAYS('WBS Schedule'!$H$18,$C$21,Holidays)/'WBS Schedule'!$G$18))*'WBS Schedule'!$P$18 -> 1.28 | S80: =IF($C$22<'WBS Schedule'!$H$18,0,MIN(1,NETWORKDAYS('WBS Schedule'!$H$18,$C$22,Holidays)/'WBS Schedule'!$G$18))*'WBS Schedule'!$P$18 -> 1.28 | T80: =IF($C$23<'WBS Schedule'!$H$18,0,MIN(1,NETWORKDAYS('WBS Schedule'!$H$18,$C$23,Holidays)/'WBS Schedule'!$G$18))*'WBS Schedule'!$P$18 -> 1.28 | U80: =IF($C$24<'WBS Schedule'!$H$18,0,MIN(1,NETWORKDAYS('WBS Schedule'!$H$18,$C$24,Holidays)/'WBS Schedule'!$G$18))*'WBS Schedule'!$P$18 -> 1.28 | V80: =IF($C$25<'WBS Schedule'!$H$18,0,MIN(1,NETWORKDAYS('WBS Schedule'!$H$18,$C$25,Holidays)/'WBS Schedule'!$G$18))*'WBS Schedule'!$P$18 -> 1.28
A81: ='WBS Schedule'!A21 -> 2.1 | B81: =IF($C$5<'WBS Schedule'!$H$21,0,MIN(1,NETWORKDAYS('WBS Schedule'!$H$21,$C$5,Holidays)/'WBS Schedule'!$G$21))*'WBS Schedule'!$P$21 -> 0 | C81: =IF($C$6<'WBS Schedule'!$H$21,0,MIN(1,NETWORKDAYS('WBS Schedule'!$H$21,$C$6,Holidays)/'WBS Schedule'!$G$21))*'WBS Schedule'!$P$21 -> 0 | D81: =IF($C$7<'WBS Schedule'!$H$21,0,MIN(1,NETWORKDAYS('WBS Schedule'!$H$21,$C$7,Holidays)/'WBS Schedule'!$G$21))*'WBS Schedule'!$P$21 -> 0 | E81: =IF($C$8<'WBS Schedule'!$H$21,0,MIN(1,NETWORKDAYS('WBS Schedule'!$H$21,$C$8,Holidays)/'WBS Schedule'!$G$21))*'WBS Schedule'!$P$21 -> 0 | F81: =IF($C$9<'WBS Schedule'!$H$21,0,MIN(1,NETWORKDAYS('WBS Schedule'!$H$21,$C$9,Holidays)/'WBS Schedule'!$G$21))*'WBS Schedule'!$P$21 -> 0.64 | G81: =IF($C$10<'WBS Schedule'!$H$21,0,MIN(1,NETWORKDAYS('WBS Schedule'!$H$21,$C$10,Holidays)/'WBS Schedule'!$G$21))*'WBS Schedule'!$P$21 -> 0.64 | H81: =IF($C$11<'WBS Schedule'!$H$21,0,MIN(1,NETWORKDAYS('WBS Schedule'!$H$21,$C$11,Holidays)/'WBS Schedule'!$G$21))*'WBS Schedule'!$P$21 -> 0.64 | I81: =IF($C$12<'WBS Schedule'!$H$21,0,MIN(1,NETWORKDAYS('WBS Schedule'!$H$21,$C$12,Holidays)/'WBS Schedule'!$G$21))*'WBS Schedule'!$P$21 -> 0.64 | J81: =IF($C$13<'WBS Schedule'!$H$21,0,MIN(1,NETWORKDAYS('WBS Schedule'!$H$21,$C$13,Holidays)/'WBS Schedule'!$G$21))*'WBS Schedule'!$P$21 -> 0.64 | K81: =IF($C$14<'WBS Schedule'!$H$21,0,MIN(1,NETWORKDAYS('WBS Schedule'!$H$21,$C$14,Holidays)/'WBS Schedule'!$G$21))*'WBS Schedule'!$P$21 -> 0.64 | L81: =IF($C$15<'WBS Schedule'!$H$21,0,MIN(1,NETWORKDAYS('WBS Schedule'!$H$21,$C$15,Holidays)/'WBS Schedule'!$G$21))*'WBS Schedule'!$P$21 -> 0.64 | M81: =IF($C$16<'WBS Schedule'!$H$21,0,MIN(1,NETWORKDAYS('WBS Schedule'!$H$21,$C$16,Holidays)/'WBS Schedule'!$G$21))*'WBS Schedule'!$P$21 -> 0.64 | N81: =IF($C$17<'WBS Schedule'!$H$21,0,MIN(1,NETWORKDAYS('WBS Schedule'!$H$21,$C$17,Holidays)/'WBS Schedule'!$G$21))*'WBS Schedule'!$P$21 -> 0.64 | O81: =IF($C$18<'WBS Schedule'!$H$21,0,MIN(1,NETWORKDAYS('WBS Schedule'!$H$21,$C$18,Holidays)/'WBS Schedule'!$G$21))*'WBS Schedule'!$P$21 -> 0.64 | P81: =IF($C$19<'WBS Schedule'!$H$21,0,MIN(1,NETWORKDAYS('WBS Schedule'!$H$21,$C$19,Holidays)/'WBS Schedule'!$G$21))*'WBS Schedule'!$P$21 -> 0.64 | Q81: =IF($C$20<'WBS Schedule'!$H$21,0,MIN(1,NETWORKDAYS('WBS Schedule'!$H$21,$C$20,Holidays)/'WBS Schedule'!$G$21))*'WBS Schedule'!$P$21 -> 0.64 | R81: =IF($C$21<'WBS Schedule'!$H$21,0,MIN(1,NETWORKDAYS('WBS Schedule'!$H$21,$C$21,Holidays)/'WBS Schedule'!$G$21))*'WBS Schedule'!$P$21 -> 0.64 | S81: =IF($C$22<'WBS Schedule'!$H$21,0,MIN(1,NETWORKDAYS('WBS Schedule'!$H$21,$C$22,Holidays)/'WBS Schedule'!$G$21))*'WBS Schedule'!$P$21 -> 0.64 | T81: =IF($C$23<'WBS Schedule'!$H$21,0,MIN(1,NETWORKDAYS('WBS Schedule'!$H$21,$C$23,Holidays)/'WBS Schedule'!$G$21))*'WBS Schedule'!$P$21 -> 0.64 | U81: =IF($C$24<'WBS Schedule'!$H$21,0,MIN(1,NETWORKDAYS('WBS Schedule'!$H$21,$C$24,Holidays)/'WBS Schedule'!$G$21))*'WBS Schedule'!$P$21 -> 0.64 | V81: =IF($C$25<'WBS Schedule'!$H$21,0,MIN(1,NETWORKDAYS('WBS Schedule'!$H$21,$C$25,Holidays)/'WBS Schedule'!$G$21))*'WBS Schedule'!$P$21 -> 0.64
A82: ='WBS Schedule'!A22 -> 2.2 | B82: =IF($C$5<'WBS Schedule'!$H$22,0,MIN(1,NETWORKDAYS('WBS Schedule'!$H$22,$C$5,Holidays)/'WBS Schedule'!$G$22))*'WBS Schedule'!$P$22 -> 0 | C82: =IF($C$6<'WBS Schedule'!$H$22,0,MIN(1,NETWORKDAYS('WBS Schedule'!$H$22,$C$6,Holidays)/'WBS Schedule'!$G$22))*'WBS Schedule'!$P$22 -> 0 | D82: =IF($C$7<'WBS Schedule'!$H$22,0,MIN(1,NETWORKDAYS('WBS Schedule'!$H$22,$C$7,Holidays)/'WBS Schedule'!$G$22))*'WBS Schedule'!$P$22 -> 0 | E82: =IF($C$8<'WBS Schedule'!$H$22,0,MIN(1,NETWORKDAYS('WBS Schedule'!$H$22,$C$8,Holidays)/'WBS Schedule'!$G$22))*'WBS Schedule'!$P$22 -> 0 | F82: =IF($C$9<'WBS Schedule'!$H$22,0,MIN(1,NETWORKDAYS('WBS Schedule'!$H$22,$C$9,Holidays)/'WBS Schedule'!$G$22))*'WBS Schedule'!$P$22 -> 1.28 | G82: =IF($C$10<'WBS Schedule'!$H$22,0,MIN(1,NETWORKDAYS('WBS Schedule'!$H$22,$C$10,Holidays)/'WBS Schedule'!$G$22))*'WBS Schedule'!$P$22 -> 1.28 | H82: =IF($C$11<'WBS Schedule'!$H$22,0,MIN(1,NETWORKDAYS('WBS Schedule'!$H$22,$C$11,Holidays)/'WBS Schedule'!$G$22))*'WBS Schedule'!$P$22 -> 1.28 | I82: =IF($C$12<'WBS Schedule'!$H$22,0,MIN(1,NETWORKDAYS('WBS Schedule'!$H$22,$C$12,Holidays)/'WBS Schedule'!$G$22))*'WBS Schedule'!$P$22 -> 1.28 | J82: =IF($C$13<'WBS Schedule'!$H$22,0,MIN(1,NETWORKDAYS('WBS Schedule'!$H$22,$C$13,Holidays)/'WBS Schedule'!$G$22))*'WBS Schedule'!$P$22 -> 1.28 | K82: =IF($C$14<'WBS Schedule'!$H$22,0,MIN(1,NETWORKDAYS('WBS Schedule'!$H$22,$C$14,Holidays)/'WBS Schedule'!$G$22))*'WBS Schedule'!$P$22 -> 1.28 | L82: =IF($C$15<'WBS Schedule'!$H$22,0,MIN(1,NETWORKDAYS('WBS Schedule'!$H$22,$C$15,Holidays)/'WBS Schedule'!$G$22))*'WBS Schedule'!$P$22 -> 1.28 | M82: =IF($C$16<'WBS Schedule'!$H$22,0,MIN(1,NETWORKDAYS('WBS Schedule'!$H$22,$C$16,Holidays)/'WBS Schedule'!$G$22))*'WBS Schedule'!$P$22 -> 1.28 | N82: =IF($C$17<'WBS Schedule'!$H$22,0,MIN(1,NETWORKDAYS('WBS Schedule'!$H$22,$C$17,Holidays)/'WBS Schedule'!$G$22))*'WBS Schedule'!$P$22 -> 1.28 | O82: =IF($C$18<'WBS Schedule'!$H$22,0,MIN(1,NETWORKDAYS('WBS Schedule'!$H$22,$C$18,Holidays)/'WBS Schedule'!$G$22))*'WBS Schedule'!$P$22 -> 1.28 | P82: =IF($C$19<'WBS Schedule'!$H$22,0,MIN(1,NETWORKDAYS('WBS Schedule'!$H$22,$C$19,Holidays)/'WBS Schedule'!$G$22))*'WBS Schedule'!$P$22 -> 1.28 | Q82: =IF($C$20<'WBS Schedule'!$H$22,0,MIN(1,NETWORKDAYS('WBS Schedule'!$H$22,$C$20,Holidays)/'WBS Schedule'!$G$22))*'WBS Schedule'!$P$22 -> 1.28 | R82: =IF($C$21<'WBS Schedule'!$H$22,0,MIN(1,NETWORKDAYS('WBS Schedule'!$H$22,$C$21,Holidays)/'WBS Schedule'!$G$22))*'WBS Schedule'!$P$22 -> 1.28 | S82: =IF($C$22<'WBS Schedule'!$H$22,0,MIN(1,NETWORKDAYS('WBS Schedule'!$H$22,$C$22,Holidays)/'WBS Schedule'!$G$22))*'WBS Schedule'!$P$22 -> 1.28 | T82: =IF($C$23<'WBS Schedule'!$H$22,0,MIN(1,NETWORKDAYS('WBS Schedule'!$H$22,$C$23,Holidays)/'WBS Schedule'!$G$22))*'WBS Schedule'!$P$22 -> 1.28 | U82: =IF($C$24<'WBS Schedule'!$H$22,0,MIN(1,NETWORKDAYS('WBS Schedule'!$H$22,$C$24,Holidays)/'WBS Schedule'!$G$22))*'WBS Schedule'!$P$22 -> 1.28 | V82: =IF($C$25<'WBS Schedule'!$H$22,0,MIN(1,NETWORKDAYS('WBS Schedule'!$H$22,$C$25,Holidays)/'WBS Schedule'!$G$22))*'WBS Schedule'!$P$22 -> 1.28
A83: ='WBS Schedule'!A23 -> 2.3 | B83: =IF($C$5<'WBS Schedule'!$H$23,0,MIN(1,NETWORKDAYS('WBS Schedule'!$H$23,$C$5,Holidays)/'WBS Schedule'!$G$23))*'WBS Schedule'!$P$23 -> 0 | C83: =IF($C$6<'WBS Schedule'!$H$23,0,MIN(1,NETWORKDAYS('WBS Schedule'!$H$23,$C$6,Holidays)/'WBS Schedule'!$G$23))*'WBS Schedule'!$P$23 -> 0 | D83: =IF($C$7<'WBS Schedule'!$H$23,0,MIN(1,NETWORKDAYS('WBS Schedule'!$H$23,$C$7,Holidays)/'WBS Schedule'!$G$23))*'WBS Schedule'!$P$23 -> 0 | E83: =IF($C$8<'WBS Schedule'!$H$23,0,MIN(1,NETWORKDAYS('WBS Schedule'!$H$23,$C$8,Holidays)/'WBS Schedule'!$G$23))*'WBS Schedule'!$P$23 -> 0 | F83: =IF($C$9<'WBS Schedule'!$H$23,0,MIN(1,NETWORKDAYS('WBS Schedule'!$H$23,$C$9,Holidays)/'WBS Schedule'!$G$23))*'WBS Schedule'!$P$23 -> 0 | G83: =IF($C$10<'WBS Schedule'!$H$23,0,MIN(1,NETWORKDAYS('WBS Schedule'!$H$23,$C$10,Holidays)/'WBS Schedule'!$G$23))*'WBS Schedule'!$P$23 -> 1.28 | H83: =IF($C$11<'WBS Schedule'!$H$23,0,MIN(1,NETWORKDAYS('WBS Schedule'!$H$23,$C$11,Holidays)/'WBS Schedule'!$G$23))*'WBS Schedule'!$P$23 -> 1.28 | I83: =IF($C$12<'WBS Schedule'!$H$23,0,MIN(1,NETWORKDAYS('WBS Schedule'!$H$23,$C$12,Holidays)/'WBS Schedule'!$G$23))*'WBS Schedule'!$P$23 -> 1.28 | J83: =IF($C$13<'WBS Schedule'!$H$23,0,MIN(1,NETWORKDAYS('WBS Schedule'!$H$23,$C$13,Holidays)/'WBS Schedule'!$G$23))*'WBS Schedule'!$P$23 -> 1.28 | K83: =IF($C$14<'WBS Schedule'!$H$23,0,MIN(1,NETWORKDAYS('WBS Schedule'!$H$23,$C$14,Holidays)/'WBS Schedule'!$G$23))*'WBS Schedule'!$P$23 -> 1.28 | L83: =IF($C$15<'WBS Schedule'!$H$23,0,MIN(1,NETWORKDAYS('WBS Schedule'!$H$23,$C$15,Holidays)/'WBS Schedule'!$G$23))*'WBS Schedule'!$P$23 -> 1.28 | M83: =IF($C$16<'WBS Schedule'!$H$23,0,MIN(1,NETWORKDAYS('WBS Schedule'!$H$23,$C$16,Holidays)/'WBS Schedule'!$G$23))*'WBS Schedule'!$P$23 -> 1.28 | N83: =IF($C$17<'WBS Schedule'!$H$23,0,MIN(1,NETWORKDAYS('WBS Schedule'!$H$23,$C$17,Holidays)/'WBS Schedule'!$G$23))*'WBS Schedule'!$P$23 -> 1.28 | O83: =IF($C$18<'WBS Schedule'!$H$23,0,MIN(1,NETWORKDAYS('WBS Schedule'!$H$23,$C$18,Holidays)/'WBS Schedule'!$G$23))*'WBS Schedule'!$P$23 -> 1.28 | P83: =IF($C$19<'WBS Schedule'!$H$23,0,MIN(1,NETWORKDAYS('WBS Schedule'!$H$23,$C$19,Holidays)/'WBS Schedule'!$G$23))*'WBS Schedule'!$P$23 -> 1.28 | Q83: =IF($C$20<'WBS Schedule'!$H$23,0,MIN(1,NETWORKDAYS('WBS Schedule'!$H$23,$C$20,Holidays)/'WBS Schedule'!$G$23))*'WBS Schedule'!$P$23 -> 1.28 | R83: =IF($C$21<'WBS Schedule'!$H$23,0,MIN(1,NETWORKDAYS('WBS Schedule'!$H$23,$C$21,Holidays)/'WBS Schedule'!$G$23))*'WBS Schedule'!$P$23 -> 1.28 | S83: =IF($C$22<'WBS Schedule'!$H$23,0,MIN(1,NETWORKDAYS('WBS Schedule'!$H$23,$C$22,Holidays)/'WBS Schedule'!$G$23))*'WBS Schedule'!$P$23 -> 1.28 | T83: =IF($C$23<'WBS Schedule'!$H$23,0,MIN(1,NETWORKDAYS('WBS Schedule'!$H$23,$C$23,Holidays)/'WBS Schedule'!$G$23))*'WBS Schedule'!$P$23 -> 1.28 | U83: =IF($C$24<'WBS Schedule'!$H$23,0,MIN(1,NETWORKDAYS('WBS Schedule'!$H$23,$C$24,Holidays)/'WBS Schedule'!$G$23))*'WBS Schedule'!$P$23 -> 1.28 | V83: =IF($C$25<'WBS Schedule'!$H$23,0,MIN(1,NETWORKDAYS('WBS Schedule'!$H$23,$C$25,Holidays)/'WBS Schedule'!$G$23))*'WBS Schedule'!$P$23 -> 1.28
A84: ='WBS Schedule'!A24 -> 2.4 | B84: =IF($C$5<'WBS Schedule'!$H$24,0,MIN(1,NETWORKDAYS('WBS Schedule'!$H$24,$C$5,Holidays)/'WBS Schedule'!$G$24))*'WBS Schedule'!$P$24 -> 0 | C84: =IF($C$6<'WBS Schedule'!$H$24,0,MIN(1,NETWORKDAYS('WBS Schedule'!$H$24,$C$6,Holidays)/'WBS Schedule'!$G$24))*'WBS Schedule'!$P$24 -> 0 | D84: =IF($C$7<'WBS Schedule'!$H$24,0,MIN(1,NETWORKDAYS('WBS Schedule'!$H$24,$C$7,Holidays)/'WBS Schedule'!$G$24))*'WBS Schedule'!$P$24 -> 0 | E84: =IF($C$8<'WBS Schedule'!$H$24,0,MIN(1,NETWORKDAYS('WBS Schedule'!$H$24,$C$8,Holidays)/'WBS Schedule'!$G$24))*'WBS Schedule'!$P$24 -> 0 | F84: =IF($C$9<'WBS Schedule'!$H$24,0,MIN(1,NETWORKDAYS('WBS Schedule'!$H$24,$C$9,Holidays)/'WBS Schedule'!$G$24))*'WBS Schedule'!$P$24 -> 0 | G84: =IF($C$10<'WBS Schedule'!$H$24,0,MIN(1,NETWORKDAYS('WBS Schedule'!$H$24,$C$10,Holidays)/'WBS Schedule'!$G$24))*'WBS Schedule'!$P$24 -> 0.32 | H84: =IF($C$11<'WBS Schedule'!$H$24,0,MIN(1,NETWORKDAYS('WBS Schedule'!$H$24,$C$11,Holidays)/'WBS Schedule'!$G$24))*'WBS Schedule'!$P$24 -> 0.32 | I84: =IF($C$12<'WBS Schedule'!$H$24,0,MIN(1,NETWORKDAYS('WBS Schedule'!$H$24,$C$12,Holidays)/'WBS Schedule'!$G$24))*'WBS Schedule'!$P$24 -> 0.32 | J84: =IF($C$13<'WBS Schedule'!$H$24,0,MIN(1,NETWORKDAYS('WBS Schedule'!$H$24,$C$13,Holidays)/'WBS Schedule'!$G$24))*'WBS Schedule'!$P$24 -> 0.32 | K84: =IF($C$14<'WBS Schedule'!$H$24,0,MIN(1,NETWORKDAYS('WBS Schedule'!$H$24,$C$14,Holidays)/'WBS Schedule'!$G$24))*'WBS Schedule'!$P$24 -> 0.32 | L84: =IF($C$15<'WBS Schedule'!$H$24,0,MIN(1,NETWORKDAYS('WBS Schedule'!$H$24,$C$15,Holidays)/'WBS Schedule'!$G$24))*'WBS Schedule'!$P$24 -> 0.32 | M84: =IF($C$16<'WBS Schedule'!$H$24,0,MIN(1,NETWORKDAYS('WBS Schedule'!$H$24,$C$16,Holidays)/'WBS Schedule'!$G$24))*'WBS Schedule'!$P$24 -> 0.32 | N84: =IF($C$17<'WBS Schedule'!$H$24,0,MIN(1,NETWORKDAYS('WBS Schedule'!$H$24,$C$17,Holidays)/'WBS Schedule'!$G$24))*'WBS Schedule'!$P$24 -> 0.32 | O84: =IF($C$18<'WBS Schedule'!$H$24,0,MIN(1,NETWORKDAYS('WBS Schedule'!$H$24,$C$18,Holidays)/'WBS Schedule'!$G$24))*'WBS Schedule'!$P$24 -> 0.32 | P84: =IF($C$19<'WBS Schedule'!$H$24,0,MIN(1,NETWORKDAYS('WBS Schedule'!$H$24,$C$19,Holidays)/'WBS Schedule'!$G$24))*'WBS Schedule'!$P$24 -> 0.32 | Q84: =IF($C$20<'WBS Schedule'!$H$24,0,MIN(1,NETWORKDAYS('WBS Schedule'!$H$24,$C$20,Holidays)/'WBS Schedule'!$G$24))*'WBS Schedule'!$P$24 -> 0.32 | R84: =IF($C$21<'WBS Schedule'!$H$24,0,MIN(1,NETWORKDAYS('WBS Schedule'!$H$24,$C$21,Holidays)/'WBS Schedule'!$G$24))*'WBS Schedule'!$P$24 -> 0.32 | S84: =IF($C$22<'WBS Schedule'!$H$24,0,MIN(1,NETWORKDAYS('WBS Schedule'!$H$24,$C$22,Holidays)/'WBS Schedule'!$G$24))*'WBS Schedule'!$P$24 -> 0.32 | T84: =IF($C$23<'WBS Schedule'!$H$24,0,MIN(1,NETWORKDAYS('WBS Schedule'!$H$24,$C$23,Holidays)/'WBS Schedule'!$G$24))*'WBS Schedule'!$P$24 -> 0.32 | U84: =IF($C$24<'WBS Schedule'!$H$24,0,MIN(1,NETWORKDAYS('WBS Schedule'!$H$24,$C$24,Holidays)/'WBS Schedule'!$G$24))*'WBS Schedule'!$P$24 -> 0.32 | V84: =IF($C$25<'WBS Schedule'!$H$24,0,MIN(1,NETWORKDAYS('WBS Schedule'!$H$24,$C$25,Holidays)/'WBS Schedule'!$G$24))*'WBS Schedule'!$P$24 -> 0.32
A85: ='WBS Schedule'!A25 -> 2.5 | B85: =IF($C$5<'WBS Schedule'!$H$25,0,MIN(1,NETWORKDAYS('WBS Schedule'!$H$25,$C$5,Holidays)/'WBS Schedule'!$G$25))*'WBS Schedule'!$P$25 -> 0 | C85: =IF($C$6<'WBS Schedule'!$H$25,0,MIN(1,NETWORKDAYS('WBS Schedule'!$H$25,$C$6,Holidays)/'WBS Schedule'!$G$25))*'WBS Schedule'!$P$25 -> 0 | D85: =IF($C$7<'WBS Schedule'!$H$25,0,MIN(1,NETWORKDAYS('WBS Schedule'!$H$25,$C$7,Holidays)/'WBS Schedule'!$G$25))*'WBS Schedule'!$P$25 -> 0 | E85: =IF($C$8<'WBS Schedule'!$H$25,0,MIN(1,NETWORKDAYS('WBS Schedule'!$H$25,$C$8,Holidays)/'WBS Schedule'!$G$25))*'WBS Schedule'!$P$25 -> 0 | F85: =IF($C$9<'WBS Schedule'!$H$25,0,MIN(1,NETWORKDAYS('WBS Schedule'!$H$25,$C$9,Holidays)/'WBS Schedule'!$G$25))*'WBS Schedule'!$P$25 -> 2.88 | G85: =IF($C$10<'WBS Schedule'!$H$25,0,MIN(1,NETWORKDAYS('WBS Schedule'!$H$25,$C$10,Holidays)/'WBS Schedule'!$G$25))*'WBS Schedule'!$P$25 -> 2.88 | H85: =IF($C$11<'WBS Schedule'!$H$25,0,MIN(1,NETWORKDAYS('WBS Schedule'!$H$25,$C$11,Holidays)/'WBS Schedule'!$G$25))*'WBS Schedule'!$P$25 -> 2.88 | I85: =IF($C$12<'WBS Schedule'!$H$25,0,MIN(1,NETWORKDAYS('WBS Schedule'!$H$25,$C$12,Holidays)/'WBS Schedule'!$G$25))*'WBS Schedule'!$P$25 -> 2.88 | J85: =IF($C$13<'WBS Schedule'!$H$25,0,MIN(1,NETWORKDAYS('WBS Schedule'!$H$25,$C$13,Holidays)/'WBS Schedule'!$G$25))*'WBS Schedule'!$P$25 -> 2.88 | K85: =IF($C$14<'WBS Schedule'!$H$25,0,MIN(1,NETWORKDAYS('WBS Schedule'!$H$25,$C$14,Holidays)/'WBS Schedule'!$G$25))*'WBS Schedule'!$P$25 -> 2.88 | L85: =IF($C$15<'WBS Schedule'!$H$25,0,MIN(1,NETWORKDAYS('WBS Schedule'!$H$25,$C$15,Holidays)/'WBS Schedule'!$G$25))*'WBS Schedule'!$P$25 -> 2.88 | M85: =IF($C$16<'WBS Schedule'!$H$25,0,MIN(1,NETWORKDAYS('WBS Schedule'!$H$25,$C$16,Holidays)/'WBS Schedule'!$G$25))*'WBS Schedule'!$P$25 -> 2.88 | N85: =IF($C$17<'WBS Schedule'!$H$25,0,MIN(1,NETWORKDAYS('WBS Schedule'!$H$25,$C$17,Holidays)/'WBS Schedule'!$G$25))*'WBS Schedule'!$P$25 -> 2.88 | O85: =IF($C$18<'WBS Schedule'!$H$25,0,MIN(1,NETWORKDAYS('WBS Schedule'!$H$25,$C$18,Holidays)/'WBS Schedule'!$G$25))*'WBS Schedule'!$P$25 -> 2.88 | P85: =IF($C$19<'WBS Schedule'!$H$25,0,MIN(1,NETWORKDAYS('WBS Schedule'!$H$25,$C$19,Holidays)/'WBS Schedule'!$G$25))*'WBS Schedule'!$P$25 -> 2.88 | Q85: =IF($C$20<'WBS Schedule'!$H$25,0,MIN(1,NETWORKDAYS('WBS Schedule'!$H$25,$C$20,Holidays)/'WBS Schedule'!$G$25))*'WBS Schedule'!$P$25 -> 2.88 | R85: =IF($C$21<'WBS Schedule'!$H$25,0,MIN(1,NETWORKDAYS('WBS Schedule'!$H$25,$C$21,Holidays)/'WBS Schedule'!$G$25))*'WBS Schedule'!$P$25 -> 2.88 | S85: =IF($C$22<'WBS Schedule'!$H$25,0,MIN(1,NETWORKDAYS('WBS Schedule'!$H$25,$C$22,Holidays)/'WBS Schedule'!$G$25))*'WBS Schedule'!$P$25 -> 2.88 | T85: =IF($C$23<'WBS Schedule'!$H$25,0,MIN(1,NETWORKDAYS('WBS Schedule'!$H$25,$C$23,Holidays)/'WBS Schedule'!$G$25))*'WBS Schedule'!$P$25 -> 2.88 | U85: =IF($C$24<'WBS Schedule'!$H$25,0,MIN(1,NETWORKDAYS('WBS Schedule'!$H$25,$C$24,Holidays)/'WBS Schedule'!$G$25))*'WBS Schedule'!$P$25 -> 2.88 | V85: =IF($C$25<'WBS Schedule'!$H$25,0,MIN(1,NETWORKDAYS('WBS Schedule'!$H$25,$C$25,Holidays)/'WBS Schedule'!$G$25))*'WBS Schedule'!$P$25 -> 2.88
A86: ='WBS Schedule'!A26 -> 2.6 | B86: =IF($C$5<'WBS Schedule'!$H$26,0,MIN(1,NETWORKDAYS('WBS Schedule'!$H$26,$C$5,Holidays)/'WBS Schedule'!$G$26))*'WBS Schedule'!$P$26 -> 0 | C86: =IF($C$6<'WBS Schedule'!$H$26,0,MIN(1,NETWORKDAYS('WBS Schedule'!$H$26,$C$6,Holidays)/'WBS Schedule'!$G$26))*'WBS Schedule'!$P$26 -> 0 | D86: =IF($C$7<'WBS Schedule'!$H$26,0,MIN(1,NETWORKDAYS('WBS Schedule'!$H$26,$C$7,Holidays)/'WBS Schedule'!$G$26))*'WBS Schedule'!$P$26 -> 0 | E86: =IF($C$8<'WBS Schedule'!$H$26,0,MIN(1,NETWORKDAYS('WBS Schedule'!$H$26,$C$8,Holidays)/'WBS Schedule'!$G$26))*'WBS Schedule'!$P$26 -> 0 | F86: =IF($C$9<'WBS Schedule'!$H$26,0,MIN(1,NETWORKDAYS('WBS Schedule'!$H$26,$C$9,Holidays)/'WBS Schedule'!$G$26))*'WBS Schedule'!$P$26 -> 0 | G86: =IF($C$10<'WBS Schedule'!$H$26,0,MIN(1,NETWORKDAYS('WBS Schedule'!$H$26,$C$10,Holidays)/'WBS Schedule'!$G$26))*'WBS Schedule'!$P$26 -> 1.28 | H86: =IF($C$11<'WBS Schedule'!$H$26,0,MIN(1,NETWORKDAYS('WBS Schedule'!$H$26,$C$11,Holidays)/'WBS Schedule'!$G$26))*'WBS Schedule'!$P$26 -> 2.56 | I86: =IF($C$12<'WBS Schedule'!$H$26,0,MIN(1,NETWORKDAYS('WBS Schedule'!$H$26,$C$12,Holidays)/'WBS Schedule'!$G$26))*'WBS Schedule'!$P$26 -> 2.56 | J86: =IF($C$13<'WBS Schedule'!$H$26,0,MIN(1,NETWORKDAYS('WBS Schedule'!$H$26,$C$13,Holidays)/'WBS Schedule'!$G$26))*'WBS Schedule'!$P$26 -> 2.56 | K86: =IF($C$14<'WBS Schedule'!$H$26,0,MIN(1,NETWORKDAYS('WBS Schedule'!$H$26,$C$14,Holidays)/'WBS Schedule'!$G$26))*'WBS Schedule'!$P$26 -> 2.56 | L86: =IF($C$15<'WBS Schedule'!$H$26,0,MIN(1,NETWORKDAYS('WBS Schedule'!$H$26,$C$15,Holidays)/'WBS Schedule'!$G$26))*'WBS Schedule'!$P$26 -> 2.56 | M86: =IF($C$16<'WBS Schedule'!$H$26,0,MIN(1,NETWORKDAYS('WBS Schedule'!$H$26,$C$16,Holidays)/'WBS Schedule'!$G$26))*'WBS Schedule'!$P$26 -> 2.56 | N86: =IF($C$17<'WBS Schedule'!$H$26,0,MIN(1,NETWORKDAYS('WBS Schedule'!$H$26,$C$17,Holidays)/'WBS Schedule'!$G$26))*'WBS Schedule'!$P$26 -> 2.56 | O86: =IF($C$18<'WBS Schedule'!$H$26,0,MIN(1,NETWORKDAYS('WBS Schedule'!$H$26,$C$18,Holidays)/'WBS Schedule'!$G$26))*'WBS Schedule'!$P$26 -> 2.56 | P86: =IF($C$19<'WBS Schedule'!$H$26,0,MIN(1,NETWORKDAYS('WBS Schedule'!$H$26,$C$19,Holidays)/'WBS Schedule'!$G$26))*'WBS Schedule'!$P$26 -> 2.56 | Q86: =IF($C$20<'WBS Schedule'!$H$26,0,MIN(1,NETWORKDAYS('WBS Schedule'!$H$26,$C$20,Holidays)/'WBS Schedule'!$G$26))*'WBS Schedule'!$P$26 -> 2.56 | R86: =IF($C$21<'WBS Schedule'!$H$26,0,MIN(1,NETWORKDAYS('WBS Schedule'!$H$26,$C$21,Holidays)/'WBS Schedule'!$G$26))*'WBS Schedule'!$P$26 -> 2.56 | S86: =IF($C$22<'WBS Schedule'!$H$26,0,MIN(1,NETWORKDAYS('WBS Schedule'!$H$26,$C$22,Holidays)/'WBS Schedule'!$G$26))*'WBS Schedule'!$P$26 -> 2.56 | T86: =IF($C$23<'WBS Schedule'!$H$26,0,MIN(1,NETWORKDAYS('WBS Schedule'!$H$26,$C$23,Holidays)/'WBS Schedule'!$G$26))*'WBS Schedule'!$P$26 -> 2.56 | U86: =IF($C$24<'WBS Schedule'!$H$26,0,MIN(1,NETWORKDAYS('WBS Schedule'!$H$26,$C$24,Holidays)/'WBS Schedule'!$G$26))*'WBS Schedule'!$P$26 -> 2.56 | V86: =IF($C$25<'WBS Schedule'!$H$26,0,MIN(1,NETWORKDAYS('WBS Schedule'!$H$26,$C$25,Holidays)/'WBS Schedule'!$G$26))*'WBS Schedule'!$P$26 -> 2.56
A87: ='WBS Schedule'!A27 -> 2.7 | B87: =IF($C$5<'WBS Schedule'!$H$27,0,MIN(1,NETWORKDAYS('WBS Schedule'!$H$27,$C$5,Holidays)/'WBS Schedule'!$G$27))*'WBS Schedule'!$P$27 -> 0 | C87: =IF($C$6<'WBS Schedule'!$H$27,0,MIN(1,NETWORKDAYS('WBS Schedule'!$H$27,$C$6,Holidays)/'WBS Schedule'!$G$27))*'WBS Schedule'!$P$27 -> 0 | D87: =IF($C$7<'WBS Schedule'!$H$27,0,MIN(1,NETWORKDAYS('WBS Schedule'!$H$27,$C$7,Holidays)/'WBS Schedule'!$G$27))*'WBS Schedule'!$P$27 -> 0 | E87: =IF($C$8<'WBS Schedule'!$H$27,0,MIN(1,NETWORKDAYS('WBS Schedule'!$H$27,$C$8,Holidays)/'WBS Schedule'!$G$27))*'WBS Schedule'!$P$27 -> 0 | F87: =IF($C$9<'WBS Schedule'!$H$27,0,MIN(1,NETWORKDAYS('WBS Schedule'!$H$27,$C$9,Holidays)/'WBS Schedule'!$G$27))*'WBS Schedule'!$P$27 -> 0 | G87: =IF($C$10<'WBS Schedule'!$H$27,0,MIN(1,NETWORKDAYS('WBS Schedule'!$H$27,$C$10,Holidays)/'WBS Schedule'!$G$27))*'WBS Schedule'!$P$27 -> 0 | H87: =IF($C$11<'WBS Schedule'!$H$27,0,MIN(1,NETWORKDAYS('WBS Schedule'!$H$27,$C$11,Holidays)/'WBS Schedule'!$G$27))*'WBS Schedule'!$P$27 -> 1.92 | I87: =IF($C$12<'WBS Schedule'!$H$27,0,MIN(1,NETWORKDAYS('WBS Schedule'!$H$27,$C$12,Holidays)/'WBS Schedule'!$G$27))*'WBS Schedule'!$P$27 -> 1.92 | J87: =IF($C$13<'WBS Schedule'!$H$27,0,MIN(1,NETWORKDAYS('WBS Schedule'!$H$27,$C$13,Holidays)/'WBS Schedule'!$G$27))*'WBS Schedule'!$P$27 -> 1.92 | K87: =IF($C$14<'WBS Schedule'!$H$27,0,MIN(1,NETWORKDAYS('WBS Schedule'!$H$27,$C$14,Holidays)/'WBS Schedule'!$G$27))*'WBS Schedule'!$P$27 -> 1.92 | L87: =IF($C$15<'WBS Schedule'!$H$27,0,MIN(1,NETWORKDAYS('WBS Schedule'!$H$27,$C$15,Holidays)/'WBS Schedule'!$G$27))*'WBS Schedule'!$P$27 -> 1.92 | M87: =IF($C$16<'WBS Schedule'!$H$27,0,MIN(1,NETWORKDAYS('WBS Schedule'!$H$27,$C$16,Holidays)/'WBS Schedule'!$G$27))*'WBS Schedule'!$P$27 -> 1.92 | N87: =IF($C$17<'WBS Schedule'!$H$27,0,MIN(1,NETWORKDAYS('WBS Schedule'!$H$27,$C$17,Holidays)/'WBS Schedule'!$G$27))*'WBS Schedule'!$P$27 -> 1.92 | O87: =IF($C$18<'WBS Schedule'!$H$27,0,MIN(1,NETWORKDAYS('WBS Schedule'!$H$27,$C$18,Holidays)/'WBS Schedule'!$G$27))*'WBS Schedule'!$P$27 -> 1.92 | P87: =IF($C$19<'WBS Schedule'!$H$27,0,MIN(1,NETWORKDAYS('WBS Schedule'!$H$27,$C$19,Holidays)/'WBS Schedule'!$G$27))*'WBS Schedule'!$P$27 -> 1.92 | Q87: =IF($C$20<'WBS Schedule'!$H$27,0,MIN(1,NETWORKDAYS('WBS Schedule'!$H$27,$C$20,Holidays)/'WBS Schedule'!$G$27))*'WBS Schedule'!$P$27 -> 1.92 | R87: =IF($C$21<'WBS Schedule'!$H$27,0,MIN(1,NETWORKDAYS('WBS Schedule'!$H$27,$C$21,Holidays)/'WBS Schedule'!$G$27))*'WBS Schedule'!$P$27 -> 1.92 | S87: =IF($C$22<'WBS Schedule'!$H$27,0,MIN(1,NETWORKDAYS('WBS Schedule'!$H$27,$C$22,Holidays)/'WBS Schedule'!$G$27))*'WBS Schedule'!$P$27 -> 1.92 | T87: =IF($C$23<'WBS Schedule'!$H$27,0,MIN(1,NETWORKDAYS('WBS Schedule'!$H$27,$C$23,Holidays)/'WBS Schedule'!$G$27))*'WBS Schedule'!$P$27 -> 1.92 | U87: =IF($C$24<'WBS Schedule'!$H$27,0,MIN(1,NETWORKDAYS('WBS Schedule'!$H$27,$C$24,Holidays)/'WBS Schedule'!$G$27))*'WBS Schedule'!$P$27 -> 1.92 | V87: =IF($C$25<'WBS Schedule'!$H$27,0,MIN(1,NETWORKDAYS('WBS Schedule'!$H$27,$C$25,Holidays)/'WBS Schedule'!$G$27))*'WBS Schedule'!$P$27 -> 1.92
A88: ='WBS Schedule'!A28 -> 2.8 | B88: =IF($C$5<'WBS Schedule'!$H$28,0,MIN(1,NETWORKDAYS('WBS Schedule'!$H$28,$C$5,Holidays)/'WBS Schedule'!$G$28))*'WBS Schedule'!$P$28 -> 0 | C88: =IF($C$6<'WBS Schedule'!$H$28,0,MIN(1,NETWORKDAYS('WBS Schedule'!$H$28,$C$6,Holidays)/'WBS Schedule'!$G$28))*'WBS Schedule'!$P$28 -> 0 | D88: =IF($C$7<'WBS Schedule'!$H$28,0,MIN(1,NETWORKDAYS('WBS Schedule'!$H$28,$C$7,Holidays)/'WBS Schedule'!$G$28))*'WBS Schedule'!$P$28 -> 0 | E88: =IF($C$8<'WBS Schedule'!$H$28,0,MIN(1,NETWORKDAYS('WBS Schedule'!$H$28,$C$8,Holidays)/'WBS Schedule'!$G$28))*'WBS Schedule'!$P$28 -> 0 | F88: =IF($C$9<'WBS Schedule'!$H$28,0,MIN(1,NETWORKDAYS('WBS Schedule'!$H$28,$C$9,Holidays)/'WBS Schedule'!$G$28))*'WBS Schedule'!$P$28 -> 0 | G88: =IF($C$10<'WBS Schedule'!$H$28,0,MIN(1,NETWORKDAYS('WBS Schedule'!$H$28,$C$10,Holidays)/'WBS Schedule'!$G$28))*'WBS Schedule'!$P$28 -> 0 | H88: =IF($C$11<'WBS Schedule'!$H$28,0,MIN(1,NETWORKDAYS('WBS Schedule'!$H$28,$C$11,Holidays)/'WBS Schedule'!$G$28))*'WBS Schedule'!$P$28 -> 0 | I88: =IF($C$12<'WBS Schedule'!$H$28,0,MIN(1,NETWORKDAYS('WBS Schedule'!$H$28,$C$12,Holidays)/'WBS Schedule'!$G$28))*'WBS Schedule'!$P$28 -> 1.92 | J88: =IF($C$13<'WBS Schedule'!$H$28,0,MIN(1,NETWORKDAYS('WBS Schedule'!$H$28,$C$13,Holidays)/'WBS Schedule'!$G$28))*'WBS Schedule'!$P$28 -> 1.92 | K88: =IF($C$14<'WBS Schedule'!$H$28,0,MIN(1,NETWORKDAYS('WBS Schedule'!$H$28,$C$14,Holidays)/'WBS Schedule'!$G$28))*'WBS Schedule'!$P$28 -> 1.92 | L88: =IF($C$15<'WBS Schedule'!$H$28,0,MIN(1,NETWORKDAYS('WBS Schedule'!$H$28,$C$15,Holidays)/'WBS Schedule'!$G$28))*'WBS Schedule'!$P$28 -> 1.92 | M88: =IF($C$16<'WBS Schedule'!$H$28,0,MIN(1,NETWORKDAYS('WBS Schedule'!$H$28,$C$16,Holidays)/'WBS Schedule'!$G$28))*'WBS Schedule'!$P$28 -> 1.92 | N88: =IF($C$17<'WBS Schedule'!$H$28,0,MIN(1,NETWORKDAYS('WBS Schedule'!$H$28,$C$17,Holidays)/'WBS Schedule'!$G$28))*'WBS Schedule'!$P$28 -> 1.92 | O88: =IF($C$18<'WBS Schedule'!$H$28,0,MIN(1,NETWORKDAYS('WBS Schedule'!$H$28,$C$18,Holidays)/'WBS Schedule'!$G$28))*'WBS Schedule'!$P$28 -> 1.92 | P88: =IF($C$19<'WBS Schedule'!$H$28,0,MIN(1,NETWORKDAYS('WBS Schedule'!$H$28,$C$19,Holidays)/'WBS Schedule'!$G$28))*'WBS Schedule'!$P$28 -> 1.92 | Q88: =IF($C$20<'WBS Schedule'!$H$28,0,MIN(1,NETWORKDAYS('WBS Schedule'!$H$28,$C$20,Holidays)/'WBS Schedule'!$G$28))*'WBS Schedule'!$P$28 -> 1.92 | R88: =IF($C$21<'WBS Schedule'!$H$28,0,MIN(1,NETWORKDAYS('WBS Schedule'!$H$28,$C$21,Holidays)/'WBS Schedule'!$G$28))*'WBS Schedule'!$P$28 -> 1.92 | S88: =IF($C$22<'WBS Schedule'!$H$28,0,MIN(1,NETWORKDAYS('WBS Schedule'!$H$28,$C$22,Holidays)/'WBS Schedule'!$G$28))*'WBS Schedule'!$P$28 -> 1.92 | T88: =IF($C$23<'WBS Schedule'!$H$28,0,MIN(1,NETWORKDAYS('WBS Schedule'!$H$28,$C$23,Holidays)/'WBS Schedule'!$G$28))*'WBS Schedule'!$P$28 -> 1.92 | U88: =IF($C$24<'WBS Schedule'!$H$28,0,MIN(1,NETWORKDAYS('WBS Schedule'!$H$28,$C$24,Holidays)/'WBS Schedule'!$G$28))*'WBS Schedule'!$P$28 -> 1.92 | V88: =IF($C$25<'WBS Schedule'!$H$28,0,MIN(1,NETWORKDAYS('WBS Schedule'!$H$28,$C$25,Holidays)/'WBS Schedule'!$G$28))*'WBS Schedule'!$P$28 -> 1.92
A89: ='WBS Schedule'!A29 -> 2.9 | B89: =IF($C$5<'WBS Schedule'!$H$29,0,MIN(1,NETWORKDAYS('WBS Schedule'!$H$29,$C$5,Holidays)/'WBS Schedule'!$G$29))*'WBS Schedule'!$P$29 -> 0 | C89: =IF($C$6<'WBS Schedule'!$H$29,0,MIN(1,NETWORKDAYS('WBS Schedule'!$H$29,$C$6,Holidays)/'WBS Schedule'!$G$29))*'WBS Schedule'!$P$29 -> 0 | D89: =IF($C$7<'WBS Schedule'!$H$29,0,MIN(1,NETWORKDAYS('WBS Schedule'!$H$29,$C$7,Holidays)/'WBS Schedule'!$G$29))*'WBS Schedule'!$P$29 -> 0 | E89: =IF($C$8<'WBS Schedule'!$H$29,0,MIN(1,NETWORKDAYS('WBS Schedule'!$H$29,$C$8,Holidays)/'WBS Schedule'!$G$29))*'WBS Schedule'!$P$29 -> 0 | F89: =IF($C$9<'WBS Schedule'!$H$29,0,MIN(1,NETWORKDAYS('WBS Schedule'!$H$29,$C$9,Holidays)/'WBS Schedule'!$G$29))*'WBS Schedule'!$P$29 -> 0 | G89: =IF($C$10<'WBS Schedule'!$H$29,0,MIN(1,NETWORKDAYS('WBS Schedule'!$H$29,$C$10,Holidays)/'WBS Schedule'!$G$29))*'WBS Schedule'!$P$29 -> 1.28 | H89: =IF($C$11<'WBS Schedule'!$H$29,0,MIN(1,NETWORKDAYS('WBS Schedule'!$H$29,$C$11,Holidays)/'WBS Schedule'!$G$29))*'WBS Schedule'!$P$29 -> 2.56 | I89: =IF($C$12<'WBS Schedule'!$H$29,0,MIN(1,NETWORKDAYS('WBS Schedule'!$H$29,$C$12,Holidays)/'WBS Schedule'!$G$29))*'WBS Schedule'!$P$29 -> 2.56 | J89: =IF($C$13<'WBS Schedule'!$H$29,0,MIN(1,NETWORKDAYS('WBS Schedule'!$H$29,$C$13,Holidays)/'WBS Schedule'!$G$29))*'WBS Schedule'!$P$29 -> 2.56 | K89: =IF($C$14<'WBS Schedule'!$H$29,0,MIN(1,NETWORKDAYS('WBS Schedule'!$H$29,$C$14,Holidays)/'WBS Schedule'!$G$29))*'WBS Schedule'!$P$29 -> 2.56 | L89: =IF($C$15<'WBS Schedule'!$H$29,0,MIN(1,NETWORKDAYS('WBS Schedule'!$H$29,$C$15,Holidays)/'WBS Schedule'!$G$29))*'WBS Schedule'!$P$29 -> 2.56 | M89: =IF($C$16<'WBS Schedule'!$H$29,0,MIN(1,NETWORKDAYS('WBS Schedule'!$H$29,$C$16,Holidays)/'WBS Schedule'!$G$29))*'WBS Schedule'!$P$29 -> 2.56 | N89: =IF($C$17<'WBS Schedule'!$H$29,0,MIN(1,NETWORKDAYS('WBS Schedule'!$H$29,$C$17,Holidays)/'WBS Schedule'!$G$29))*'WBS Schedule'!$P$29 -> 2.56 | O89: =IF($C$18<'WBS Schedule'!$H$29,0,MIN(1,NETWORKDAYS('WBS Schedule'!$H$29,$C$18,Holidays)/'WBS Schedule'!$G$29))*'WBS Schedule'!$P$29 -> 2.56 | P89: =IF($C$19<'WBS Schedule'!$H$29,0,MIN(1,NETWORKDAYS('WBS Schedule'!$H$29,$C$19,Holidays)/'WBS Schedule'!$G$29))*'WBS Schedule'!$P$29 -> 2.56 | Q89: =IF($C$20<'WBS Schedule'!$H$29,0,MIN(1,NETWORKDAYS('WBS Schedule'!$H$29,$C$20,Holidays)/'WBS Schedule'!$G$29))*'WBS Schedule'!$P$29 -> 2.56 | R89: =IF($C$21<'WBS Schedule'!$H$29,0,MIN(1,NETWORKDAYS('WBS Schedule'!$H$29,$C$21,Holidays)/'WBS Schedule'!$G$29))*'WBS Schedule'!$P$29 -> 2.56 | S89: =IF($C$22<'WBS Schedule'!$H$29,0,MIN(1,NETWORKDAYS('WBS Schedule'!$H$29,$C$22,Holidays)/'WBS Schedule'!$G$29))*'WBS Schedule'!$P$29 -> 2.56 | T89: =IF($C$23<'WBS Schedule'!$H$29,0,MIN(1,NETWORKDAYS('WBS Schedule'!$H$29,$C$23,Holidays)/'WBS Schedule'!$G$29))*'WBS Schedule'!$P$29 -> 2.56 | U89: =IF($C$24<'WBS Schedule'!$H$29,0,MIN(1,NETWORKDAYS('WBS Schedule'!$H$29,$C$24,Holidays)/'WBS Schedule'!$G$29))*'WBS Schedule'!$P$29 -> 2.56 | V89: =IF($C$25<'WBS Schedule'!$H$29,0,MIN(1,NETWORKDAYS('WBS Schedule'!$H$29,$C$25,Holidays)/'WBS Schedule'!$G$29))*'WBS Schedule'!$P$29 -> 2.56
